Workbook

Sheet Master_Site
A1: id13 | B1: slug | C1: titre_norm | D1: sous_titre_norm | E1: credit_ligne | F1: auteurs | G1: direction | H1: traduction | I1: compilation | J1: editeur | K1: Marque | L1: collection | M1: Nombre séquentiel | N1: date_parution_norm | O1: Numéro d'édition | P1: format_site | Q1: Code support | R1: Product form detail | S1: Description courte | T1: Description longue | U1: Table des matières | V1: URL image de couverture | W1: cover_file | X1: Nombre de pages (pages totales imprimées) | Y1: Largeur | Z1: Hauteur | AA1: Epaisseur | AB1: Poids | AC1: Sujet BISAC principal | AD1: Sujet CLIL principal | AE1: Sujet THEMA principal | AF1: Code public visé ONIX | AG1: GCOI | AH1: Code interne | AI1: active_site | AJ1: active_onix | AK1: price | AL1: availability | AM1: contributeurs_onix | AN1: auteurs_onix | AO1: direction_onix | AP1: traduction_onix | AQ1: compilation_onix | AR1: openedition_url | AS1: EAN13 (texte) | AT1: Disponibilité (code ONIX) | AU1: Statut publication (code ONIX) | AV1: BIC_BIC code sujet | AW1: BIC_Qualificatif géographique BIC | AX1: BIC_Qualificatif de langue BIC (langue comme sujet) | AY1: BIC_Qualificatif de période historique BIC | AZ1: BIC_Qualificatif de niveau scolaire BIC | BA1: BIC_Qualificatif BIC du niveau de lecture et de l’intérêt particulier | BB1: Apple conseil parental | BC1: Code Evaluation ONIX du public adulte | BD1: THEMA_Classification (raw) | BE1: THEMA_Codes (liste ;) | BF1: THEMA_Principal | BG1: THEMA_Secondaires | BH1: THEMA_Qualif_lieu | BI1: THEMA_Qualif_langue | BJ1: THEMA_Qualif_période | BK1: THEMA_Qualif_niveau_scolaire | BL1: THEMA_Qualif_niveau_lecture | BM1: THEMA_Qualif_style | BN1: THEMA_Code support | BO1: THEMA_Code détail présentation
A2: 9791024019826 | C2: Penser l'éducation, n° 58 | E2: Auteurs diverts | F2: Auteurs divers | J2: Presses universitaires de Rouen et du Havre | L2: Penser l'éducation | M2: 58 | N2: 46317 | O2: 1 | P2: Livre broché | Q2: BC | S2: La revue Penser l'éducation s’inscrit dans le champ spécifique qui croise la philosophie de l’éducation et l’histoire des idées pédagogiques. | T2: La revue Penser l'éducation s’inscrit dans le champ spécifique qui croise la philosophie de l’éducation et l’histoire des idées pédagogiques. Ces deux aspects sont reliés et relèvent de la philosophie de l’éducation. Penser l’éducation n’est pas un titre anodin, il porte une injonction et une promesse : en ces temps de mutation, il s’agit de (re)penser, à nouveaux frais, l’éducation, dans ses principes, ses finalités, ses valeurs, ses pratiques et leurs conséquences. Le numéro 58 explore des sujets tels que le système éducatif guyanais ; les transformations du corps des CPE par le concours ; la régulation des désordres à l'école ; la philosophie de Bernard Stiegler face à la cris de l'éducation ; la communauté de recherche philosophique et orientante et enfin la rencontre des épistémologies du Nord et du Sud. En fin d'opus : une recension, les rubriques « Les fonds du MUNAÉ » et « Penser l’éducation ailleurs ». | U2: <p>François Lechby - Prise en compte des cultures corporelles des sociétés businenge : une intégration dans le système éducatif guyanais ?<br/> Sofia Hachemi - Le concours, un analyseur des transformations du corps des conseillers principaux d’éducation<br/> Gwénaël Lefeuvre, Rémi Bonasio et Bruno Fondeville - Régulation des désordres à l’école : enjeux d’enseignement-apprentissage<br/> Romain Mollard - La philosophie de l’éducation de Bernard Stiegler et la crise de l’éducation à l’ère des technologies numériques : une introduction<br/> Charlie Renard et Elodie Chaumont - La communauté de recherche philosophique et orientante : proposition éducative pour s’orienter au défi de l’inanticipable<br/> Adriana-Renée Tobos et Marie Stoecklin Burr - Rencontre entre les épistémologies du Nord et du Sud : pour une nouvelle écriture de la vie<br/> Recension par Henri Louis Go: Riondet, X. (2025). À l’école althussérienne. Aperçus d’une (non) philosophie de l’éducation. Le Bord de l’Eau, 240 p.<br/> « Les fonds du MUNAÉ », par Kristell Gilbert, documentaliste au Musée national de l’Éducation: Dessins d’enfants (1936-1941) : du Munaé à l’UNESCO<br/> | W2: 9791024019826.jpg | X2: 240 | Y2: 15.5 | Z2: 23 | AA2: 1.5 | AB2: 350
A3: 9791024019796 | C3: Saintuaires | D3: Reliques et reliquaires dans les textes français des XIe-XVIe siècles | E3: Albert, Sophie, B15;Heckmann, Hubert, B15 | F3: Sophie Albert; Hubert Heckman | J3: Presses universitaires de Rouen et du Havre | N3: 46345 | O3: 1 | P3: Livre broché | Q3: BC | S3: Tout en s’appuyant sur les travaux des historien·nes, le volume inscrit l’étude des reliques dans une perspective transdisciplinaire | T3: Tout en s’appuyant sur les travaux des historien·nes, le volume inscrit l’étude des reliques dans une perspective transdisciplinaire : il rassemble les réflexions de chercheurs en histoire, en histoire de l’art et en littérature. Il embrasse un champ chronologique allant du XIe au XVIe siècle, et une pluralité de genres et de registres : textes hagiographiques, mais aussi épiques, romanesques, dramatiques, comiques, lyriques et courtois. Cette ouverture disciplinaire, chronologique et générique, de même que le croisement des méthodes et des points de vue, éclairent la manière dont les corpus français médiévaux pensent, disent et donnent à voir les reliques, réelles ou métaphoriques. | U3: <p>Introduction par Hubert Heckmann<br/> Des fictions apocryphes à l’aventure chevaleresque<br/> Jean-Marie Sansterre, Véronique et son image-relique du Christ dans quelques textes français de la fin du XIIe au début du XIVe siècle<br/> Beate Langenbruch, Reliques et saints de Rhénanie dans la construction d’un récit épique français : le témoignage de Renaut de Montauban<br/> Catherine Nicolas, La sainte chapelle du Graal : imaginaire du morceau et translation des reliques dans le Haut Livre du Graal<br/> De dames, de saintes et de vierges<br/> Françoise Laurent, Traduire la Vie de sainte Léocade : les Miracles de Nostre Dame de Gautier de Coinci et le livre reliquaire<br/> Gérard Gros, Une relique, en somme efficace : le saint soulier de la Vierge Soissons (Gautier de Coinci, Miracles de Nostre Dame, IV, Item dou soller)<br/> Denis Hüe, Marie sacraire, le reliquaire vide<br/> Adriane Boussac, Il n’avoit de remanant de s’amie que le seul gant. Le gant, relique d’amour dans le Cléomadès d’Adenet le roi<br/> Laëtitia Tabard, Les reliques des martyrs d’amour dans quelques dits et poèmes allégoriques du XVe siècle<br/> Reliques en scènes, reliques en jeu<br/> Thierry Revol, La dramaturgie des reliques dans les entrées royales au XVe siècle<br/> Jean-Pierre Bordier, Dévotion et dérision : deux usages des reliques au théâtre<br/> Véronique Dominguez, Rappeler la Passion : l’opsis et la couronne d’épines (XIIIe-XVIe siècles)<br/> Fabienne Pomel, La relique burlesque ou le jeu avec le signe : métonymie, métaphores et substitutions facétieuses<br/> Coda<br/> François Lecercle, La littérature de l’image-relique dans la Contre-Réforme<br/> Conclusion par Sophie Albert : La relique : traversée</p> | W3: 9791024019796.jpg | X3: 350 | Y3: 15.5 | Z3: 23 | AA3: 2 | AB3: 450
A4: 9791024019673 | C4: Les revues au cœur des échanges culturels entre l'Autriche et la France | D4: XIXe-XXIe siècle | E4: Lacheny, Marc, B15;Aurélie, Le Née, B15 | F4: Marc Lacheny; Aurélie Le Née | J4: Presses universitaires de Rouen et du Havre | L4: France-Autriche | N4: 46317 | O4: 1 | P4: Livre broché | Q4: BC | S4: Les revues, par leur périodicité, la diversité de leur contenu et de leurs contributeurs, mais aussi par leurs moyens de diffusion apparaissent comme des opérateurs de premier plan des échanges interculturels. | T4: Les revues, par leur périodicité, la diversité de leur contenu et de leurs contributeurs, mais aussi par leurs moyens de diffusion apparaissent comme des opérateurs de premier plan des échanges interculturels. Le présent ouvrage propose de se pencher sur leur rôle dans les interactions entre l’Autriche et la France du XIXe au XXIe siècle. Il permet d’appréhender l’image de l’autre pays véhiculée par des revues artistiques, sociopolitiques ou académiques. Composé de contributions de spécialistes de l’Autriche et du dialogue interculturel entre l’Autriche et la France, l’ouvrage met en évidence la diversité des revues et des échanges entre les deux pays, et ce faisant, dessine les contours d’une histoire culturelle européenne. | U4: <p>Introduction, Marc Lacheny et Aurélie Le Née<br/> Première partie : Regards socioculturels des revues autrichiennes sur la France au XIXe siècle<br/> Image de la France et (non-)transfert d’idées dans la revue <i>Carinthia</i> (1811-1848/1849), Ute Weinmann<br/> Le vaudeville et la presse autrichienne de la premiere moitié du XIXe siècle, Maria Piok<br/> La France vue par l’<i>Österreichische Lehrerinnen Zeitung</i> (1893-1901) : une relecture engagée de la modernité, Sylvie Arlaud<br/> Deuxième partie : Les revues d’art et de musique de la seconde moitié du XIXe siècle à la première moitié du XXe siècle<br/> La Sécession viennoise dans les revues artistiques françaises (1897-1937), Irène Cagneau<br/> L’Autriche a la découverte de la musique française, Jean-François Candoni<br/> Paris-Vienne ou l’axe des avant-gardes ?, Sophie Picard<br/> Troisième partie : De la France à l’Autriche, de l’Autriche à la France : la revue <i>Austriaca</i>, de 1975 à nos jours<br/> La revue <i>Austriaca</i>, agent des transferts culturels entre la France et l’Autriche, Jacques Lajarrige<br/> Les auteur·e·</p> | W4: 9791024019673.jpg | X4: 198 | Y4: 15.5 | Z4: 23 | AA4: 1.9 | AB4: 300 | AI4: TRUE | AJ4: TRUE | AK4: 13 | AL4: À paraître | AM4: Lacheny, Marc; Aurélie, Le Née, B15 | AS4: 9791024019673 | AT4: 20 | AU4: 2
A5: 9791024019765 | C5: Les Oraisons funèbres de Bossuet | D5: Ou le ravissement de la mort | E5: Lyraud, Pierre | F5: Pierre Lyraud | J5: Presses universitaires de Rouen et du Havre | L5: Cours | N5: 46345 | O5: 1 | P5: Livre broché | Q5: BC | S5: <i>Les oraisons funèbres</i> de Bossuet, oscillant entre déploration et consolation, grandeur et néant, ne correspondent pas à l’image pétrifiante qu’en donne notre histoire littéraire. | T5: <i>Les oraisons funèbres</i> de Bossuet, oscillant entre déploration et consolation, grandeur et néant, ne correspondent pas à l’image pétrifiante qu’en donne notre histoire littéraire. Réinscrivant ces discours dans leur tradition rhétorique et mettant au jour les tensions qui les traversent, cet essai réinscrit ces discours dans leur tradition rhétorique, met au jour leurs tensions, et montre que la mémoire de la perte est convertie en ressource pour l’avenir de la communauté endeuillée. | W5: 9791024019765.jpg | X5: 200 | Y5: 15.5 | Z5: 23 | AA5: 1.8 | AB5: 300 | AF5: 6 | AI5: TRUE | AJ5: TRUE | AK5: 13 | AL5: À paraître | AM5: Lyraud, Pierre | AS5: 9791024019765 | AT5: 20 | AU5: 2
A6: 9791024019734 | C6: Faire du jour la nuit | D6: Lorenzaccio ou les ombres du pouvoir | E6: Mentzel, Sophie | F6: Sophie Mentzel | J6: Presses universitaires de Rouen et du Havre | L6: Cours | N6: 46345 | O6: 1 | P6: Livre broché | Q6: BC | S6: Pièce conçue pour la lecture mais dotée d’une puissance scénique manifeste, "Lorenzaccio" de Musset est une œuvre du paradoxe et du renversement : le vice y masque la vertu, le pouvoir s'y révèle déprédation, et les espaces comme les consciences s’y défont sous le poids de la corruption et de l'inertie. | T6: Pièce conçue pour la lecture mais dotée d’une puissance scénique manifeste, "Lorenzaccio" de Musset est une œuvre du paradoxe et du renversement : le vice y masque la vertu, le pouvoir s'y révèle déprédation, et les espaces comme les consciences s’y défont sous le poids de la corruption et de l'inertie. Cet ouvrage analyse le clair-obscur qui structure la pièce, de la sombre ruelle au palais ducal. Il montre comment l'espace florentin fonctionne à la fois comme révélateur des âmes et tombeau des illusions, et comment, dans cette cité où lieux du pouvoir et lieux de débauche se confondent, le drame consigne l’échec du politique. Écho au pessimisme des premières années de la monarchie de Juillet, il révèle ainsi la modernité désespérée de Musset. | W6: 9791024019734.jpg | X6: 200 | Y6: 15.5 | Z6: 23 | AA6: 1.8 | AB6: 300 | AF6: 6 | AI6: TRUE | AJ6: TRUE | AK6: 13 | AL6: À paraître | AM6: Mentzel, Sophie | AS6: 9791024019734 | AT6: 20 | AU6: 2
A7: 9791024015880 | B7: manuel-d-entrainement-a-l-apnee-9791024015880 | C7: Manuel d'entraînement à l'apnée | E7: Lemaître, Frédéric, B15 | F7: Frédéric Lemaître | J7: Presses universitaires de Rouen et du Havre | N7: 46752 | O7: 1 | P7: Livre broché | Q7: BC | V7: https://www.pun-ed.fr/resources/titles/28777100909220/images/0f6b1f657ac30ab76519ed4c677e9909/HIGHQ/9791024015880.jpg | W7: 9791024015880.jpg | AG7: 28777100909220 | AI7: TRUE | AJ7: TRUE | AK7: 29 | AL7: À paraître | AM7: Lemaître, Frédéric, B15 | AS7: 9791024015880 | AT7: 20 | AU7: 4 | AV7: W;WSSC | BB7: 0 | BD7: SPC | BE7: SPC | BF7: SPC | BN7: BC
A8: 9791024018966 | B8: histoire-de-rouen-vol-2-9791024018966 | C8: Histoire de Rouen, vol. 2 | D8: De 1815 à nos jours | E8: Marec, Yannick, B15 | F8: Yannick Marec | J8: Presses universitaires de Rouen et du Havre | N8: 46289 | O8: 1 | P8: Livre broché | Q8: BC | S8: Ce second volume de l'Histoire de Rouen couvre la période 1815 à nos jours. Ouvrage collectif illustré, rédigé par près d’une quinzaine d’auteurs, il aborde les différents aspects, économiques, sociaux, politiques, patrimoniaux et culturels d’une grande cité, siège de la Métropole Rouen-Normandie. | T8: <p>Durant la période contemporaine, la ville de Rouen a pu apparaître, comme une des toutes premières cités de l'espace hexagonal, en particulier avec son complexe industriel et portuaire. Certains Rouennais ont aussi acquis un rayonnement international comme le grand écrivain Gustave Flaubert, ou encore le prix Nobel de médecine, Charles Nicolle.</p> <p>Rouen se caractérise aussi par la richesse de son patrimoine et la diversité des initiatives culturelles locales. En même temps, le développement urbain doit prendre en compte de nouvelles aspirations, notamment écologiques, les effets délétères d’une industrialisation rapprochée, ayant été, à plusieurs reprises, durement ressentis.</p> | U8: <p>Prologue</p> <p><strong>Chapitre 1.</strong><strong> Rouen entre Monarchie, Empire et République (1815-1870), par Yannick Marec</strong></p> <p>Stéphane Rioland, Jules Adeline et<em> Rouen tel qu'il aurait pu être. Proposition d'un présent possible</em>&nbsp;</p> <p>Karl Feltgen, Le Choléra de 1832</p> <p>Yannick Marec, 1830 et 1848 dans l'imaginaire social et politique rouennais&nbsp;: significations et prolongements</p> <p>Bénédicte Percheron, L'enclos Sainte-Marie&nbsp;: Naissance d’un sanctuaire des sciences</p> <p><strong>Chapitre 2. </strong><strong>Rouen, entre République modérée et République sociale&nbsp;? (1870-1914), par </strong><strong>Yannick Marec</strong></p> <p>Joëlle Robert, Le monument Louis Bouilhet &nbsp;&nbsp;&nbsp;&nbsp;</p> <p>Stéphane Rioland, Jules Adeline habitant et illustrateur des villes&nbsp;</p> <p>Bénédicte Percheron, Un enclos pour une République des Sciences</p> <p>Karl Feltgen, La grippe russe de 1889 &nbsp;</p> <p><strong>Chapitre 3.</strong><strong> Art, Culture et patrimoine au XIX<sup>e</sup> siècle, par </strong><strong>Claire Maingon</strong> &nbsp;</p> <p>Joëlle Robert, Flaubert et Rouen</p> <p>Yvan Leclerc, Louis Bouilhet&nbsp;: Rouen Paris et retour</p> <p><strong>Chapitre 4. </strong><strong>La guerre comme horizon&nbsp;? (1914-1940). Rouen entre renouveau et stagnation, par </strong><strong>Yannick Marec</strong></p> <p>Karl Feltgen, La grippe espagnole de 1918</p> <p>Michel Croguennec, Le renouveau du port de Rouen</p> <p>Réjane Silighini, Le culte rouennais de Jeanne d’Arc et les fêtes du Ve centenaire en 1931</p> <p>Loïc Vadelorge, La vie culturelle à Rouen dans l’entre-deux guerres</p> <p><strong>Chapitre 5.</strong><strong> Souffrances, destructions et reconstruction (1940-1958), par Jean-Marie Cipolat-Gotet</strong>&nbsp;</p> <p>Cécile Anne-Sibout, Pierre René Wolf, patron de presse régionale (1945-1972)</p> <p>J-M Cipolat-Gotet, Les années 1950-1960&nbsp;: redéploiement industriel et perte d’autonomie&nbsp;</p> <p><strong>Chapitre 6. </strong><strong>Expansion et modernisation (1958-1968), par </strong><strong>Jean-Marie Cipolat-Gotet</strong> &nbsp;&nbsp;&nbsp;&nbsp;</p> <p>Michel Croguennec, La renaissance du port&nbsp;: le port et la nouvelle industrialisation jusqu’à Haropa</p> <p><strong>Chapitre 7.</strong> <strong>Rouen et sa périphérie, au temps de Jean Lecanuet (1968-1993), par </strong><strong>Cécile Anne-Sibout</strong></p> <p>La désindustrialisation</p> <p>Loïc Vadelorge, Rouen ville universitaire</p> <p><strong>Chapitre 8. </strong><strong>Rouen à la charnière du XX<sup>e</sup> et du XXI<sup>e</sup> siècle. Essai d’histoire du temps présent, par </strong><strong>Loïc Vadelorge</strong></p> <p>Réjane Silighini, L’Historial Jeanne d’Arc</p> <p>Michel Croguennec et Loïc Vadelorge, Lubrizol ou la quadrature du cercle de l’aménagement métropolitain</p> <p>Michel Croguennec, La raffinerie de pétrole de Petit-Couronne</p> <p>Françoise Lucchini, Les pratiques culturelles de la Métropole Rouen Normandie&nbsp;</p> <p><strong>Chapitre 9. </strong><strong>L’agglomération rouennaise depuis les années 1990, par </strong><strong>Arnaud Brennetot</strong></p> <p>Michel Croguennec, Le port, de la patrimonialisation à la reconversion de l’emprise foncière</p> <p>&nbsp;</p> <p>Epilogue par Yannick Marec</p> <p>Postface par Michel Bussi</p> <p>Bibliographie</p> | V8: https://www.pun-ed.fr/resources/titles/28777100057900/images/2bd388f731f26312bfc0fe30da009595/HIGHQ/9791024018966.jpg | W8: 9791024018966.jpg | X8: 460 | Y8: 18 | Z8: 24 | AB8: 1000 | AC8: HIS013000 | AD8: 3394 | AF8: 6 | AG8: 28777100057900 | AH8: 9791024018966 | AI8: TRUE | AJ8: TRUE | AK8: 35 | AL8: À paraître | AM8: Marec, Yannick, B15 | AS8: 9791024018966 | AT8: 20 | AU8: 2 | AV8: HBJ | BB8: 0 | BN8: BC
A9: 9791024019291 | B9: introduction-a-la-theorie-de-l-information-9791024019291 | C9: Introduction à la théorie de l'information | D9: Travaux pratiques en python | E9: Omar Khadir | F9: Omar Khadir | J9: Presses universitaires de Rouen et du Havre | L9: Cours | N9: 46289 | O9: 1 | P9: Livre broché | Q9: BC | S9: Ce livre est un cours sur la théorie de l'information destiné aux étudiants en licence de mathématiques, d’informatique ou d’électronique et à ceux des grandes écoles. C’est un support pédagogique pour des enseignements adaptés à ces niveaux. Il contient plus de cent trente exercices corrigés et des travaux pratiques traités par le logiciel Python. | T9: <p>La théorie de l'information intervient dans plusieurs disciplines telles que les réseaux de communication, la robotique, l'intelligence artificielle, le e-commerce ou la cybersécurité. Ce livre est un cours sur la théorie de l'information destiné aux étudiants en licence de mathématiques, d’informatique ou d’électronique et à ceux des grandes écoles. C'est un support de cours pour des enseignements correspondant à ces niveaux. Il contient plus de cent trente exercices corrigés et des travaux pratiques testés par le logiciel Python. Les sujets traités concernent le codage et la mesure de l'information, le codage des sources, les canaux discrets sans mémoire et les codes correcteurs d'erreurs.</p> | U9: <p>Préface</p> <p>Remerciements</p> <p><strong>1 Généralités sur le codage de l'information 1</strong></p> <p>1.1 Introduction</p> <p>1.2 Les codes historiques</p> <p>1.3 Source et codage de source</p> <p>1.4 Exercices</p> <p>1.5 Corrigé des exercices</p> <p>1.6 Travaux pratiques</p> <p>1.7 Corrigé des TP</p> <p><strong>2 Mesure de l'information</strong></p> <p>2.1 Introduction</p> <p>2.2 Espace probabilisé discret</p> <p>2.3 Entropie de Shannon d'une source</p> <p>2.4 Une définition de l'information mutuelle</p> <p>2.5 Exercices</p> <p>2.6 Corrigé des exercices</p> <p>2.7 Travaux pratiques</p> <p>2.8 Corrigé des TP</p> <p><strong>3 Codage des sources discrètes</strong></p> <p>3.1 Codes et Test de Sardinas et Patterson</p> <p>3.2 Les codes préfixes</p> <p>3.3 Premier théorème de Shannon</p> <p>3.4 Algorithme de compression LZ77</p> <p>3.5 Exercices</p> <p>3.6 Corrigé des exercices</p> <p>3.7 Travaux pratiques</p> <p>3.8 Corrigé des TP</p> <p><strong>4 Canaux discrets sans mémoire 146</strong></p> <p>4.1 Généralités</p> <p>4.2 Capacité d'un canal</p> <p>4.3 Capacité d'un canal symétrique</p> <p>4.4 Capacité d'un canal binaire à effacement</p> <p>4.5 Le second théorème de Shannon</p> <p>4.6 Exercices</p> <p>4.7 Corrigé des exercices</p> <p>4.8 Travaux pratiques</p> <p>4.9 Corrigé des TP</p> <p><strong>5 Les codes correcteurs d'erreurs</strong></p> <p>5.1 Introduction</p> <p>5.2 Le code de Hamming</p> <p>5.3 Le code de Viterbi</p> <p>5.4 Exercices</p> <p>5.5 Corrigé des exercices</p> <p>5.6 Travaux pratiques</p> <p>5.7 Corrigé des TP</p> <p>Table des figures</p> <p>Bibliographie</p> <p>Index</p> | W9: 9791024019291.jpg | X9: 230 | Y9: 15.5 | Z9: 23 | AB9: 400 | AC9: COM031000 | AD9: 3194 | AF9: 6 | AG9: 28777100421020 | AH9: 9791024019291 | AI9: TRUE | AJ9: TRUE | AK9: 18 | AL9: À paraître | AM9: Khadir, Omar, A01 | AN9: Omar Khadir | AS9: 9791024019291 | AT9: 10 | AU9: 2 | AV9: GPJ | BB9: 0 | BN9: BC
A10: 9791024019420 | B10: eduquer-et-former-depuis-la-pandemie-9791024019420 | C10: Éduquer et former depuis la pandémie | D10: Stabilité et changements | E10: Papi, Cathia, B15; Boéchat-Heer, Stéphanie, B15; Rinaudo, Jean-Luc, B15 | F10: Cathia Papi | J10: Presses universitaires de Rouen et du Havre | L10: Numérique en éducation | M10: 4 | N10: 46289 | O10: 1 | P10: Livre broché | Q10: BC | S10: En 2020, la COVID19 a brutalement eu pour effet la fermeture massive, au niveau mondial, des établissements d'enseignement et de formation, plongeant brutalement enseignants et apprenants dans une forme imposée d’enseignement-apprentissage à distance. Quatre ans après la fin des confinements, que reste-t-il de ces transformations brutales ? | T10: <p>Cet ouvrage résulte de la réflexion de chercheurs réunis lors d'un symposium du Réseau francophone en éducation et formation (REF), à Fribourg en juillet 2024. Mais plus qu’une conclusion, il se veut une ouverture vers des pratiques des acteurs et des institutions qui bénéficient de l’expérience acquise lors des périodes de confinement.</p> <p>À mesure que nous avançons dans un contexte postpandémique, il est en effet crucial de continuer à réfléchir aux pratiques d’enseignement et d’apprentissage, en cherchant à pérenniser les innovations qui ont émergé, en les adaptant aux différents contextes. Les résultats présentés dans cet ouvrage ouvrent des pistes pour une réflexion plus approfondie sur la formation à distance, l’hybridation des pratiques et l’engagement des apprenants, en montrant l'importance d'une approche réfléchie et adaptable face aux défis éducatifs. Ils appellent à une mobilisation collective pour intégrer de manière durable les leçons tirées de la pandémie, afin de bâtir un avenir éducatif inclusif et innovant.</p> | U10: <p><em>Préface</em><br /> Les leçons de la crise</p> <p>À marée basse</p> <p>De quelques changements de l'activité enseignante depuis le passage par la formation à distance</p> <p>De la continuité pédagogique à la transformation des pratiques pédagogiques en enseignement supérieur. Retour sur l'intégration des outils numériques dans les dispositifs innovants pendant et après la pandémie</p> <p>Interroger la pandémie en tant que levier pour le développement de l'hybridation dans les formations</p> <p>L’accompagnement des enseignants face à l’équipement massif des élèves par la collectivité au lendemain de la pandémie. Le cas du Pack Numérique Lycéen dans les lycées professionnels normands</p> <p>Nature de la motivation et Open Badges dans un contexte de postpandémie</p> <p>L’ingénierie pédagogique dans les entités publiques du Québec en période postpandémique</p> <p>Présence du numérique en éducation durant la pandémie&nbsp;: perceptions de parents et d’enseignants canadiens de tous les niveaux scolaires</p> <p>L’évolution du sentiment de compétences numériques et des stratégies d’ajustement des étudiant·e·s avant et après la pandémie</p> <p>Vécu de cours de danse comodaux&nbsp;: l’expérience de professeures et d’apprenantes en contexte de loisir québécois</p> <p>Accords perdus</p> <p>La présence à distance. Une analyse didactique clinique du temps didactique</p> <p><em>Conclusion</em><br /> Quel est l’impact à court et long terme des pratiques innovantes forcées ?</p> <p><em>Postface</em></p> <p><em>Bibliographie</em></p> <p><em>Les auteurs</em></p> | W10: 9791024019420.jpg | Y10: 15.5 | Z10: 23 | AB10: 400 | AC10: EDU000000;EDU026000;EDU029000;EDU059000;ET;TP;ET050;ET034;TP086 | AD10: 3080 | AF10: 5 | AG10: 28777100857700 | AI10: TRUE | AJ10: TRUE | AK10: 15 | AL10: À paraître | AM10: Papi, Cathia, B15; Boéchat-Heer, Stéphanie, B15; Rinaudo, Jean-Luc, B15 | AS10: 9791024019420 | AT10: 10 | AU10: 2 | AV10: Y;YQ | BB10: 0 | BN10: BC
A11: 9791024019543 | B11: le-rire-colonial-9791024019543 | C11: Le rire colonial | D11: La presse satirique illustrée face à la colonisation (1830-1990) | E11: Sofiane Taouchichet | F11: Sofiane Taouchichet | J11: Presses universitaires de Rouen et du Havre | L11: Charivari | M11: 4 | N11: 46289 | O11: 1 | P11: Livre broché | Q11: BC | S11: Histoire des représentations satiriques de la colonisation, entre 1829 et 1990. L'ouvrage est structuré en cinq parties : Histoire de la presse satirique ; La presse satirique illustrée face à l’histoire coloniale ; La stéréotypie coloniale ; Le miroir colonial ; Mécaniques et usages de la presse satirique. | T11: <p>Entre 1829 et 1990, la presse satirique illustrée française accompagne la formation et le chute du second empire colonial. Entre exaltation des conquêtes et dénonciation des violences, elle livre un regard ambivalent où la caricature révèle toutes les ambiguïtés de l'histoire coloniale et offre un miroir mouvant, drôle ou cruel, des sensibilités à l’égard de la colonisation. L’analyse, fondée sur un vaste corpus satirique, met en lumière stéréotypes, usages publics et héritages visuels d’un pan méconnu de la culture impériale. Les images révèlent comment, au fil des pages et des rires, la satire participe à façonner le regard public et à inscrire, jusque dans les imaginaires, les ambiguïtés et les héritages de l’empire.</p> | U11: <p><strong>Préface</strong><br /> <em>Le repas des cannibales</em><br /> <br /> <strong>Introduction</strong></p> <p><strong>Chapitre I.&nbsp;Presse satirique illustrée, histoire et objet médiatique</strong></p> <p>Histoire de la presse satirique illustrée</p> <p>La presse satirique illustrée, un genre (populaire) comme un autre</p> <p><strong>Chapitre II. La presse satirique illustrée face à l</strong><strong><span dir="RTL">'</span></strong><strong>histoire coloniale </strong></p> <p>Le Temps des conquêtes</p> <p>D<span dir="RTL">'</span>une guerre à l<span dir="RTL">’</span>autre</p> <p>Effacement de l<span dir="RTL">’</span>empire</p> <p><strong>Chapitre III. La st</strong><strong>éréotypie satirique coloniale </strong></p> <p>Représenter l<span dir="RTL">’</span>espace des colonies, entre connaissances utiles et romanesque</p> <p>Figures génériques</p> <p>L<span dir="RTL">’</span>Arabe</p> <p>Le Noir</p> <p><strong>Chapitre IV. Le Miroir colonial, l</strong><strong><span dir="RTL">’</span></strong><strong>Autre et le Soi-même </strong></p> <p>Relations internationales : le partage du Monde</p> <p>Miroir politique</p> <p>Mission civilisatrice</p> <p>L<span dir="RTL">’</span>Autre, c<span dir="RTL">’</span>est moi</p> <p><strong>Chapitre V. Mécaniques et usages de la presse satirique </strong></p> <p>Faire rayonner la stéréotypie</p> <p>Caractéristiques de la presse satirique</p> <p>Usages de la presse satirique et pouvoir de la caricature coloniale</p> <p>Histoire de la presse satirique illustrée</p> <p>La presse satirique illustrée, un genre (populaire) comme un autre</p> <p><strong>Chapitre II. La presse satirique illustrée face à l</strong><strong><span dir="RTL">’</span></strong><strong>histoire coloniale </strong></p> <p>Le Temps des conquêtes</p> <p>D<span dir="RTL">’</span>une guerre à l<span dir="RTL">’</span>autre</p> <p>Effacement de l<span dir="RTL">’</span>empire</p> <p><strong>Chapitre III. La st</strong><strong>éréotypie satirique coloniale </strong></p> <p>Représenter l<span dir="RTL">’</span>espace des colonies, entre connaissances utiles et romanesque</p> <p>Figures génériques</p> <p>L<span dir="RTL">’</span>Arabe</p> <p>Le Noir</p> <p><strong>Chapitre IV. Le Miroir colonial, l</strong><strong><span dir="RTL">’</span></strong><strong>Autre et le Soi-même </strong></p> <p>Relations internationales : le partage du Monde</p> <p>Miroir politique</p> <p>Mission civilisatrice</p> <p>L<span dir="RTL">’</span>Autre, c<span dir="RTL">’</span>est moi</p> <p><strong>Chapitre V. Mécaniques et usages de la presse satirique </strong></p> <p>Faire rayonner la stéréotypie</p> <p>Caractéristiques de la presse satirique</p> <p>Usages de la presse satirique et pouvoir de la caricature coloniale</p> <p><strong>Conclusion<br /> Annexes<br /> Chronologie sélective<br /> Bibliographie</strong></p> | W11: 9791024019543.jpg | Y11: 19.5 | Z11: 25.5 | AC11: HIS000000;ART000000;ART037000;HIS010000;HIS054000;ET;TP;ET050;TP024 | AD11: 3377 | AF11: 5 | AG11: 28777100307100 | AI11: TRUE | AJ11: TRUE | AK11: 30 | AL11: À paraître | AM11: Taouchichet, Sofiane, A01 | AN11: Sofiane Taouchichet | AS11: 9791024019543 | AT11: 10 | AU11: 2 | AV11: A;AC | BB11: 0 | BN11: BC
A12: 9791024019604 | B12: une-allure-si-vagabonde-9791024019604 | C12: Une allure si vagabonde | D12: Mélanges en l'honneur de Jean-Claude Arnould | E12: Milhe Poutingon, Gérard, B15; Bonnier, Xavier, B15; Provini, Sandra, B15 | F12: Gérard Milhe Poutingon | J12: Presses universitaires de Rouen et du Havre | N12: 46289 | O12: 1 | P12: Livre broché | Q12: BC | S12: Spécialiste de la littérature du XVIe siècle et professeur émérite à l'université de Rouen Normandie, Jean-Claude Arnould a étudié les narrations brèves, Montaigne et Gournay, les paratextes ou la théorie de la traduction. Autant de thèmes abordés par ses collègues réunis dans ce livre hommage d’une variété fidèle à l’esprit de la Renaissance. | T12: <p>Spécialiste de la littérature française du XVI<sup>e</sup> siècle et professeur émérite à l'université de Rouen Normandie, Jean-Claude Arnould est l’auteur de nombreuses éditions critiques et de travaux sur la narration brève et les histoires tragiques, les œuvres de Montaigne et de Marie de Gournay, les paratextes dans les imprimés anciens ou encore la théorie de la traduction au XVI<sup>e</sup> siècle. Autant de thèmes abordés par ses collègues et amis, européens ou sud-américains, réunis dans ce livre hommage d’une variété fidèle à l’esprit de la Renaissance. Leurs études prolongent la réflexion menée par Jean-Claude Arnould sur la transmission et la traduction des œuvres du XVI<sup>e</sup> siècle, de part et d’autre de l’Atlantique.</p> | U12: <p><strong>Remerciements</strong><br /> <br /> Xavier Bonnier et Sandra Provini<br /> <strong>Avant-propos</strong></p> <p><em>Vie professionnelle et bibliographie de Jean-Claude Arnould</em><br /> &nbsp;</p> <p><strong>I<sup>re </sup>partie -&nbsp;&nbsp;Malheurs, valeurs et humeurs dans la littérature du XVI<sup>e</sup>&nbsp;siècle</strong></p> <p>Gérard Milhe Poutingon<br /> Le « triballement » du « tonneau diogenic » : une critique de la paresse au&nbsp;XVI<sup>e</sup>&nbsp;siècle</p> <p>Pascal Debailly<br /> L'indignation satirique et la restauration de la dignité chez Du Bellay</p> <p>José Alexandrino De Souza Filho<br /> La <em>sprezzatura</em>&nbsp;: concept littéraire, mode vestimentaire et attitude comportementale à la Renaissance&nbsp;</p> <p>Michèle Guéret-Laferté et Rafael Afonso Gonçalves<br /> Les manuscrits du <em>Livro</em> de Duarte Barbosa entre pratique médiévale et renouveau des horizons culturels à la Renaissance</p> <p>Witold Konstanty Pietrzak<br /> L’intertexte dans la <em>Continuation des histoires tragiques</em> de François de Belleforest</p> <p>Ariane Ferry<br /> Le puissant désir d’être auteur : de quelques mises en récit de l’histoire du prince Hamlet (John Updike, Saxo Grammaticus, François de Belleforest et Shakespeare)&nbsp;</p> <p>Marie-Claire Thomine et Romain Weber<br /> <em>Les Heures perdues</em> <em>de R. D. M. Cavalier François</em> (1615) et la tradition facétieuse</p> <p><strong>II<sup>e </sup>partie -&nbsp;Traduire, transmettre, commenter le XVI<sup>e</sup>&nbsp;siècle</strong></p> <p>Sebastian Garcia Barrera<br /> Un long XVI<sup>e</sup>&nbsp;siècle&nbsp;? Réflexions indisciplinées sur l’historiographie de la traduction&nbsp;</p> <p>Martha Lucía Pulido Correa<br /> Étienne Dolet, Jean-Claude Arnould et L’Universidad de Antioquia&nbsp;</p> <p>Myriam Dufour-Maître<br /> <em>La Princesse de Clèves</em> : une &nbsp;« chimère » ?</p> <p>Frank Greiner<br /> Francion ou la pensée libre</p> <p>Tony Gheeraert<br /> <em>Les Histoires ou contes du temps passé</em> de Charles Perrault. De la boutade à la méprise</p> <p>Yvan Leclerc<br /> Notes inédites de Flaubert sur Ronsard et Rabelais, extraites d’Étienne Pasquier, <em>Les Recherches de la France</em></p> <p>Stéphanie Champeau<br /> Une « histoire tragique&nbsp;» : <em>Une page d’histoire</em> de Barbey d’Aurevilly</p> <p>Valerio Cordiner<br /> Montaigne, Lafargue et la rentable fainéantise</p> <p><strong>II<sup>e </sup>partie -&nbsp;Saveurs d’ici, saveurs d’ailleurs&nbsp;: échappées littéraires et humanistes</strong></p> <p>Judith Le Blanc<br /> La fine appellation (d’origine contrôlée)&nbsp;: un(e) Arnould peut en cacher un(e) autre</p> <p>Joann Élart<br /> J’ai un canard sur le feu</p> <p>Hervé Baudry<br /> Des livres et du caviar. Éléments pour l’analyse de microcensure</p> <p>Georges Mathieu<br /> Éléments de physiologie du cul-de-lampe christophien</p> <p>Jean Maurice<br /> <em>Les Chardons du Baragan</em>&nbsp;: l’évasion hors du destin</p> <p>Ariane Eissen<br /> Écritures migrantes au féminin (Laura Alcoba, Agota Kristof, Maryam Madjidi, Shumona Sinha)</p> <p>Françoise Simonet-Tenant<br /> Port-Cros ou les vacances de <em>La NRF</em></p> <p><strong>Table des matières</strong></p> | W12: 9791024019604.jpg | Y12: 15.5 | Z12: 23 | AA12: 4 | AC12: LIT000000;LIT004130;LIT020000 | AD12: 3435 | AF12: 5 | AG12: 28777100348690 | AI12: TRUE | AJ12: TRUE | AK12: 30 | AL12: À paraître | AM12: Milhe Poutingon, Gérard, B15; Bonnier, Xavier, B15; Provini, Sandra, B15 | AS12: 9791024019604 | AT12: 10 | AU12: 2 | AV12: D;DS;DSB;DB | BB12: 0 | BN12: BC
A13: 9791024019468 | B13: la-sylloge-parisina-9791024019468 | C13: La Sylloge Parisina | D13: Édition et traduction | E13: Floridi, Lucia, B10 | F13: Lucia Floridi | J13: Presses universitaires de Rouen et du Havre | L13: Ario | M13: 1 | N13: 46289 | O13: 1 | P13: Livre broché | Q13: BC | S13: Ce travail propose la première édition critique moderne – après la princeps de Cramer (1841) – du recueil d'épigrammes grecques connu sous le nom de Sylloge Parisina, traduits en français et en italien, en double format papier et numérique. | T13: <p>Après l'edition <em>princeps</em> de John Anthony Cramer (1841), est proposée ici pour la première fois l'édition critique du recueil d'épigrammes grecques connu sous le nom de <em>Sylloge Parisina</em>, conservé dans un manuscrit du XII<sup>e</sup>-XIII<sup>e</sup> siècle et dans un apographe partiel datant de la moitié du XIV<sup>e</sup> siècle.</p> <p>L'introduction décrit les témoins, discute de la datation, de la structure et du contenu du recueil, réfléchit sur la transmission anthologique de l'épigramme grec et sur son histoire éditoriale. Les épigrammes sont accompagnées de traductions en italien et en français, afin d'être accessibles même aux non-spécialistes. Le format papier traditionnel est accompagné d'une édition numérique, qui permet d'expérimenter de nouvelles formes de visualisation du texte, rendant plus immédiatement perceptibles les différentes structures qu'il prend dans les différents témoins.</p> | U13: <p>Préambule général</p> <p>Introduction</p> <p>&nbsp;</p> <p><strong>I. Transmission anthologique et histoire éditoriale de l'épigramme grec</strong></p> <p><strong>II. La <em>Sylloge Parisina</em></strong></p> <p>Les témoins</p> <p>Relation entre SS et B</p> <p>Structure, contenu et datation du recueil</p> <p>Le texte de S : réductions, divisions et regroupements d'épigrammes</p> <p>Le texte de S : variantes</p> <p>Accords erronés de S avec P et Pl</p> <p><strong>III. Autres témoins utilisés dans cette édition</strong></p> <p>Les compilations majeures : P et Pl (et l'apographe Q)</p> <p>Recueils mineurs porteurs d'une tradition indépendante</p> <p>Recueils mineurs dérivés de Planudes</p> <p>&nbsp;</p> <p>Introduction au texte</p> <p><em>Conspectus Siglorum</em></p> <p>Texte critique</p> <p>Traduction italienne</p> <p>Traduction française</p> <p><em>Auctarium Lectionum</em></p> <p>Annexe</p> <p>Bibliographie</p> <p>Lexique</p> <p>Index des notions</p> | V13: https://www.pun-ed.fr/resources/titles/28777100504790/images/579600f6b6044f107758cdda0ca0aacb/HIGHQ/9791024019468.jpg | W13: 9791024019468.jpg | X13: 200 | Y13: 15.5 | Z13: 23 | AA13: 1.5 | AB13: 400 | AC13: LIT004190 | AD13: 3437 | AF13: 6 | AG13: 28777100504790 | AH13: 9791024019468 | AI13: TRUE | AJ13: TRUE | AK13: 18 | AL13: À paraître | AM13: Floridi, Lucia, B10 | AS13: 9791024019468 | AT13: 10 | AU13: 2 | AV13: DB | BB13: 0 | BN13: BC
A14: 9791024019574 | B14: austriaca-n-98-9791024019574 | C14: Austriaca, n° 98 | E14: Weinmann, Ute, B15; Baric, Daniel, B15 | F14: Ute Weinmann | J14: Presses universitaires de Rouen et du Havre | L14: Austriaca | M14: 98 | N14: 46226 | O14: 1 | P14: Livre broché | Q14: BC | S14: La tenue des Jeux olympiques à Paris en 2024 est apparue comme l'occasion de consacrer pour la première fois un cahier thématique d’"Austriaca" au sport autrichien en général et à l’olympisme en particulier. En explorant l’histoire du sport par le biais de l’olympisme, ce dossier souhaite contribuer à une historiographie multidisciplinaire. | T14: <p>La tenue des Jeux olympiques à Paris en 2024 est apparue comme l'occasion de consacrer pour la première fois un cahier thématique d’<em>Austriaca </em>au sport autrichien en général et à l’olympisme en particulier.</p> <p>En explorant l’histoire du sport par le biais de l’olympisme, ce dossier intitulé "Olympiades" souhaite contribuer à une historiographie résolument multidisciplinaire. Les études réunies s’inscrivent dans une recherche collective sur l’histoire du Mouvement olympique autrichien au sens large, sur une chronologie plus que centenaire, tant dans l’espace habsbourgeois que dans les configurations successives de l’Autriche. Sont rassemblés des articles qui abordent la question de l'olympisme <em>stricto sensu</em> tout en explorant ce qui fait l'originalité de l’essor et du rôle des compétitions olympiques en Autriche.</p> <p>L’un de ces aspects originaux concerne la précocité et la permanence d’un intérêt esthétique et scientifique pour les Jeux de l’Antiquité. En 1733, à l’occasion de l’anniversaire de l’impératrice Élisabeth-Christine de Brunswick-Wolfenbüttel, épouse de l’empereur Charles VI et mère de Marie-Thérèse, Métastase (1698-1782), poète à la cour de Vienne, compose une <em>Olimpiade</em>, un livret en trois actes mêlant intrigues amoureuses sur fond de Jeux olympiques. Le succès de cette thématique olympique mise en scène avec différentes partitions ne se dément pas, notamment avec celle du compositeur tchèque Josef Mysliveček (1737-1781), jouée en 1778, encore reprise à Vienne en 2014 au <em>Theater an der Wien</em>. Les Jeux olympiques sont un spectacle, suscitent un imaginaire, inventés et goûtés à Vienne avant même leur réinvention moderne.</p> <p></p> </P> | U14: <p>Avant-propos</p> <p>Le corps, le sport et ses métaphores<br /> <strong>Daniel BARIC et Ute WEINMANN</strong></p> <p>Julius Jüthner&nbsp;: profil d'un projet pionnier d'histoire du sport antique, de sa genèse à sa postérité, de l'Empire à la République<br /> <strong>Daniel BARIC</strong></p> <p> Otto Herschmann, un pionnier des sports olympiques en Autriche&nbsp;<br /> strong>Matthias MARSCHIK, Rudolf MÜLLNER</strong></p> <p> Die lange Reise des Fußballdoktors Emanuel „Michl" Schwarz<br /> <strong>Wolfgang MADERTHANER</strong></p> <p> Sport und Politik. Die Wiener Sportlandschaft der Zwischenkriegszeit&nbsp;<br /> <strong>Bernhard HACHLEITNER</strong><br /> <br /> Les Olympiades ouvrières de Vienne (1931)&nbsp;: Une démonstration de force en trompe-l'oeil<br /> <strong>Guillaume ROBIN</strong></p> <p>"Ich gehörte noch nicht der allerneuesten Generation an, die durch Fußball, Skilauf und Boxen geschlechtsreif wird" –Joseph Roths skeptisches Verhältnis zu sportlichen Aktivitäten&nbsp;<br /> <strong>Herta Luise OTT</strong></p> <p>« Man hört nur das Beste vom Gedeihen der Berliner Olympiade ». Friedrich Torberg, contempteur des Jeux olympiques de Berlin<br /> <strong>Jacques LAJARRIGE</strong></p> <p>L’Autriche et les Jeux de Hitler à Garmisch-Partenkirchen et Berlin<br /> <strong>Alfred PFOSER</strong></p> <p><strong>Ski alpin et invention de la nation autrichienne&nbsp;: contribution d’une discipline olympique à l’identité nationale dans l’Autriche d’après-guerre<br /> <strong>Ute WEINMANN</strong></p> <p>Karl Schranz, un olympien trop professionnel&nbsp;? Une affaire entre dilemmes olympiques et rivalité franco-autrichienne<br /> ;<strong>Karl ZIEGER</strong></p> <p>Sport und Nationalgefühl;<br /> <strong>Gerald STIEG</strong></p> <p>Résumés/Zusammenfassungen/Abstracts</p> | W14: 9791024019574.jpg | Y14: 15.5 | Z14: 23 | AA14: 1.45 | AB14: 420 | AC14: SPO000000;HIS000000;HIS010000;SPO058000;SPO066000;ET;EV;ET060 | AD14: 3435 | AF14: 5 | AG14: 28777100239170 | AI14: TRUE | AJ14: TRUE | AK14: 25 | AL14: À paraître | AM14: Baric, Daniel, B15; Weinmann, Ute, B15 | AS14: 9791024019574 | AT14: 10 | AU14: 2 | AV14: D;DS;J;W;WZ | BB14: 0 | BN14: BC
A15: 9791024019208 | B15: european-studies-in-sports-history-vol-18-9791024019208 | C15: European Studies in Sports History, vol. 18 | D15: Sport and Religion | E15: Auteurs divers | F15: Auteurs divers | J15: Presses universitaires de Rouen et du Havre | L15: European Studies in Sports History | M15: 18 | N15: 46163 | O15: 1 | P15: Livre broché | Q15: BC | S15: The 18th issue of ESSH joins a long-standing and dynamic academic conversation on the intersection of sport and religion, offering a historical perspective that spans from the 19th century to the present day. Across this period, profound shifts in cultural and social practices have redefined how societies experience ritual, faith and the body. | T15: <p>The eighteenth issue of <em>European Studies in Sport History</em> joins a long-standing and dynamic academic conversation on the intersection of sport and religion, offering a historical perspective that spans from the nineteenth century to the present day. Across this period, profound shifts in cultural and social practices have redefined how societies experience ritual, faith, and the body. Sport has become one of the key spaces in which these transformations are expressed, contested, and sometimes ritualized in new ways. The famous story of Eric Liddell in <em>Chariots of Fire</em>, who refused to run on a Sunday because of his religious convictions, evokes a time when sacred obligations could outweigh Olympic ambition. Today, however, churches often stand empty while stadiums overflow. Collective identity and belonging, once nurtured through religious communities, are increasingly found in sport — through shared chants, symbols, and emotional rituals. The sacred has not disappeared but has migrated, changed form, or found new expressions. The contributions assembled in this volume examine the complex and evolving relationships between religion and sport: from competition to leisure, from amateur practice to professional performance, from sacred rituals to modern spectacles. Authors explore how both spheres have historically shared — and sometimes struggled over — values, spaces, gestures, and communities. The volume also reveals the persistence of religious expressions in contemporary sport, amplified by media and global audiences. Bringing together historians, sociologists, scholars of religion, anthropologists, and philosophers, this special issue offers a multifaceted portrait of how sport has mirrored, replaced, or intertwined with spiritual experience in modern and contemporary societies. It invites readers to reflect on the ways belief, identity, and the body continue to be negotiated on playing fields as much as in places of worship.</p> | U15: <p>Arnd Krüger, Angela Teja </br> <em>Sport and Religion: An Introduction </em></br> Manon Hedenborg White, Daniel Svensson </br> <em>Back to Nature? Natural Training and the Pursuit of Spiritual Well-Being in Swedish Sports Biographies </em></br> Dries Vanysacker </br> <em>John XXIII (1958-1963) and his Attitude towards Sport: just a Go-Between Pope or an Innovator?<em> </br> Florian G. Mildenberger </br> <em>Sport in the German Catholic Community: The Emergence and Relevance of the</em> Deutsche Jugendkraft (DJK) <em>until 1945 </em> Pere Fullana Puigserver, Rafel Morro Aguilar </br> <em>Club Deportivo Sant Felipe (1945-1969). El fonda de documentaci6n deportiva en el archiva del oratorio de Sant Felipe Neri De Palma</em> </br> Silvio Dorigo, Marco Dorigo </br> <em>La ginnastica e i primi sport tra i cattolici sloveni fmo alla prima guerra mondiale (1896-1914)</em> </br> Fatia Terfous </br> <em>Politique et mouvement sportif catholique pendant la seconde guerre mondiale : la question des femmes (1940-1944)</em> </br> Maria Eugenia Garda-Sottile, Isabella Scursatone </br> <em>Why Do We Give an Opinion Instead of Asking? In Search of the Voices and Staries of Muslim Sportswomen and the Wearing of the Hijab</em> </br> Book review </br> Abstracts </p> | W15: 9791024019208.jpg | X15: 200 | Y15: 15.5 | Z15: 23 | AA15: 1.1 | AB15: 342 | AC15: SPO000000 | AD15: 3864 | AF15: 6 | AG15: 28777100345730 | AH15: 9791024019208 | AI15: TRUE | AJ15: TRUE | AK15: 25 | AL15: Disponible | AM15: Auteurs divers, A01 | AN15: Auteurs divers | AS15: 9791024019208 | AT15: 20 | AU15: 4 | AV15: WS;HB | BN15: BC
A16: 9791024019505 | B16: penser-l-education-n-57-9791024019505 | C16: Penser l'éducation, n° 57 | E16: Auteurs divers | F16: Auteurs divers | J16: Presses universitaires de Rouen et du Havre | L16: Penser l'éducation | M16: 57 | N16: 46163 | O16: 1 | P16: Livre broché | Q16: BC | S16: La revue, varia, s'inscrit dans le champ spécifique qui croise la philosophie de l'éducation et l'histoire des idées pédagogiques et en ces temps de mutation, (re)pense, à nouveaux frais, l'éducation, dans ses principes, ses finalités, ses valeurs, ses pratiques et leurs conséquences. | T16: <p>La revue<em> Penser l'éducation</em> est une revue scientifique internationale à comité de lecture, adossée au Centre interdisciplinaire de recherches normand en éducation et en formation (CIRNEF), laboratoire de l'université de Rouen.<br /> Cette revue, qui existe depuis 1996, s'inscrit dans le champ spécifique qui croise la philosophie de l'éducation et l'histoire des idées pédagogiques.<br /> Traditionnellement, ces deux aspects sont reliés et relèvent de la philosophie de l'éducation. <em>Penser l'éducation</em> n'est pas un titre anodin, il porte une injonction et une promesse: en ces temps de mutation, il s'agit de (re)penser, à nouveaux frais, l'éducation, dans ses principes, ses finalités, ses valeurs, ses pratiques et leurs conséquences.<br /> Deux numéros sont publiés chaque année. Ils ont la particularité d'être composés, sans contrainte thématique, uniquement de varia et de comptes rendus de lecture. Depuis 2014, la revue <em>Penser l'éducation</em> est publiée par les Presses universitaires de Rouen et du Havre et en décembre 2022, elle ouvre sa page sur le portail OpenEdition Journals. La revue offre, à partir de 2024, une nouvelle formule en publiant des numéros thématiques ponctuels qui permettent une articulation de contributions autour d'un thème central qui a un écho en philosophie de l'éducation et/ou en histoire des idées pédagogiques. Une jeune rubrique «&nbsp;Penser l'éducation ailleurs&nbsp;» vient complémenter celles déjà existantes&nbsp;: «&nbsp;Recensions&nbsp;» et «&nbsp;Les fonds du MUNAÉ&nbsp;».</p> | U16: <p>Pierre Billouet<br /> <em>De la zététique</em></p> <p>Dominique Broussal<br /> <em>Qui veut la peau de la gamification&nbsp;? Du débat pédagogique comme opportunité de «&nbsp;mise en crise&nbsp;» des modèles de formation</em></p> <p>Elisa Frassetto<br /> <em>Exercices de pensée conceptuelle, imaginative et sociale en classes de troisième et de seconde</em> Renaud Hétier<br /> <em>La démocratie à l'épreuve de l'Anthropocène&nbsp;: quelle réponse éducative&nbsp;?</em></p> <p>Élisabeth Maizonnier-Payelle<br /> <em>Instauration et circulation de la pédagogie d’initiation de Germaine Tortel. Entre voix pédagogiques et voies institutionnelles pour une Education Through Art</em></p> <p>Olivier Marty<br /> <em>Qu’est-ce que le métier d’enseignante du supérieur&nbsp;? Enseigner, (re)chercher et administrer dans le troisième degré</em></p> <p>Sandra Psomas<br /> <em>Des pensées de Hegel sur l’enseignement dans ses Textes pédagogiques : des caractéristiques dialectiques&nbsp;?</em></p> <p><strong>Recension</strong></p> <p>Alain Trouvé, <em>L’enquête et le sens. Littérature et questionnement</em>. (Michel Fabre, L’Harmattan, 2023)</p> <p><strong>Les fonds du MUNAÉ</strong></p> <p><em>La figure de Louis Pasteur dans les collections du Musée national de l’Éducation</em>, par Emily Busato</p> <p><strong>Penser l’éducation ailleurs</strong></p> <p><em>Retour sur l’éducation zapatiste au Mexique, entretien avec Bruno Baronnet</em></p> <p><strong>Résumés</strong></p> <p><strong>Les auteurs</strong></p> | V16: https://www.pun-ed.fr/resources/titles/28777100383440/images/8c2d7d2728733cad5681b6b79ae799e4/HIGHQ/9791024019505.jpg | W16: 9791024019505.jpg | X16: 206 | Y16: 15.5 | Z16: 23 | AA16: 1.1 | AB16: 352 | AC16: PSY012000;PHI000000;PSY000000;PSY030000;ET | AD16: 3013 | AF16: 6 | AG16: 28777100383440 | AH16: 9791024019505 | AI16: TRUE | AJ16: TRUE | AK16: 26 | AL16: Disponible | AM16: Auteurs divers, A01 | AN16: Auteurs divers | AS16: 9791024019505 | AT16: 20 | AU16: 4 | AV16: Y | BB16: 0 | BN16: BC
A17: 9791024018737 | B17: microfinance-et-innovations-9791024018737 | C17: Microfinance et innovations | D17: Un regain de dynamisme de la finance inclusive | E17: Acclassato Houensou, Denis, B15; Galiègue, Xavier, B15; Sossou, Gilles Armand, B15 | F17: Denis Acclassato Houensou | J17: Presses universitaires de Rouen et du Havre | L17: Microfinance contemporaine | M17: 4 | N17: 46072 | O17: 1 | P17: Livre broché | Q17: BC | S17: Face aux défis que la microfinance doit relever, cet ouvrage se structure en trois axes. Il fait un état des lieux de la situation de la microfinance en Afrique subsaharienne, avant de se pencher sur la performance des institutions de microfinance. Enfin, il s'interroge sur les nouvelles tendances observées dans le domaine de la microfinance. | T17: <p>Cet ouvrage est le quatrième de la collection «&nbsp;Microfinance contemporaine&nbsp;» ouverte par l'Association internationale de chercheurs francophones en microfinance (AICFM) crée en 2012 avec le soutien de l’Agence universitaire de la francophonie (AUF). Cette association a pour but de faciliter les échanges – en français – entre chercheurs du Nord et du Sud sur la microfinance et les problèmes qu’elle soulève désormais.</p> <p>Le premier volume, <em>La microfinance contemporaine&nbsp;: défis et perspectives</em>, était issu de journées scientifiques organisées à Brazzaville. Le deuxième, <em>La microfinance contemporaine&nbsp;: crises et mutations</em>, des journées de Douala. Le troisième, <em>La microfinance contemporaine&nbsp;: Le financement de la microfinance</em>, des rencontres de Casablanca. Ce cinquième volume revient sur les journées qui se sont déroulées à l’université d’Abomey-Calavi (Bénin).</p> <p>Face aux défis que la microfinance doit relever, les contributions qui ont été retenues se structurent selon trois grands axes. Tout d’abord, un certain nombre d’entre elles font un <em>état des lieux</em> de la situation de la microfinance en Afrique subsaharienne, en précisant le contexte contemporain dans lequel elle s’inscrit, à savoir une sous-bancarisation et une évolution vers le microcrédit entrepreneurial, dans un contexte de numérisation des moyens de paiement. Ensuite, la <em>performance</em> des institutions de microfinance fait l’objet d’un examen particulier. Cette performance s’explique en comparaisons internationales par des facteurs institutionnels et réglementaires spécifiques à chaque pays, et entre institutions de microfinance sur leur capacité à mobiliser des fonds propres plutôt que des ressources externes. Enfin, un ensemble de contributions s’interrogent sur <em>les nouvelles tendances</em> observées dans le domaine de la microfinance, qui viennent alimenter des débats déjà anciens&nbsp;: le caractère innovant de la microfinance, en termes de public visé et de méthodes de recouvrement, le développement du paiement mobile en chine ou encore la surchauffe observée sur le marché de la microfinance et la complémentarité entre banques traditionnelles et IMF.</p> | U17: <p><strong>Remerciements</strong></p> <p><strong>Avant-propos par Xavier Galiègue</strong></p> <p><strong>Partie 1 - </strong><strong>La microfinance en Afrique subsaharienne : état des lieux</strong></p> <p><em>Les établissements de microfinance et la sous-bancarisation dans la CEMAC</em>, par Hilarion Kontchop</p> <p><em>Microfinance et innovations sociales au Bénin : vers un microcrédit entrepreneurial</em>, par Denis Acclassato Houensou, Achille Barnabé Assouto, Modeste Senou et Sylvain Hekponhoue</p> <p><em>Finance numérique et règlementation de la microfinance dans les pays de l'UEMOA&nbsp;: un survol de la littérature</em>, par Alastaire Alinsato et Eudoxie Bessan</p> <p><em>Droit, finance digitale et croissance économique en Afrique subsaharienne</em>, par Fidèle K. Delidji et Magloire Lanha</p> <p><em>Microfinance, capital social et inégalités</em>, par Maxime Menuet et Patrick Villieu</p> <p>&nbsp;</p> <p><strong>Partie 2 - Quelles performances des institutions de microfinance&nbsp;?</strong></p> <p><em>Facteurs macro-économiques et macro-institutionnels et performances des institutions de microfinance (IMF) dans l'Union Economique et Monétaire Ouest-Africaine (UEMOA)</em>, par Tchapo Gbandi, Mawuli K. Couchoro et Jacques M. Agossou</p> <p><em>Sources de financement et performances des structures financières décentralisées au Bénin</em>, par Yves Hounguevou, Magloire Lanha et Jude Eggoh</p> <p><em>Inclusions financière et foncière&nbsp;: quels effets sur le bien-être des ménages au Bénin&nbsp;?</em>, par Alastaire Sèna Alinsato et Ken'tché Gérard Houndote</p> <p><em>Régime d'incitation et performance des institutions de microfinance au Bénin</em>, par Denis Acclassato Houensou et Melain Modeste Senou</p> <p><em>Exclusion sur les marchés de crédit en présence des coûts de transaction des garanties</em>, par Albert Honlonkou</p> <p>&nbsp;</p> <p><strong>Partie 3 - Nouveaux enjeux, anciens débats&nbsp;?</strong></p> <p><em>Innovations en microfinance ou recours à de vieilles recettes&nbsp;?</em>, par Christian Rietsch</p> <p><em>En Chine, le paiement mobile est-il "&nbsp;monnaie courante&nbsp;"&nbsp;?</em>, par Thierry Pairault</p> <p><em>Freiner un marché de microcrédit en surchauffe : les plafonds de taux d’intérêt sont-ils pertinents&nbsp;?</em>, par Tristan Caballero-Montes, Cécile Godfroid et Marc Labie</p> <p><em>Les liens sociaux et la confiance&nbsp;: quelle influence sur les modes de financement alternatifs des Très Petites Entreprises (TPE)&nbsp;? Une application au Bénin</em>, par Marc Dieudonné Gnanho, Marie-Thérèse Um-Ngouem et Noé Ndjeck</p> <p><em>Complémentarité financière Banque islamique du Sénégal/institutions de microfinance et financement des PME sénégalaises&nbsp;: modélisation et estimation sur données de panel dynamique</em>, par Massamba Souleymane Seck et Ibrahima Thiam</p> | V17: https://www.pun-ed.fr/resources/titles/28777100665710/images/a2cdd86a458242d42a17c2bf4feff069/HIGHQ/9791024018737.jpg | W17: 9791024018737.jpg | X17: 272 | Y17: 15.5 | Z17: 23 | AA17: 2.6 | AB17: 750 | AC17: BUS027000;BUS092000;BUS090000;BUS069000;LAW014000 | AD17: 3177 | AF17: 6 | AG17: 28777100665710 | AI17: TRUE | AJ17: TRUE | AK17: 24 | AL17: Disponible | AM17: Acclassato Houensou, Denis, B15; Galiègue, Xavier, B15; Sossou, Gilles Armand, B15 | AS17: 9791024018737 | AT17: 10 | AU17: 4 | AV17: K;KC;KF;KJ;LB | BB17: 0 | BC17: 1 | BN17: BC
A18: 9791024019130 | B18: austriaca-n-97-9791024019130 | C18: Austriaca, n° 97 | D18: Raoul Schrott, poète érudit et rêveur de sciences | E18: Grimm-Hamen, Sylvie, B15 | F18: Sylvie Grimm-Hamen | J18: Presses universitaires de Rouen et du Havre | L18: Austriaca | M18: 97 | N18: 2025-12-11 | O18: 1 | P18: Livre broché | Q18: BC | S18: Ce numéro est consacré au poète et romancier Raoul Schrott (1964) mettant en avant sa facette de « poète érudit » en quête de savoir animant sa démarche créatrice. Figure singulière et originale de la littérature autrichienne contemporaine, il est un écrivain éclectique, dont l'œuvre prolifique fait dialoguer les époques, les genres et les savoirs. | T18: <p>Les contributions rassemblées dans ce volume tentent de saisir l'œuvre de Raoul Schrott à partir de la figure du poète-érudit et d'un mode de création reposant sur la circulation des savoirs et des discours. Elles interrogent les ressorts et les effets de cette quête d’érudition, sur les plans heuristique, épistémologique, littéraire, méthodologique. Elles s’attachent à décrire non seulement ses manifestations dans le détail des textes mais s’efforcent aussi de saisir les enjeux symboliques d’une telle posture, entre désir d’affirmation professionnelle, polémiques savantes, impératif de la défense de la littérature. Les textes sont publiés dans leur langue originale. S’y adjoignent des poèmes et un court texte en prose inédits de Raoul Schrott, en lien avec le sujet du numéro.</p> | U18: <p>Avant-propos<br /> Biographie</p> <p><!--StartFragment-->Zum Poeta Laureatus<br /> <strong>Raoul Schrott&nbsp;</strong><!--EndFragment--></p> <p><em>Poetologische Gedichte</em><br /> <strong>Raoul Schrott&nbsp;</strong></p> <p><em>Naturpolitik. Raoul Schrott und Alexander von Humboldt</em><br /> <!--StartFragment--><strong>Oliver Lubrich</strong><!--EndFragment--><!--EndFragment--></p> <p><em>Zur Gedichtsprache Raoul Schrotts in </em>Hotels<br /> <!--StartFragment-->Sigurd Paul Scheichl<!--EndFragment--></p> <p><em>Raoul Schrott. La figure du </em>poeta doctus<em> au prisme de l'épistémocritique</em><br /> <!--StartFragment--><strong>Laurence Dahan-Gaida</strong><!--EndFragment--><br /> <br /> <em>Raoul Schrott als „poeta doctus"</em><br /> <!--StartFragment--><strong>Heribert Tommek</strong><!--EndFragment--></p> <p><em>Écriture littéraire, écriture savante&nbsp;: la mise en scène de la science par Raoul Schrott</em><br /> <!--StartFragment--><strong>Sylvie Grimm-Hamen</strong><!--EndFragment--><em> </em></p> <p><em>Das planetarische Gedächtnis, das Gedächtnis des Genoms und das Gedächtnis der lyrischen Form in Raoul Schrotts „Erste Erde. Epos"</em><br /> <!--StartFragment--><strong>Aura Heydenreich</strong><!--EndFragment--></p> <p><em>VARIA</em></p> <p><em>Gregor von Rezzoris </em>Idiotenführer<em> - Das Handbuch zur deutschen Nachkriegsgesellschaft?</em><br /> <!--StartFragment--><strong>Nathalie Fend de Sousa Lobo</strong><!--EndFragment--></p> <p><em>Bourbons et légitimistes exilés dans l'empire d'Autriche : survivre sans régner (1832-1836)</em><br /> <!--StartFragment--><strong>Pierre Morel</strong><!--EndFragment--></p> <p>DES IDÉES ET DES FAITS<em>&nbsp;</em><br /> <br /> <em>Le kafkaesque</em><br /> <!--StartFragment--><strong>Fiona O'Donnell<!--EndFragment--><em>&nbsp;</em></strong></p> <p>Notices bibliographiques<br /> Publications récentes sur l'Autriche<br /> Résumés/ Zusammenfassungen/ Abstracts</p> | V18: https://www.pun-ed.fr/resources/titles/28777100555360/images/c7c3e78e3c9d26cc1158a8735d548eaa/HIGHQ/9791024019130.jpg | W18: 9791024019130.jpg | X18: 256 | Y18: 15.5 | Z18: 23 | AA18: 1.45 | AB18: 426 | AC18: LIT004170;POE000000;SCI015000;LIT024050 | AF18: 6 | AG18: 28777100555360 | AH18: 9791024019130 | AI18: TRUE | AJ18: TRUE | AK18: 25 | AL18: Disponible | AM18: Grimm-Hamen, Sylvie, B15 | AS18: 9791024019130 | AT18: 20 | AU18: 4 | AV18: D;C;DC;DS | BB18: 0 | BN18: BC
A19: 9791024019178 | B19: european-studies-in-sports-history-vol-17-9791024019178 | C19: European Studies in Sports History, vol. 17 | D19: Sports and Politics | E19: Kumar, Rahul, B15; Serapiglia, Daniele, B15 | F19: Rahul Kumar | J19: Presses universitaires de Rouen et du Havre | L19: European Studies in Sports History | M19: 17 | N19: 2025-12-11 | O19: 1 | P19: Livre broché | Q19: BC | S19: The seventeenth volume of European Studies in Sport History is devoted to one of the most debated and interdisciplinary themes in sports historiography: the relationship between sport and politics. This issue brings together a selection of studies that reflect the diversity of approaches and chronologies. | T19: <p>The seventeenth volume of <em>European Studies in Sport History</em> is devoted to one of the most debated and interdisciplinary themes in sports historiography: the relationship between sport and politics. Based on contributions first presented at the 2021 CESH Congress in Lisbon – held jointly with the ISHPES Congress – this issue brings together a selection of studies that reflect the diversity of approaches, chronologies, and contexts through which this intersection has been explored and reinterpreted in recent years. Building on the framework developed by Allen Guttmann, who identified six key areas – from totalitarian regimes to Olympic policies, from racial and gender politics to class dynamics – the articles in this volume extend the conversation by asking new questions and adopting innovative methodologies. Political dimensions of sport are examined in colonial contexts, such as football in Mozambique under Portuguese rule, and in symbolic rivalries between sporting heroes, such as that between Fausto Coppi and Gino Bartali in postwar Italy, laden with ideological and religious meaning. The issue also explores how sports clubs became spaces for political resistance and social integration, as seen in the case of C.F. Estrela da Amadora in Portugal, and how sport was managed under authoritarian systems such as Francoist Spain and Piłsudski's Poland. Local studies, such as the case of Rijeka/Fiume, and broader investigations like the dissemination of Italian fencing in Argentina, reveal how power, identity, and belonging intersected in the sporting world of the twentieth century. Collectively, the articles offer a critical perspective on sport’s role in shaping national imaginaries, producing social hierarchies, and negotiating collective identities. The volume confirms the value of sports history as a privileged lens through which to understand the political and social dynamics of modernity.</p> | U19: <p>Rahul Kumar, Daniele Serapiglia, <em>Sport and Politics: an introduction</em></p> <p>Nuno Domingos<em>, </em><em>Colonial Football and Contentious Integrations: the case of Lourenço Marques under Portuguese rule</em></p> <p>Stefano Pivato, <em>Italian sports between politics, myths, and fake news</em></p> <p>Andreia Fontenete Louro, Daniel Freire Santos, Gil Gonçalves, <em>The Value of Small Clubs – C.F. Estrela da Amadora and the contributions of a club-based analysis to sports history (1932-2011</em>)</p> <p>Vanni D'Alessio, <em>Football and Ethnicity in Hungarian Fiume-Rijeka. Sports, Nationalization and Multilingualism at the Dawn of the 20th century</em></p> <p>Kamil Potrzuski, <em>Józef Piłsudski and his influence on the development of physical culture and sport in Poland in the light of Polish historiography - an outline</em></p> <p>Carlos García Martí, <em>Amateurism Fascist Style: From Fervent Amateurism to Pragmatic Shamateurism in Francoist Athletics (1939-1957)</em></p> <p>Deborah Guazzoni, <em>Sports immigration and its political implications in Argentina: the cases of the Italian fencers Eugenio Pini and Candido Sassone in Argentina</em></p> <p>Abstracts</p> | V19: https://www.pun-ed.fr/resources/titles/28777100470610/images/3ff4cea152080fd7d692a8286a587a67/HIGHQ/9791024019178.jpg | W19: 9791024019178.jpg | X19: 202 | Y19: 15.5 | Z19: 23 | AA19: 1.15 | AB19: 250 | AC19: SPO019000 | AD19: 3377 | AF19: 6 | AG19: 28777100470610 | AH19: 9791024019178 | AI19: TRUE | AJ19: TRUE | AK19: 25 | AL19: Disponible | AM19: Kumar, Rahul, B15; Serapiglia, Daniele, B15 | AS19: 9791024019178 | AT19: 20 | AU19: 4 | AV19: WS | BN19: BC
A20: 9791024019239 | B20: revue-du-philanthrope-n-13-9791024019239 | C20: Revue du Philanthrope, n° 13 | D20: Abolition et antiesclavagisme du XVIIe au XIXe siècle | E20: Auteurs divers | F20: Auteurs divers | J20: Presses universitaires de Rouen et du Havre | L20: Revue du Philanthrope | M20: 13 | N20: 2025-12-11 | O20: 1 | P20: Livre broché | Q20: BC | S20: Ce numéro se tourne vers l'Atlantique, à travers l'étude du Directoire, du mouvement quaker originel, de la mémoire, des stratégies discursives des militants abolitionnistes et de ses liens avec la franc-maçonnerie. Ce dossier précède des contributions sur les libres de couleur à Nantes, sur le judaïsme et sur les planteurs normands en Guadeloupe. | T20: <p>Ce numéro de la <em>Revue du Philanthrope</em> est essentiellement consacré à de nouvelles approches de l'Abolition de la traite et de l’esclavage atlantiques et de leurs mémoires. Des contributions de Marie-Jeanne Rossignol, Simon Ferelloc, Germaine Lemétayer et Fernando Marques traitent de thèmes aussi variés que le maintien de la défense de la cause abolitionniste sous le Directoire, les conditions d’apparition des thèses abolitionnistes dans le mouvement quaker, la place qu’elles occupent dans la mémoire protestante, les stratégies discursives adoptées par les militants abolitionnistes et la complexité des relations entre l’antiesclavagisme et des milieux philanthropiques emblématiques comme la franc-maçonnerie. Il s’achève par des contributions sur les libres de couleur dans le plus grand port de traite français (Nantes), sur les positions du judaïsme devant l’esclavage et les premiers planteurs de Guadeloupe.</p> | U20: <p>Editorial</p> <p><strong>Dossier Abolition et antiesclavagisme du XVII<sup>e</sup> au XIX<sup>e</sup> siècle</strong></p> <p><em>Le «&nbsp;moment&nbsp;» quaker, Lumières et révolutions&nbsp;: l'engagement antiesclavagiste des Amis américains, des origines (1688) au schisme de 1827 </em></p> <p>Marie-Jeanne Rossignol</p> <p>&nbsp;</p> <p><em>Un port de traite face à l'abolitionnisme du Directoire&nbsp;: l'exemple de Nantes (1794-1799)</em></p> <p>Simon Férelloc</p> <p>&nbsp;</p> <p><em>La mort de l'esclave dans le débat abolitionniste français dans la première moitié du XIX<sup>e </sup>siècle</em></p> <p>Bérénice Juret</p> <p>&nbsp;</p> <p><em>De l'injonction d’oubli au devoir de mémoire : l’Abolition de l’esclavage et la transmission de l’expérience irénique de Paray-le-Monial</em></p> <p>Germaine Lemétayer</p> <p>&nbsp;</p> <p><em>L</em><em>a franc-maçonnerie portugaise entre esclavagisme et antiesclavagisme. Réseaux maçonniques transocéaniques dans l’Empire portugais</em></p> <p>Fernando Marques da Costa</p> <p>&nbsp;</p> <p><em><strong>Varia</strong></em></p> <p><em>Les libres de couleur </em><em>au XVIII<sup>e</sup>&nbsp;siècle dans le premier port de traite français&nbsp;: Nantes</em></p> <p>Bernard Michon</p> <p>&nbsp;</p> <p><em>L’image de l’esclave juif dans le monde hellénistique et romain</em></p> <p>Nicolas Masuez</p> <p>&nbsp;</p> <p><em>Les origines normandes des premiers maîtres de la Guadeloupe </em></p> <p>Frédéric Régent</p> <p>&nbsp;</p> <p><em>Nantes, port d’émigration vers les colonies antillaises de la France au XVIII<sup>e</sup>&nbsp;siècle&nbsp;: premiers jalons d’une recherche en cours</em></p> <p>Bernard Michon</p> <p>&nbsp;</p> <p><strong>Recension </strong></p> <p>Gilbert Buti, <em>Traites négrières en France méditerranéenne XVII<sup>e</sup>-XIX<sup>e</sup>&nbsp;siècle. Trafic infâme et discours vertueux</em>, Paris, Les Éditions du Cerf, 2023</p> <p>Bernard Michon</p> <p>&nbsp;</p> | V20: https://www.pun-ed.fr/resources/titles/28777100669230/images/44e55ed981c434536b85d307e6215b26/HIGHQ/9791024019239.jpg | W20: 9791024019239.jpg | X20: 218 | Y20: 15.5 | Z20: 23 | AA20: 1.25 | AB20: 350 | AC20: HIS010000;HIS001000;HIS039000;HIS054000 | AD20: 3389 | AF20: 6 | AG20: 28777100669230 | AH20: 9791024019239 | AI20: TRUE | AJ20: TRUE | AK20: 19 | AL20: Disponible | AM20: Auteurs divers, A01 | AN20: Auteurs divers | AS20: 9791024019239 | AT20: 20 | AU20: 4 | AV20: HBG | BB20: 0 | BN20: BC
A21: 9791024019260 | B21: beautes-vitales-9791024019260 | C21: Beautés vitales | D21: Pour une approche contemporaine de la beauté | E21: Worms, Anne-Lise, B15; Zernik, Clélia, B15 | F21: Anne-Lise Worms | J21: Presses universitaires de Rouen et du Havre | N21: 2025-12-11 | O21: 1 | P21: Livre broché | Q21: BC | S21: À quoi bon, pourquoi donc parler – encore – de « beauté » ? Pour retrouver dans celle-ci une vitalité, une valeur, un pouvoir de transformation et d'orientation capables de nous interroger sur la manière de nous confronter aux enjeux d’aujourd’hui ; car, loin d’être mortifère, la beauté peut être l’opérateur d’un futur commun, d’un monde habitable. | T21: <p>Inscrite dans le temps long de l'histoire, la notion de beauté serait intimidante, aliénante, parfaitement relative, voire poussiéreuse. À quoi bon, pourquoi donc parler – encore – de «&nbsp;beauté&nbsp;»&nbsp;? L’hypothèse que nous soutenons réaffirme à l’inverse les enjeux d’universalité, d’humanisme, de plaisirs et d’émotions qui sont spécifiques à la beauté. Nous pensons possible, et même nécessaire, de retrouver dans celle-ci une vitalité, une valeur, un pouvoir de transformation et d’orientation capables de nous interroger sur la manière de nous confronter aux enjeux d’aujourd’hui&nbsp;; car, loin d’être mortifère, la beauté peut être, selon nous, l’opérateur d’un futur commun, d’un monde habitable.</p> | U21: <p>Remerciements</p> <p>Avant-propos</p> <p>I. BEAUTÉ ET VIE&nbsp;: ANCIENS ET NOUVEAUX DISCOURS</p> <p>Anne-Lise Worms -&nbsp;<em>Plotin contre Platon&nbsp;? Chercher la beauté dans le vivant et dans la vie&nbsp;&nbsp;</em></p> <p>Catherine Baroin -&nbsp;<em>Vieux et laid, mais sage : éloges romains de la laideur</em></p> <p>Rémi Mermet -&nbsp;<em>La beauté contemporaine au miroir de l'esthétique</em></p> <p>II. LA BEAUTÉ AU CŒUR DE LA VIE ET DU VIVANT &nbsp;&nbsp;&nbsp;&nbsp;&nbsp;&nbsp;&nbsp;&nbsp;&nbsp;&nbsp;&nbsp;&nbsp;&nbsp;&nbsp;&nbsp;&nbsp;&nbsp;&nbsp;&nbsp;&nbsp;&nbsp;&nbsp;&nbsp;&nbsp;&nbsp;&nbsp;&nbsp;&nbsp;&nbsp;&nbsp;&nbsp;&nbsp;&nbsp;&nbsp;&nbsp;&nbsp;&nbsp;&nbsp;&nbsp;&nbsp;&nbsp;&nbsp;&nbsp;&nbsp;&nbsp;&nbsp;&nbsp;&nbsp;&nbsp;&nbsp;&nbsp;</p> <p>Claudine Cohen -&nbsp;<em>Formes, diversité et beauté du vivant. Morphologie, science et art de Richard Owen à Stephen Jay Gould</em></p> <p>Bertrand Prévost -&nbsp;<em>Beautés animales&nbsp;: ordre ou expression ?</em></p> <p>Claudine Sagaert -&nbsp;<em>L'herbe et la bête. </em><em>Philosophie de la «&nbsp;mauvaise&nbsp;» herbe à la bestiole</em></p> <p>Didier Nectoux -&nbsp;<em>Beautés minérales, sources d’inspiration et de création</em></p> <p>Philippe Bonnin -&nbsp;<em>Poétique du jardin japonais : la villa détachée et les jardins de Katsura&nbsp;</em></p> <p>III. QUELS PARADIGMES DE BEAUTÉ DANS LES ARTS&nbsp;?</p> <p>Chiara Vecchiarelli -&nbsp;<em>Notes pour une philosophie de la tension de surface</em> <em>ou La beauté comme relation&nbsp; &nbsp; </em></p> <p>Carole Maigné -&nbsp;<em>Sauver les phénomènes : la beauté vitale en photographie. À partir de Simondon et de Marker</em></p> <p>Pierre Sauvanet -&nbsp;<em>Beautés jazz(s)</em></p> <p>Guilhem Marion -&nbsp;<em>La beauté, une expérience socialement définie&nbsp;?&nbsp; &nbsp; &nbsp; &nbsp;</em></p> <p>IV. L’ENJEU VITAL DE LA BEAUTÉ &nbsp;&nbsp;&nbsp;&nbsp;&nbsp;&nbsp;&nbsp;&nbsp;&nbsp;&nbsp;&nbsp;&nbsp;&nbsp;&nbsp;&nbsp;&nbsp;&nbsp;&nbsp;&nbsp;&nbsp;&nbsp;&nbsp;&nbsp;&nbsp;&nbsp;&nbsp;&nbsp;&nbsp;&nbsp;&nbsp;&nbsp;&nbsp;&nbsp;&nbsp;&nbsp;&nbsp;&nbsp;&nbsp;&nbsp;&nbsp;&nbsp;&nbsp;&nbsp;&nbsp;&nbsp;&nbsp;&nbsp;&nbsp;&nbsp;&nbsp;&nbsp;&nbsp;&nbsp;&nbsp;&nbsp;&nbsp;&nbsp;&nbsp;&nbsp;&nbsp;&nbsp;&nbsp;&nbsp;&nbsp;&nbsp;&nbsp;&nbsp;&nbsp;&nbsp;&nbsp;&nbsp;&nbsp;&nbsp;&nbsp;&nbsp;&nbsp;&nbsp;&nbsp;&nbsp;</p> <p>Gisèle Dambuyant -&nbsp;<em>Approche sociologique de la beauté en situation de vulnérabilité&nbsp; &nbsp; &nbsp; &nbsp;</em></p> <p>Clelia Zernik -&nbsp;<em>La beauté comme baume, après la catastrophe&nbsp; &nbsp; &nbsp;</em></p> <p>Frédéric Worms -&nbsp;<em>La beauté réellement vitale</em>&nbsp;</p> <p>V. <em>VARIA</em>&nbsp;&nbsp;&nbsp;&nbsp;&nbsp;&nbsp;&nbsp;&nbsp;&nbsp;&nbsp;&nbsp;&nbsp;&nbsp;&nbsp;&nbsp;&nbsp;&nbsp;&nbsp;&nbsp;&nbsp;&nbsp;&nbsp;&nbsp;&nbsp;&nbsp;&nbsp;&nbsp;&nbsp;&nbsp;&nbsp;&nbsp;&nbsp;&nbsp;&nbsp;&nbsp;&nbsp;&nbsp;&nbsp;&nbsp;&nbsp;&nbsp;&nbsp;&nbsp;&nbsp;&nbsp;&nbsp;&nbsp;&nbsp;&nbsp;&nbsp;&nbsp;&nbsp;&nbsp;&nbsp;&nbsp;&nbsp;&nbsp;&nbsp;&nbsp;&nbsp;&nbsp;&nbsp;&nbsp;&nbsp;&nbsp;&nbsp;&nbsp;&nbsp;&nbsp;&nbsp;&nbsp;&nbsp;&nbsp;&nbsp;&nbsp;&nbsp;&nbsp;&nbsp;&nbsp;&nbsp;&nbsp;&nbsp;&nbsp;&nbsp;&nbsp;&nbsp;&nbsp;&nbsp;&nbsp;&nbsp;&nbsp;&nbsp;&nbsp;&nbsp;&nbsp;&nbsp;&nbsp;&nbsp;&nbsp;&nbsp;&nbsp;&nbsp;&nbsp;&nbsp;&nbsp;&nbsp;&nbsp;&nbsp;&nbsp;&nbsp;&nbsp;&nbsp;&nbsp;&nbsp;&nbsp;&nbsp;&nbsp;&nbsp;&nbsp;&nbsp;&nbsp;&nbsp;&nbsp;&nbsp;</p> <p>Célia Boutilier -&nbsp;<em>Un galet au fond d’un lac boueux</em></p> <p>Mathias Dambuyant -&nbsp;<em>Quelques facéties sur le colloque «&nbsp;Beautés vitales&nbsp;» de Cerisy-la-Salle&nbsp; &nbsp; &nbsp; &nbsp; &nbsp; &nbsp; &nbsp; &nbsp; &nbsp;&nbsp;</em></p> <p>Lena Osseyran -&nbsp;<em>Des traces sur la beauté&nbsp;</em></p> <p><em>K</em>eiko Courdy -&nbsp;<em>Le Goût de la Beauté</em></p> <p>Les auteurs&nbsp; &nbsp; &nbsp; &nbsp; &nbsp; &nbsp; &nbsp; &nbsp; &nbsp; &nbsp; &nbsp; &nbsp; &nbsp; &nbsp; &nbsp; &nbsp; &nbsp; &nbsp; &nbsp; &nbsp; &nbsp; &nbsp; &nbsp; &nbsp; &nbsp; &nbsp; &nbsp; &nbsp; &nbsp; &nbsp; &nbsp; &nbsp; &nbsp; &nbsp; &nbsp; &nbsp; &nbsp; &nbsp; &nbsp; &nbsp; &nbsp; &nbsp; &nbsp; &nbsp; &nbsp; &nbsp; &nbsp; &nbsp; &nbsp; &nbsp; &nbsp; &nbsp; &nbsp; &nbsp; &nbsp;&nbsp;</p> | V21: https://www.pun-ed.fr/resources/titles/28777100918780/images/015389e74278202135dd6ed947ed32da/HIGHQ/9791024019260.jpg | W21: 9791024019260.jpg | X21: 284 | Y21: 15.5 | Z21: 23 | AA21: 1.65 | AB21: 468 | AC21: ART008000;ART009000;ART015000 | AD21: 3670 | AF21: 6 | AG21: 28777100918780 | AH21: 9791024019260 | AI21: TRUE | AJ21: TRUE | AK21: 15 | AL21: Disponible | AM21: Worms, Anne-Lise, B15; Zernik, Clélia, B15 | AS21: 9791024019260 | AT21: 20 | AU21: 4 | AV21: ABA | BB21: 0 | BN21: BC
A22: 9791024019338 | B22: le-c-ur-seul-9791024019338 | C22: « Le cœur seul » | D22: Vestiges de l'amour et ferments de la liberté dans l'œuvre de Claire de Duras | E22: Florence Filippi | F22: Florence Filippi | J22: Presses universitaires de Rouen et du Havre | L22: Cours | N22: 2025-11-20 | O22: 1 | P22: Livre broché | Q22: BC | S22: Claire de Duras détourne les codes du roman sentimental pour dénoncer les préjugés sociaux, raciaux et genrés. À travers des figures marginales, son œuvre interroge les illusions postrévolutionnaires et dénonce les systèmes d'oppression. Ses récits dessinent un horizon de solitude lucide, où l'amitié et la spiritualité remplacent l’idéal amoureux | T22: <p>L'œuvre de Claire de Duras déjoue l'image convenue de l’aristocrate éclairée et de la salonnière influente sous la Restauration. Ses trois romans donnent voix à des figures marginales, dont les souffrances révèlent les contradictions idéologiques et les désillusions de l’ère postrévolutionnaire. Loin de se conformer pleinement aux attentes du roman sentimental, son œuvre explore le «&nbsp;mal du siècle&nbsp;» selon une perspective singulière, pour en dénoncer les racines sociales et politiques. Elle examine ainsi la persistance des préjugés de race et de classe, non sans conserver les ambivalences d’un imaginaire colonial et genré. Cet essai entend montrer que le cadre traditionnel du roman sentimental n’est ici que prétexte à une redéfinition du canon romanesque, qui s’ouvre aux questions sociales pour déployer une critique, en creux, des inégalités et des structures oppressives.</p> <p>À défaut d’un salut possible dans l’amour, <em>Ourika, Édouard </em>et <em>Olivier ou le secret </em>explorent un horizon de solitude adoucie par les valeurs de l’amitié et de la spiritualité. Longtemps reléguée au second plan des histoires littéraires, l’œuvre de Claire de Duras esquisse les prémisses d’une pensée lucide sur la condition féminine entravée – qui est aussi celle des autrices de son temps – et préfère, aux impasses de l’idéal amoureux, des liens plus justes fondés sur l’égalité et l’émancipation.</p> | U22: <p><strong>Introduction </strong></p> <p><em>D'une exilée l'autre&nbsp;: Germaine de Staël et Claire de Duras</em></p> <p><em>De la </em>«&nbsp;délicieuse production<em>&nbsp;</em>» <em>à la revalorisation académique&nbsp;: fortune de l’œuvre</em></p> <p><em>Anti-roman sentimental ou roman anti-sentimental ?</em></p> <p>&nbsp;</p> <p><strong>Chapitre 1&nbsp;: Grandeur et solitude d’une femme puissante</strong></p> <p><em>Une légende du siècle&nbsp;: les vies parallèles de Claire de Duras</em></p> <p><em>Une artistocrate en bas-bleus&nbsp; &nbsp;&nbsp;</em></p> <p>&nbsp;</p> <p><strong>Chapitre 2 : Influences et héritages durassiens : pour un antiroman sentimental</strong></p> <p><em>Un modèle à réinventer : la tradition du roman sentimental</em></p> <p><em>Les affinités électives de Claire de Duras : entre héritage et modernité</em></p> <p><em>Des héritiers usurpateurs : Aloys, Stendhal et Fromentin</em></p> <p>&nbsp;</p> <p><strong>Chapitre 3 : Petite histoire et grande histoire : les récits enchâssés</strong></p> <p><em>Confessions d'enfants du siècle</em></p> <p><em>La puissance impuissante de l'aristocratie</em></p> <p>&nbsp;</p> <p><strong>Chapitre 4&nbsp;: Éloge de la claustration : tableaux de l'effacement consenti</strong></p> <p><em>Des personnages enfermés en eux-mêmes</em></p> <p><em>Voir sans être vu : le conte comme échappatoire</em></p> <p><em>Tableaux en liberté et cadres ouverts : peintures et portraits détourés</em></p> <p>&nbsp; &nbsp; &nbsp; &nbsp; &nbsp;&nbsp;<br /> <strong>Conclusion</strong></p> <p><strong>Bibliographie</strong></p> | V22: https://www.pun-ed.fr/resources/titles/28777100799070/images/c8b9abffb45bf79a630fb613dcd23449/HIGHQ/9791024019338.jpg | W22: 9791024019338.jpg | X22: 178 | Y22: 15.5 | Z22: 23 | AA22: 1.05 | AB22: 304 | AC22: LIT024040;LIT004150;LIT003000 | AD22: 3440 | AF22: 6 | AG22: 28777100799070 | AH22: 9791024019338 | AI22: TRUE | AJ22: TRUE | AK22: 13 | AL22: Disponible | AM22: Filippi, Florence, A01 | AN22: Florence Filippi | AS22: 9791024019338 | AT22: 10 | AU22: 4 | AV22: DSBF | BB22: 0 | BN22: BC
A23: 9791024018768 | B23: des-ethnographes-engage-e-s-9791024018768 | C23: Des ethnographes engagé·e·s | E23: Patrice Cohen; Anne Monjaret | F23: Patrice Cohen; Anne Monjaret | J23: Presses universitaires de Rouen et du Havre | N23: 2025-10-23 | O23: 1 | P23: Livre broché | Q23: BC | S23: Quelles sont les formes d'engagement dans la pratique ethnographique ? Une vingtaine d'ethnographes de différentes sciences sociales et générations présentent leurs expériences. Des régimes d’engagement sont ainsi discutés, à l’échelle d’un terrain, d’une carrière, d’un apprentissage universitaire. Un accès original aux coulisses de la recherche. | T23: <p>Quelles sont les formes d'engagement dans la pratique ethnographique&nbsp;? Une vingtaine d'ethnographes de différentes sciences sociales et générations présentent leurs expériences. Des régimes d’engagement sont ainsi discutés, à l’échelle d’un terrain, d’une carrière ou d’un apprentissage universitaire. Un accès original aux coulisses de la recherche en France comme ailleurs dans le monde, et aux rapports d’altérité qui se construisent en enquête. Vivre pleinement son ethnographie conduit souvent à s’adapter aux contextes étudiés, à s’impliquer dans la cité, parfois à militer, tout en interrogeant sa propre biographie et sa responsabilité éthique.</p> | U23: <p><strong>Note de l'éditeur</strong></p> <p><strong>Remerciements</strong></p> <p><strong>Introduction</strong></p> <p align="left"><em>Patrice Cohen et Anne Monjaret </em></p> <p>Les engagements de l'ethnographe</p> <p align="left"><strong>Partie&nbsp;1.&nbsp;L'apprentissage du terrain. Savoir s'ajuster et s'emparer des enjeux scientifiques</strong></p> <p align="left"><em>Sarah Pochon </em></p> <p align="left">Ethnographie en inconfort de classe<strong>. </strong>Intégration et distanciation sur le terrain de l'excellence scolaire</p> <p align="left"><em>Émilie Pontanier</em></p> <p align="left">Dons et contre-dons. Se faire accepter dans un collège de banlieue</p> <p align="left"><em>Thomas Bonnet </em></p> <p align="left">Jusqu'où aller&nbsp;? Limites du sociologue dans l'étude du risque émotionnel au travail</p> <p align="left"><em>Armèle Cloteau et Clément Petitjean </em></p> <p align="left">Être engagé·e par ou dans son terrain, une question de goût&nbsp;? Retours croisés sur des ethnographies du travail d’intermédiation à Chicago et Bruxelles</p> <p align="left"><strong>Partie&nbsp;2.&nbsp;Le gage complet de soi. Se donner à son terrain. </strong></p> <p align="left"><em>Barbara Č</em><em>urda </em></p> <p>Danseuse ou anthropologue&nbsp;? Les coulisses d’une ethnographie des pratiques de la danse Odissi en Inde</p> <p align="left"><em>Robin Delory </em></p> <p align="left">Combattre et enquêter. Une ethnographie sensorielle comparée du <em>mixed martial art</em> et du jeu vidéo de combat</p> <p align="left"><em>Audrey Tuaillon Demesy </em></p> <p align="left">S’impliquer sur le terrain jusqu’à s’engager corporellement. Une enquête dans la communauté du quidditch</p> <p align="left"><em>Florian Guerin </em></p> <p align="left">«&nbsp;Tu fais quoi ce soir&nbsp;?&nbsp;» Une immersion dans la vie nocturne et festive à Paris et à Madrid</p> <p align="left"><strong>Partie 3 – Une «&nbsp;vigilance réflexive&nbsp;». S’adapter et conceptualiser</strong></p> <p align="left"><em>Laurence Kotobi et Clara Lemonnier</em></p> <p align="left">Anthropologues de la santé face à la précarité et la migration. Des postures éthiques «&nbsp;négociées&nbsp;» aux formes d’engagement «&nbsp;situées&nbsp;»</p> <p align="left"><em>Isabelle Zinn</em></p> <p align="left">Comprendre le «&nbsp;travail bien fait&nbsp;» chez les fleuristes. Les émotions comme moteur de recherche et outil d’investigation</p> <p align="left"><em>Camille Gourdeau </em></p> <p>Recueillir les confidences de femmes migrantes victimes de violence. Un dilemme à résoudre dans une recherche sur la politique d'accueil des étranger·ère·s</p> <p align="left"><strong>Partie&nbsp;4.&nbsp;Les enjeux du militantisme. S’investir dans des terrains engagés</strong></p> <p><em>Ellie Mevel </em></p> <p align="left">Entre injonctions identitaires et engagements militants. Ethnographie de la diaspora palestinienne en France&nbsp;&nbsp;&nbsp;&nbsp;&nbsp;&nbsp;</p> <p align="left"><em>Emmanuel Pannier et Christian Culas </em></p> <p align="left">Enjeux et postures de la recherche ethnographique engagée dans des projets de développement au Vietnam</p> <p align="left"><em>Lola Vives </em></p> <p align="left">Être assignée lors d’une enquête au sein du programme «&nbsp;Un chez-soi d’abord&nbsp;». Accompagnement opérationnel et caution scientifique</p> <p align="left"><em>Émeline Zougbédé</em></p> <p align="left">Chercher et militer en milieu syndical&nbsp;? Une ethnographie à l’épreuve du temps du terrain</p> <p align="left"><strong>Partie 5. Les formes de la transmission. Innover dans la formation des ethnographes </strong></p> <p align="left"><em>Monica Heintz </em></p> <p align="left">Œuvrer pour vulgariser l’écriture ethnographique et anthropologique&nbsp;? Expériences dans un enseignement universitaire de master.</p> <p align="left"><em>Domitille Blanco,</em><em> Mélodie Gauglin, Bénédicte Rivet et Lola Vives </em></p> <p>Analyser les pratiques de recherche de terrain. Un engagement professionnel et déontologique&nbsp;?</p> <p align="left"><strong>Partie&nbsp;6.&nbsp;Des engagements professionnels au long cours. Prendre des chemins pluriels</strong></p> <p align="left"><em>Florence Weber </em></p> <p align="left">Le souci du territoire. Un espoir pour le xxi<sup>e</sup>&nbsp;siècle</p> <p align="left"><em>Alain Bertho </em></p> <p>De la recherche engagée à la recherche comme engagement. Comment je suis devenu ethnologue</p> <p align="left"><em>Dominique Desjeux</em></p> <p align="left">Un itinéraire réflexif sur l’engagement comme question épistémologique. Entre le vrai et le bien, entre connaissance et résolution des problèmes.</p> <p align="left"><strong>Conclusion</strong></p> <p align="left"><em>Patrice Cohen et Anne Monjaret </em></p> <p align="left">Être ethnographe engagé·e&nbsp;? Éprouver les mondes sociaux</p> <p><strong>Les auteur·e·s</strong></p> | V23: https://www.pun-ed.fr/resources/titles/28777100944700/images/7b3564b05f78b6739d06a2ea3187f5ca/HIGHQ/9791024018768.jpg | W23: 9791024018768.jpg | Y23: 15.5 | Z23: 23 | AA23: 2.2 | AB23: 647 | AC23: SOC000000;SOC002000;SOC008000;SOC015000 | AF23: 6 | AG23: 28777100944700 | AI23: TRUE | AJ23: TRUE | AK23: 15 | AL23: Disponible | AM23: Cohen, Patrice, A01; Monjaret, Anne, A01 | AN23: Patrice Cohen; Anne Monjaret | AS23: 9791024018768 | AT23: 20 | AU23: 4 | BN23: BC
A24: 9791024018874 | B24: dissimuler-pour-mieux-regner-9791024018874 | C24: Dissimuler pour mieux régner | D24: Locus politicus, locus secretus en littérature (XVIIe-XIXe siècles) | E24: Daguisé, Floriane, B15; Fix, Florence, B15 | F24: Floriane Daguisé | J24: Presses universitaires de Rouen et du Havre | N24: 2025-10-23 | O24: 1 | P24: Livre broché | Q24: BC | S24: Locus secretus... ou comment de la fin de l'Ancien Régime à l’avènement de la IIIe République en France subsiste un imaginaire culturel des lieux secrets comme lieux où s’exerce vraiment la politique. L’imaginaire du pouvoir repose sur ce principe : un pouvoir sérieux et respecté doit rester secret, un contre-pouvoir s’exerce dans l’ombre. | T24: <p>La fin de l'Ancien Régime voit disparaître les privilèges attachés à l’exercice d’un pouvoir puissamment hiérarchisé, ce qui laisse à penser que le fait politique se déploie alors selon des modalités plus transparentes et horizontales. Pour autant, l’imaginaire d’un pouvoir opaque, usant de cabinets dérobés et d’espaces interdits demeure, et les contre-pouvoirs mobilisent tout autant sociétés secrètes, mots de passe, masques et rendez-vous cachés. Par-delà les soubresauts politiques, de la Révolution à la Restauration, de la Monarchie à l’Empire et à la République, le pouvoir tend à s’enraciner dans le secret, dans des confidences, mais aussi, au sens le plus concret du terme, dans des espaces confidentiels où s’exerce une autre forme d’autorité. Les chapitres de ce volume mettent au jour les lieux secrets de célèbres fictions de Rousseau, Balzac ou Zola, des récits de voyage et des pièces de théâtre comme autant de lieux politiques, c’est-à-dire où se décide, s’exerce ou échoue l’action politique.</p> | U24: <p>Introduction</p> <p>&nbsp;</p> <p><strong>Première partie. Cartographie&nbsp;: situer le secret politique</strong></p> <p>Les espaces du secret dans Clarens</p> <p>Henri Portal</p> <p>&nbsp;</p> <p>Les lieux de la conjuration&nbsp;: société secrète et hétérotopie dans la littérature romantique</p> <p>Guillaume Cousin</p> <p>&nbsp;</p> <p>La politique dans le caveau. Le chronotope gothique d'<em>Une ténébreuse affaire</em></p> <p>Kathia Huynh</p> <p>&nbsp;</p> <p>Un cabinet de toilette bien politique. Les dessous du Second Empire dans trois romans d'Émile Zola</p> <p>Émilie Bauduin</p> <p>&nbsp;</p> <p><strong>Deuxième Partie. Discours : exhiber le secret politique</strong></p> <p>Énonciation référentielle et révélation des secrets du pouvoir chez Pontis, Sirot et Lenet</p> <p>Cécile Leduc</p> <p>&nbsp;</p> <p>Un secret de polichinelle&nbsp;: la révélation de la puissance de l'argent dans le <em>Code des gens honnêtes</em> (1825) de Balzac</p> <p>Marie-Agathe Tilliette</p> <p>&nbsp;</p> <p>L’échange épistolaire, lieu du secret politique dans <em>La Fortune des Rougon</em></p> <p>Etienne Poirier</p> <p>&nbsp;</p> <p><strong>Troisième Partie. Personnages&nbsp;: incarner le secret politique</strong></p> <p>Spectacle et dissimulation&nbsp;: anamorphose du tyran dans les récits de voyages de Bernier (1671) et Tavernier (1676)</p> <p>Mathilde Mougin</p> <p>&nbsp;</p> <p>Observation, exploration et espionnage dans la <em>Relation du voyage de la mer du Sud</em> d’Amédée Frézier (1716)</p> <p>Matthias Soubise</p> <p>&nbsp;</p> <p>L’œil du pouvoir&nbsp;: les lieux de Richelieu selon Georges de Scudéry</p> <p>Maxime Cartron</p> <p>&nbsp;</p> <p>Secrets de théâtre et héros «&nbsp;en déshabillé&nbsp;», de la comédie des Lumières au drame romantique</p> <p>Thibaut Julian</p> | V24: https://www.pun-ed.fr/resources/titles/28777100715080/images/6a26c75d6a576c94654bfc4dda548c72/HIGHQ/9791024018874.jpg | W24: 9791024018874.jpg | X24: 208 | Y24: 15.5 | Z24: 23 | AA24: 1.2 | AB24: 350 | AC24: LIT000000 | AD24: 3435 | AF24: 6 | AG24: 28777100715080 | AH24: 9791024018874 | AI24: TRUE | AJ24: TRUE | AK24: 14 | AL24: Disponible | AM24: Daguisé, Floriane, B15; Fix, Florence, B15 | AS24: 9791024018874 | AT24: 20 | AU24: 4 | AV24: DSA | BB24: 0 | BN24: BC
A25: 9791024018935 | B25: mazarin-et-les-pays-du-nord-9791024018935 | C25: Mazarin et les pays du Nord | E25: Loskoutoff, Yvan, B15; Carrangeot, Delphine, B15 | F25: Yvan Loskoutoff | J25: Presses universitaires de Rouen et du Havre | N25: 2025-10-23 | O25: 1 | P25: Livre broché | Q25: BC | S25: Le Mazarin méridional fut aussi un homme du Nord. Dans l'ordre politique, sa lutte contre les Habsbourg impliqua l'Europe nordique notamment par les traités de Westphalie. Dans l'ordre culturel, sa bibliothèque s'alimenta largement en Allemagne. Quant aux achats d'art, ils incluaient évidemment l'Europe du Nord (tableaux, tapisseries, curiosités). | T25: <p>Formé par les Barberini, s'affichant Romain dans sa propagande, Mazarin cultiva ses liens méridionaux. Il fut aussi un homme du Nord, dans l'ordre politique comme dans celui de la culture. Dans l'ordre politique, sa lutte contre les Habsbourg impliqua l'Europe nordique notamment par les traités de Westphalie. Contraint à l'exil par la Fronde, il se réfugia à Brühl en Rhénanie. Dans l'ordre culturel, sa bibliothèque était aussi une «&nbsp;bibliothèque nordique&nbsp;» largement alimentée en Allemagne. Quant aux achats d'art, ils incluaient évidemment l'Europe du Nord (tableaux, tapisseries, curiosités), à commencer par les acquisitions lors de la vente des collections de Charles Ier d'Angleterre.</p> | U25: <p>Remerciements</p> <p>Introduction</p> <p><strong>Première partie&nbsp;: Histoire</strong></p> <p><em>Sven Externbrink</em><br /> Dans l'ombre de Richelieu</p> <p><em>Guido Braun</em><br /> Mazarin et la conclusion de la paix de Westphalie</p> <p><em>David Parrott</em><br /> La conduite de la guerre de Trente Ans par Mazarin dans le Saint-Empire (1643-1648)</p> <p><!--StartFragment--><em>Julien Régibeau</em><!--EndFragment--><br /> L'exil comme bifurcation&nbsp;: le séjour de Mazarin à Brühl (1651)</p> <p><em>Olivier Poncet</em><br /> Négocier avec ou sans Mazarin : la mission de Pomponne&nbsp;II de Bellièvre aux Provinces-Unies (1650-1651)</p> <p><em>Maxim Boyko</em><br /> La diplomatie de Mazarin en Europe nord-orientale à l’épreuve de l’insurrection cosaque (1648-1650)</p> <p><em>Yvan Loskoutoff</em><br /> Amour et espionnage</p> <p><strong>Seconde partie&nbsp;: Arts et livres</strong></p> <p><em>Delphine Carrangeot</em><br /> Mazarin et les collections de Charles I<sup>er</sup>&nbsp;Stuart : jalons d’une histoire artistique et diplomatique</p> <p><em>Daniela del Pesco</em><br /> Mazarin et Van Dyck : les critères du collectionneur</p> <p><em>Sonia Cavicchioli</em><br /> Commandes artistiques de Marie-Béatrice d’Este, Marie de Modène, reine d’Angleterre (1673-1688)</p> <p><em>Yvan Loskoutoff</em><br /> La bibliothèque de Jean Tilleman Stella de Tercy et son acquisition pour la Mazarine</p> <p>Sources et bibliographie</p> | V25: https://www.pun-ed.fr/resources/titles/28777100225820/images/a53d1388191884b75c48bebb18709bfb/HIGHQ/9791024018935.jpg | W25: 9791024018935.jpg | X25: 334 | Y25: 15.5 | Z25: 23 | AA25: 1.9 | AB25: 551 | AC25: HIS037020 | AD25: 3387 | AF25: 6 | AG25: 28777100225820 | AH25: 9791024018935 | AI25: TRUE | AJ25: TRUE | AK25: 18 | AL25: Disponible | AM25: Carrangeot, Delphine, B15; Loskoutoff, Yvan, B15 | AS25: 9791024018935 | AT25: 20 | AU25: 4 | AV25: HBG | BB25: 0 | BN25: BC
A26: 9791024018553 | B26: heraldique-et-papaute-ii-9791024018553 | C26: Héraldique et papauté II | D26: Moyen Âge-Temps modernes | E26: Loskoutoff, Yvan, B15 | F26: Yvan Loskoutoff | J26: Presses universitaires de Rouen et du Havre | N26: 2025-07-24 | O26: 1 | P26: Livre broché | Q26: BC | S26: L'héraldique de pontifes particuliers est d’abord étudiée : art du livre (Léon X, Jules III), érudition (Urbain VIII), exploitation romaine (Innocent X, Clément XIII) ou bolonaise (Alexandre VII). On analyse ensuite l’usage monumental du blason, ses débuts, ses divers lieux : collégiale de Castelnau-Bretenoux, entrées des légats à Avignon, etc. | T26: <p>Ce recueil évoque d'abord des pontifes en particulier. Les papes de la Renaissance, Léon X et Jules III, offrent l’exemple de l’héraldique dans le livre, manuscrit ou imprimé. Au <sup>XVIIe</sup> siècle, on remarque son succès érudit sous Urbain VIII, son exploitation romaine pour Innocent X ou bolonaise pour Alexandre VII. Au XVIII<sup>e</sup> siècle, Piranèse se distingue, dédiant un cycle de frontispices à Clément XIII et décorant la villa des chevaliers de Malte. Ce qui permet d’ouvrir le second volet du recueil, portant sur l’usage monumental du blason. Il est analysé dans ses débuts, puis en ses divers lieux, de la collégiale de Castelnau-Bretenoux aux entrées des légats à Avignon, de l’église Sainte-Prisca sur l’Aventin à la basilique Saint-Pierre de Rome, pour finir par les palais de cette même ville, de Clément VIII à Clément X. </p> | U26: <p>Introduction<br /> <strong>Première partie : Papes</strong><br /> Elli Doulkaridou-Ramantani, <em>Aspects ludiques dans l'appareil héraldique des manuscrits de Léon X (1513-1521)</em><br /> Yvan Loskoutoff,<em> L'héraldique de Jules III Ciocchi del Monte (1550-1555) dans l'ornement pour le livre</em><br /> Fabrizio Federici, <em>Érudits et héraldique dans la Rome d'Urbain VIII (1623-1644)</em><br /> Daniela Del Pesco, <em>L'héraldique d'Innocent X Pamphili (1644-1655). Origines, architecture, décoration</em><br /> Sonia Cavicchioli, <em>« Micat in vertice ». L'héraldique d’Alexandre VII Chigi à Bologne, entre occultation et célébration (1658-1665)</em><br /> Yvan Loskoutoff, <em>Piranèse, l’héraldique et Clément XIII Rezzonico (1758-1769)</em><br /> <strong>Deuxième partie : Monuments</strong><br /> Laurent Hablot, <em>La mise en signe de l’espace par les papes : pratiques et conflits</em><br /> Emmanuel Moureau, <em>La collégiale Saint-Jean-Baptiste puis Saint-Louis de Castelnau-Bretenoux : un lien étroit et discret avec la papauté</em><br /> Camille Larraz, <em>Légitimer la légation avignonnaise. Héraldique et politique de l’Altera Roma (XVIe-XVIIe siècles)</em><br /> Rocco Ronzani, <em>Sainte-Prisca-sur-l’Aventin. Notes d’héraldique pontificale et cardinalice</em><br /> Martine Boiteux, <em>Héraldique et représentation à Saint-Pierre de Rome. Entre le durable et l’éphémère</em><br /> Frédéric Cousinié, <em>De Clément VIII Aldobrandini à Clément X Altieri</em><br /> Sources et bibliographie<br /> Table des figures</p> | V26: https://www.pun-ed.fr/resources/titles/28777100293930/images/4e96fc8ecd81da214039f63f34965275/HIGHQ/9791024018553.jpg | W26: 9791024018553.jpg | X26: 326 | Y26: 15.5 | Z26: 24 | AB26: 725 | AC26: HIS000000;HIS054000 | AD26: 3377 | AE26: Q | AF26: 6 | AG26: 28777100293930 | AH26: 9791024018553 | AI26: TRUE | AJ26: TRUE | AK26: 24 | AL26: Disponible | AM26: Loskoutoff, Yvan, B15 | AS26: 9791024018553 | AT26: 20 | AU26: 4 | AV26: HB;HBLH | BB26: 0 | BC26: 1 | BD26: Q | BE26: Q | BF26: Q | BN26: BC
A27: 9791024018836 | B27: spectacles-du-crime-feminin-en-europe-9791024018836 | C27: Spectacles du crime féminin en Europe | D27: Théâtre, musique, cinéma | E27: Ferry, Ariane, B15; le Blanc, Judith, B15; Le Gras, Gwénaëlle, B15 | F27: Ariane Ferry | J27: Presses universitaires de Rouen et du Havre | L27: Genre à lire... et à penser | N27: 2025-07-24 | O27: 1 | P27: Livre broché | Q27: BC | S27: Accompagnant la réévaluation par les sciences humaines de la violence des femmes, cet ouvrage explore les effets émotionnels et esthétiques de la spectacularisation du crime féminin et la production, à travers sa mise en scène (théâtre, opéra, cinéma), de figures de femmes fortes et fascinantes. | T27: <p>Pourquoi donner corps et voix aux femmes criminelles et criminalisées sur les scènes et les écrans, quand leurs agissements, leurs mots, leur assurance triomphante ou leur souffrance menacent les <em>bonnes</em> mœurs et un équilibre social reposant sur les inégalités de genre&nbsp;? Quel plaisir trouble et puissant éprouve le spectateur à voir et écouter ces femmes, à les admirer, à souffrir ou jubiler avec elles que tout semble condamner&nbsp;? Accompagnant la réévaluation par les sciences humaines de la violence des femmes, cet ouvrage interroge les effets émotionnels et esthétiques de la spectacularisation du crime féminin et la production, à travers sa mise en scène, de figures de femmes fortes.</p> | U27: <p><em>Introduction</em></p> <p style="text-align: center;">I<sup>re</sup> partie&nbsp;: Figurations de la criminelle à la scène et à l'écran : du mythe au discours social et politique</p> <p style="text-align: center;">Chap. 1&nbsp;: Criminelles mythiques et mythifiées&nbsp;: perspectives diachroniques et intermédiales</p> <p>&nbsp;</p> <p>Jean-François Lattarico, <em>La figure de Messaline (XVII<sup>e</sup>-XX<sup>e</sup>&nbsp;siècles). Entre crime et érotomanie</em></p> <p>Florence Filippi, <em>Ordonner le meurtre. Quelques exemples d'interprétation du rôle d’Hermione entre la Révolution et la Restauration</em></p> <p>Loïc Guyon, <em>«&nbsp;Mademoiselle Sept Heures&nbsp;»&nbsp;: la représentation de Charlotte Corday sur la scène théâtrale française au XIX<sup>e</sup>&nbsp;siècle</em></p> <p>Sophie Mentzel, <em>Marguerite de Bourgogne, reine criminelle en représentation : théâtre et cinéma</em></p> <p>Catherine Géry, <em>Femme criminelle et violence sexuelle : le cas de la Lady Macbeth du district de Mtsensk (littérature et opéra)</em></p> <p>Arnaud Duprat de Montero, <em>La marâtre criminelle de</em> Blancanieves <em>(Pablo berger, 2012) ou la métaphore d’une filiation paradoxale</em></p> <p>&nbsp;</p> <p style="text-align: center;">Chap. 2&nbsp;: Nouveaux discours sur la criminalité féminine à la scène et à l’écran</p> <p>&nbsp;</p> <p>Sophie Lucet, <em>Expier la violence de la Révolution ? La périlleuse </em>Théroigne de Méricourt<em> (1902) de Sarah Bernhardt et de Paul Hervieu</em></p> <p>Anne Bléger, <em>L’infanticide et la suicidaire dans le cinéma français des années 1920 : le spectacle de la vulnérabilité féminine</em></p> <p>Chiara Tognolotti, <em>Mourir (et trahir) par amour : la criminalisation de l’homosexualité féminine dans </em>Roma città aperta <em>de Roberto Rossellini (1945)</em></p> <p>Émilie Giaime, <em>Séductrice et criminelle : le procès de Dominique Marceau&nbsp;/ Brigitte Bardot dans</em> La Vérité <em>d’Henri-Georges Clouzot (1960)</em></p> <p>Armelle Talbot, <em>Un mariage et neuf enterrements : </em>Liberté à Brême <em>de Fassbinder (1971)</em></p> <p>Cécile Auzolle, «&nbsp;Je l’ai tuée parce que je voulais avoir un enfant&nbsp;». Meurtres au féminin dans les spectacles de Joël Pommerat</p> <p>&nbsp;</p> <p style="text-align: center;">II<sup>e</sup>&nbsp;partie&nbsp;: Enjeux idéologiques et esthétiques de la spectacularisation de la criminelle</p> <p style="text-align: center;">Chap. 1&nbsp;: Tensions entre criminalisation et fascination, hier et aujourd’hui</p> <p>&nbsp;</p> <p>Sabine Gruffat, <em>La méchanceté féminine sur la scène classique : une passion active ou subie ?</em></p> <p>Cécilia Laurin, <em>«&nbsp;Elle n’a que fureur et que vengeance en l’âme :&nbsp;/ mais en si peu de temps que peut faire une femme ?&nbsp;» Modalités spectaculaires du crime féminin sur la scène cornélienne</em></p> <p>Marie Saint-Martin, <em>Clytemnestre en spectacle chez Eschyle, Sénèque et Alfieri : monstre idéologique, monstre esthétique</em></p> <p>Caroline Giron-Panel, <em>Maléfiques ? Magnifiques&nbsp;! Criminelles bibliques sur les scènes lyriques ?</em></p> <p>&nbsp;</p> <p style="text-align: center;">Chap. 2&nbsp;: Enjeux esthétiques contemporains du crime féminin</p> <p>&nbsp;</p> <p>Sana M’Selmi, « Un père n’est pas toujours la solution <em>». Le crime féminin : stéréotypie, mise en spectacle et valeurs dans le cinéma de Pedro Almodóvar</em></p> <p>Delphine Edy, <em>Valérie Dréville, une mère infanticide incandescente et spectaculaire</em></p> <p>Ulysse Caillon, <em>« J’aimerais tuer » : désirs criminels et identifications meurtrières dans le théâtre d’Angélica Liddell</em></p> <p>Stéphane Hervé, <em>Poppée et Octavie, par-delà bien et mal ? Pouvoir, sexualité et mise à mort de</em> <em>l’</em>Incoronazione di Poppea <em>à</em> Poppea e Nerone</p> <p>Sarah Nancy, <em>L’opéra, spectacle d’un crime vocal féminin ? Écueils d’un scénario esthétique</em></p> <p>&nbsp;</p> <p><em>Bibliographie</em></p> <p><em>Index</em></p> <p><em>Les auteur·ice·s</em></p> | V27: https://www.pun-ed.fr/resources/titles/28777100690450/images/859b755563f548d008f936906a959c8f/HIGHQ/9791024018836.jpg | W27: 9791024018836.jpg | X27: 472 | Y27: 15.5 | Z27: 23 | AA27: 2.6 | AB27: 776 | AC27: SOC000000;ART000000;SOC010000;SOC032000;SOC028000 | AD27: 3080 | AE27: J | AF27: 5 | AG27: 28777100690450 | AI27: TRUE | AJ27: TRUE | AK27: 21 | AL27: Disponible | AM27: Ferry, Ariane, B15; le Blanc, Judith, B15; Le Gras, Gwénaëlle, B15 | AR27: https://books.openedition.org/purh/26396 | AS27: 9791024018836 | AT27: 20 | AU27: 4 | AV27: J;D;JFSJ | BB27: 0 | BD27: J | BE27: J | BF27: J | BN27: BC
A28: 9791024018904 | B28: penser-l-education-n-56-9791024018904 | C28: Penser l'éducation, n° 56 | E28: Gutierrez, Laurent, B15; Alix, Sébastien-Akira, B15 | F28: Laurent Gutierrez | J28: Presses universitaires de Rouen et du Havre | L28: Penser l'éducation | M28: 56 | N28: 45862 | O28: 1 | P28: Livre broché | Q28: BC | S28: La revue s'inscrit dans un champ qui croise la philosophie de l'éducation et l'histoire des idées pédagogiques. Le thème de ce numéro est : Penser les crises en éducation et en formation. | T28: <p>La revue s'inscrit dans un champ qui croise la philosophie de l'éducation et l'histoire des idées pédagogiques. Le thème de ce numéro est&nbsp;: "Penser les crises en éducation et en formation".</p> <p>La revue<em> Penser l'éducation</em> est une revue scientifique internationale à comité de lecture, adossée au Centre interdisciplinaire de recherches normand en éducation et en formation (CIRNEF), laboratoire de l'université de Rouen.<br /> Cette revue, qui existe depuis 1996, s'inscrit dans le champ spécifique qui croise la philosophie de l'éducation et l'histoire des idées pédagogiques.<br /> Traditionnellement, ces deux aspects sont reliés et relèvent de la philosophie de l'éducation. <em>Penser l'éducation</em> n'est pas un titre anodin, il porte une injonction et une promesse: en ces temps de mutation, il s'agit de (re)penser, à nouveaux frais, l'éducation, dans ses principes, ses finalités, ses valeurs, ses pratiques et leurs conséquences.<br /> Deux numéros sont publiés chaque année.La taille des articles n'est ni formatée ni normalisée, sans autre justification que celle d'un processus d'évaluation rigoureux.</p> <p>Ce numéro 56 est thématique&nbsp;: "Penser les crises en éducation et en formation". Les mots clés&nbsp;: Arendt, Carpentier, compétences, crise, écodélégués, école, éducation, éducation à, éducation physique, éducation sexuelle, environnement, formation, histoire des idées, individuation, inégalité, mai 1968, nature, parents d'élèves, pédagogie, Peyrefitte, philosophie, politique scolaire, postmodernité, rapports de pouvoir, savoir, travail social.</p> | U28: <p><em>Introduction</em></p> <p>Emmanuel Brassat - <em>Sens et conditions des crises de la forme scolaire et de son évolution </em></p> <p>Sameh Dellaï - <em>La notion de crise chez Arendt : approche critique et perspectives éducatives</em></p> <p>Sébastien Laffage-Cosnier et Willy Hugedet - <em>Les aléas d'une réforme pédagogique pendant la crise de Mai 68</em></p> <p>Gauthier Fradois -<em> Le tract Carpentier : crise du système d'enseignement et politisation de l'éducation sexuelle</em></p> <p>Michaël Pouteyo - <em>Formation des éducateurs : tensions conceptuelles et réarticulations par temps de crise</em></p> <p>Julien Fuchs, Anne Bertin-Renoux et Léa Gottsmann - <em>Les enjeux de l'éducation à l'environnement : prise de conscience d'une crise de sens de l'éducation contemporaine</em></p> <p>Les fonds du Munaé</p> <p><em>Recension</em></p> <p><em>Résumés</em></p> <p><em>Les auteur.e.s</em></p> <p>&nbsp;</p> | V28: https://www.pun-ed.fr/resources/titles/28777100894430/images/e1e4e65fddf79af60aab04457a6565a6/HIGHQ/9791024018904.jpg | W28: 9791024018904.jpg | X28: 180 | Y28: 15.5 | Z28: 23 | AA28: 1.05 | AB28: 180 | AC28: EDU000000;EDU016000;EDU037000;EDU009000;SOC000000 | AD28: 3080 | AE28: JN | AF28: 5 | AG28: 28777100894430 | AI28: TRUE | AJ28: TRUE | AK28: 26 | AL28: Disponible | AM28: Alix, Sébastien-Akira, B15; Gutierrez, Laurent, B15 | AS28: 9791024018904 | AT28: 20 | AU28: 4 | AV28: JN;J;JNA;JNB | BB28: 0 | BD28: JN | BE28: JN | BF28: JN | BN28: BC
A29: 9791024018522 | B29: quand-l-enfance-rencontre-l-histoire-9791024018522 | C29: Quand l'enfance rencontre l'histoire | D29: Imaginaires, représentations et savoirs | E29: Emmanuelle Fantin; Julien Tassel | F29: Emmanuelle Fantin; Julien Tassel | J29: Presses universitaires de Rouen et du Havre | L29: Littérature de jeunesse et histoire | N29: 2025-06-19 | O29: 1 | P29: Livre broché | Q29: BC | S29: Qu'apprend-on de l'histoire en jouant aux Playmobil ou en découvrant au goûter les vignettes du chocolat Poulain ? Des jeux de société aux châteaux forts, en passant par la lanterne magique, l’objectif de cet ouvrage collectif est d’examiner l’histoire transmise aux enfants en dehors de l’école, à travers les jeux, les divertissements, les livres. | T29: <p>Qu'apprend-on de l'histoire en jouant aux Playmobil ou en découvrant au goûter les vignettes du chocolat Poulain&nbsp;? Jusqu’où la littérature jeunesse peut-elle dire les violences de l’histoire&nbsp;? Des jeux de société aux châteaux forts, en passant par la lanterne magique, l’objectif de cet ouvrage collectif est d’examiner l’histoire transmise aux enfants en dehors de l’école, à travers les jeux, les divertissements, les livres. Les auteurs explorent la diversité des ingénieries du passé à destination des enfants sondant aussi bien des dimensions matérielles de ces productions culturelles, que de leurs dimensions idéologiques, économiques et symboliques.</p> | U29: <p><em>Introduction</em></p> <p><strong>Première partie. Les imaginaires du passé&nbsp;: le passé sans l'histoire&nbsp;?</strong></p> <p>Anne Besson, <em>Retenir l'enfance. Usages transgénérationnels d'un passé merveilleux et ludique</em></p> <p>Laurence Corroy et Bénédicte Milland-Bove, <em>Imaginaires et représentations du Moyen Âge dans le </em>Journal des enfants<em> et le </em>Journal des demoiselles<em> sous Louis-Philippe</em></p> <p>Adeline Werry, <em>Les plaques de verre de la lanterne magique utilisée comme jouet&nbsp;: outils pour une transmission «&nbsp;attractive&nbsp;» du passé</em></p> <p>Entretien avec Richard Unglik</p> <p><strong>Deuxième partie. Les représentations de l'histoire&nbsp;: transmissions, tiraillements et injonctions paradoxales</strong></p> <p>Christiane Connan-Pintado, <em>Imaginaires et représentations de l’esclavage à l’usage des jeunes lecteurs</em></p> <p>Juliette Massart, <em>Littérature pour la jeunesse, Shoah et happy end. Sens et utilité d’un dénouement heureux dans la littérature pour la jeunesse sur la Shoah</em></p> <p>Pierre-Éric Fageol et Frédéric Garan, <em>Patrimonialisation du passé et construction identitaire dans la BD indiaocéanique</em></p> <p>Entretien avec Isabelle Doré-Rivé</p> <p><strong>Troisième partie. Produire des savoirs historiques par la fiction</strong></p> <p>Thierry Truel, <em>Les images de barres chocolatées et l’histoire scolaire&nbsp;: une culture scolaire partagée&nbsp;?</em></p> <p>Agathe Nicolas, <em>Le débat sur le fait historique comme prétexte à la production d’un savoir sur la fiction&nbsp;: le cas du forum d’échanges La Gazette du Sorcier</em></p> <p>Fabien Lacouture,<em> Jouer l’histoire. La place des jeux de société historiques dans les pratiques enfantines du passé</em></p> <p>Entretien avec Albin Quéru et Chloé Nicolas</p> <p>Entretien avec Vincent Dugomier</p> <p><em>Postface</em></p> <p><em>Bibliographie</em></p> <p><em>Les auteurs</em></p> <p><em>Table des figures</em></p> | V29: https://www.pun-ed.fr/resources/titles/28777100811900/images/6e71d53b8718fd5c285f6a1e12622bdd/HIGHQ/9791024018522.jpg | W29: 9791024018522.jpg | X29: 256 | Y29: 15.5 | Z29: 23 | AA29: 1.45 | AB29: 429 | AC29: JUV000000;JUV003000;JUV013000;JUV051000;JUV022000 | AD29: 3722 | AF29: 6 | AG29: 28777100811900 | AH29: 9791024018522 | AI29: TRUE | AJ29: TRUE | AK29: 18 | AL29: Disponible | AM29: Fantin, Emmanuelle, A01; Tassel, Julien, A01 | AN29: Emmanuelle Fantin; Julien Tassel | AS29: 9791024018522 | AT29: 20 | AU29: 4 | AV29: A;Y;YB;YD | BB29: 0 | BN29: BC
A30: 9791024018676 | B30: penser-l-education-n-55-9791024018676 | C30: Penser l'éducation, n° 55 | E30: Auteurs divers | F30: Auteurs divers | J30: Presses universitaires de Rouen et du Havre | L30: Penser l'éducation | M30: 55 | N30: 2025-06-19 | O30: 1 | P30: Livre broché | Q30: BC | S30: La revue, varia, s'inscrit dans le champ spécifique qui croise la philosophie de l'éducation et l'histoire des idées pédagogiques et en ces temps de mutation, (re)pense, à nouveaux frais, l'éducation, dans ses principes, ses finalités, ses valeurs, ses pratiques et leurs conséquences. | T30: <p>La revue<em> Penser l'éducation</em> est une revue scientifique internationale à comité de lecture, adossée au Centre interdisciplinaire de recherches normand en éducation et en formation (CIRNEF), laboratoire de l'université de Rouen.<br /> Cette revue, qui existe depuis 1996, s'inscrit dans le champ spécifique qui croise la philosophie de l'éducation et l'histoire des idées pédagogiques.<br /> Traditionnellement, ces deux aspects sont reliés et relèvent de la philosophie de l'éducation. <em>Penser l'éducation</em> n'est pas un titre anodin, il porte une injonction et une promesse: en ces temps de mutation, il s'agit de (re)penser, à nouveaux frais, l'éducation, dans ses principes, ses finalités, ses valeurs, ses pratiques et leurs conséquences.<br /> Deux numéros sont publiés chaque année. Ils ont la particularité d'être composés, sans contrainte thématique, uniquement de varia et de comptes rendus de lecture. Depuis 2014, la revue <em>Penser l'éducation</em> est publiée par les Presses universitaires de Rouen et du Havre et en décembre 2022, elle ouvre sa page sur le portail OpenEdition Journals. La revue offre, à partir de 2024, une nouvelle formule en publiant des numéros thématiques ponctuels qui permettent une articulation de contributions autour d'un thème central qui a un écho en philosophie de l’éducation et/ou en histoire des idées pédagogiques. À partir de ce <em>Penser l'éducation </em>numéro 55, une nouvelle rubrique «&nbsp;Penser l'éducation ailleurs&nbsp;» vient complémenter celles déjà existantes&nbsp;: «&nbsp;Recensions&nbsp;» et «&nbsp;Les fonds du MUNAÉ&nbsp;».</p> | U30: <p>Ambroise Baillifard<br /> <em>De l'irrespect, de l'effort, de la soumission à la critique et de l'aveu d’ignorance à l’Université</em></p> <p>Félix Barancy<br /> <em>Une liberté sous conditions&nbsp;? La formation du canon de la philosophie</em></p> <p>Sarah Habbar et Marie Agostini<br /> <em>Kant et le rôle de l’exemple dans l’enseignement de la philosophie</em></p> <p>Sébastien Miravete<br /> <em>Bergson et la question de l’éducation des masses</em></p> <p>Benoît Peuch<br /> <em>Habileté manuelle et expression de soi. Éléments pour une analyse socio-historique des attentes expressives à l’école maternelle (1886-2023)</em></p> <p>Camille Roelens<br /> <em>L’école en France et les nouvelles pensées libérales</em></p> <p>Laurie Simon, Sandrine Nicolas, Émilie Carosin et Antoine Derobertmasure<br /> <em>Analyse de l’évolution du référentiel d’éducation (culturelle et) artistique pour l’enseignement maternel en Belgique francophone entre 2013 et 2020</em></p> <p><strong>Recension</strong></p> <p>Sébastien Pesce, <em>Circulations en éducation. Acteurs, modèles, institutions (xix<sup>e</sup>-xx<sup>e</sup>&nbsp;siècle)</em> (Renaud d’Enfert, Frédéric Mole et Marie Vergnon dir., PUG, 2023)</p> <p><strong>Les fonds du MUNAÉ</strong></p> <p>Fantastique physique&nbsp;!<em>, exposition au MUNAÉ</em>, par Éléonore Belin</p> <p><strong>Penser l’éducation ailleurs</strong></p> <p><em>La pédagogie critique aux États-Unis, entretien avec Noah De Lissovoy</em></p> <p><strong>Résumés</strong></p> <p><strong>Les auteurs</strong></p> | V30: https://www.pun-ed.fr/resources/titles/28777100387850/images/018dbfb5fec8d864714ede49cef50343/HIGHQ/9791024018676.jpg | W30: 9791024018676.jpg | X30: 200 | Y30: 15.5 | Z30: 24 | AA30: 0.9 | AB30: 290 | AC30: EDU000000;HIS000000;HIS054000;PHI000000;ET;ET060 | AD30: 3013 | AF30: 6 | AG30: 28777100387850 | AH30: 9791024018676 | AI30: TRUE | AJ30: TRUE | AK30: 26 | AL30: Disponible | AM30: Auteurs divers, A01 | AN30: Auteurs divers | AS30: 9791024018676 | AT30: 20 | AU30: 4 | AV30: J;JN;Y | BB30: 0 | BN30: BC
A31: 9791024018720 | B31: european-studies-in-sports-history-vol-16-9791024018720 | C31: European Studies in Sports History, vol. 16 | E31: Auteurs divers | F31: Auteurs divers | J31: Presses universitaires de Rouen et du Havre | L31: European Studies in Sports History | M31: 16 | N31: 2025-06-19 | O31: 1 | P31: Livre broché | Q31: BC | S31: Les ESSH sont une revue scientifique consacrée à l'histoire du sport émanant du Comité européen du sport (CESH). Elle paraît annuellement et chaque livraison accueille, à la manière d'un varia, une sélection d'articles hétéroclites. | T31: <p>C'est en Grande-Bretagne que l'histoire de l'éducation physique et l'histoire du sport sont nées, à la fin du 19<sup>e</sup>. Qualifiée d’impériale en imposant une origine britannique aux sports modernes, l’historiographie britannique a ensuite subi l’influence du marxisme à partir des années 1950, en mettant l’accent sur le sport populaire et les minorités. Ailleurs en Europe le récit sportif, davantage né vers la seconde moitié du 20<sup>e</sup> et lié à la reconnaissance universitaire des formations en sciences du sport, s’intéresse aux figures fondatrices de la pédagogie du corps et de la gymnastique militaire. L’historiographie européenne a d’abord été scindée en deux, de part et d’autre du rideau de fer. La création de divers comités lié à l’histoire du sport en Europe a permis de jeter les bases d’une histoire comparée entre les pays. Aujourd’hui l’histoire du sport se renouvèle et s’intéresse à la circulation des modèles pédagogiques et scolaires, attentive aux médiateurs et à la réception de l’enseignement sportif, aux catégories de genre, d’origine, de classe sociale.</p> <p>Ce seizième volume explore des thèmes aussi divers que la création de la Fédération internationale du sport universitaire, la revue brésilienne <em>A Gazeta, </em>les rapports entre le sport "ouvrier" et "bourgeois" en Grèce dans les publications communistes de l'entre-deux-guerres, la trajectoire d'Anne Almeida, la "comtesse" du basket français ou encore les principes de la création à Varsovue d'un district olympique durant entre-deux-guerres.</p> | U31: <p>Lidia Lesnykh, <em>The Creation of the International University Sports Federation (FISU): The Student Cold War from 1946 to 1949</em></p> <p>Daniele Medeiros, Marcelo Moraes e Silva, <em>The newspaper </em>A Gazeta<em> and the new relations between sport and the city (São Paulo, Brazil, 1925-1933)</em></p> <p>Manolis Choumerianos, Athanasios Tsoumas, <em>Accounts of 'worker' and 'bourgeois' sport in Greek Interwar Communist Publications (1926-1936)</em></p> <p>Annabelle Caprais, Florys Castan-Vicente, <em>La «&nbsp;comtesse&nbsp;» du basket français&nbsp;: la trajectoire d'Anne d'Almeida au prisme des rapports sociaux (1892-1983)</em></p> <p>Kamil Potrzuski, <em>Unrealised concepts of creating an Olympic District in interwar Warsaw</em></p> <p><em>Abstracts</em></p> | V31: https://www.pun-ed.fr/resources/titles/28777100733270/images/8ae7398026ed8f2172aefd6cbc856bc8/HIGHQ/9791024018720.jpg | W31: 9791024018720.jpg | X31: 142 | Y31: 15.5 | Z31: 23 | AA31: 0.8 | AB31: 243 | AC31: SPO000000;SPO019000 | AD31: 3377 | AE31: SCX | AF31: 6 | AG31: 28777100733270 | AI31: TRUE | AJ31: TRUE | AK31: 25 | AL31: Disponible | AM31: Auteurs divers, A01 | AN31: Auteurs divers | AS31: 9791024018720 | AT31: 20 | AU31: 4 | AV31: W;H;HB;HBTB | BB31: 0 | BD31: SCX | BE31: SCX | BF31: SCX | BN31: BC
A32: 9791024018867 | B32: c-est-la-matiere-qui-pense-9791024018867 | C32: C'est la matière qui pense | D32: Pour une philosophie de l'édition | E32: Marcello Vitali-Rosati | F32: Marcello Vitali-Rosati | J32: Presses universitaires de Rouen et du Havre | L32: De code et de plomb | M32: 1 | N32: 2025-06-19 | O32: 1 | P32: Livre broché | Q32: BC | S32: La matière n'est pas quelque chose d'inerte et passif. Et la pensée n'est pas le produit d'un sujet. À partir d'une approche néomatérialiste et posthumaniste, ce livre propose une théorie de l'édition qui permet de repenser ce qu'est un texte, mais aussi et plus fondamentalement ce qu'est un être humain. | T32: <p>La pensée n'est pas le produit de l'esprit humain, mais une émanation de la matière. En se basant sur un cadre théorique néomatérialiste et posthumaniste, cet ouvrage explore comment le sens émerge des interactions matérielles, des formats, des outils, des pratiques éditoriales. Il remet en question les distinctions entre théorie et pratique, élite et subalternes, et met en lumière le rôle essentiel des "petites mains" dans la production du savoir. Dans ce cadre, l'édition n'est plus une simple pratique, mais elle devient une théorie à part entière, un lieu où la matière révèle sa force de production du sens. Cette approche invite à reconsidérer le sens du texte comme lieu d'apparition du sens et à partir de là à se questionner radicalement sur ce qu'est un être humain.</p> | U32: <p>Préface : À propos du code et du plomb</p> <p>Une matière terrible</p> <p>Le mauvais cigare</p> <p>La théorie de l'édition</p> <p>Formats et modèles</p> <p>Le cercle de la modélisation</p> <p>Mais alors qu'est-ce qu'un être humain ?</p> <p>Postface : L'édition, ce « dangereux supplément »</p> <p>Bibliographie</p> <p>Épilogue éditorial</p> | V32: https://www.pun-ed.fr/resources/titles/28777100095780/images/c8661fbb8d748c08800779b570047110/HIGHQ/9791024018867.jpg | W32: 9791024018867.jpg | X32: 92 | Y32: 15.5 | Z32: 23 | AA32: 0.5 | AB32: 140 | AC32: PHI000000;PHI005000;SOC000000;TEC000000 | AD32: 3080 | AE32: J | AF32: 6 | AG32: 28777100095780 | AI32: TRUE | AJ32: TRUE | AK32: 11 | AL32: Disponible | AM32: Gheeraert, Tony, A19; Mellet, Margot, A15; Vitali-Rosati, Marcello, A01 | AN32: Marcello Vitali-Rosati | AR32: https://ceen.univ-rouen.fr/matiere-marcello/ | AS32: 9791024018867 | AT32: 20 | AU32: 4 | AV32: H;G;HP;J;U | BB32: 0 | BD32: J | BE32: J | BF32: J | BN32: BC
A33: 9791024018867 | B33: c-est-la-matiere-qui-pense-9791024019123 | C33: C'est la matière qui pense | D33: Pour une philosophie de l'édition | E33: Marcello Vitali-Rosati | F33: Marcello Vitali-Rosati | J33: Presses universitaires de Rouen et du Havre | L33: De code et de plomb | M33: 1 | N33: 2025-06-19 | O33: 1 | P33: eBook | Q33: EC | S33: La matière n'est pas quelque chose d'inerte et passif. Et la pensée n'est pas le produit d'un sujet. À partir d'une approche néomatérialiste et posthumaniste, ce livre propose une théorie de l'édition qui permet de repenser ce qu'est un texte, mais aussi et plus fondamentalement ce qu'est un être humain. | T33: <p>La pensée n'est pas le produit de l'esprit humain, mais une émanation de la matière. En se basant sur un cadre théorique néomatérialiste et posthumaniste, cet ouvrage explore comment le sens émerge des interactions matérielles, des formats, des outils, des pratiques éditoriales. Il remet en question les distinctions entre théorie et pratique, élite et subalternes, et met en lumière le rôle essentiel des "petites mains" dans la production du savoir. Dans ce cadre, l'édition n'est plus une simple pratique, mais elle devient une théorie à part entière, un lieu où la matière révèle sa force de production du sens. Cette approche invite à reconsidérer le sens du texte comme lieu d'apparition du sens et à partir de là à se questionner radicalement sur ce qu'est un être humain.</p> | U33: <p>Préface : À propos du code et du plomb</p> <p>Une matière terrible</p> <p>Le mauvais cigare</p> <p>La théorie de l'édition</p> <p>Formats et modèles</p> <p>Le cercle de la modélisation</p> <p>Mais alors qu'est-ce qu'un être humain ?</p> <p>Postface : L'édition, ce « dangereux supplément »</p> <p>Bibliographie</p> <p>Épilogue éditorial</p> | V33: https://www.pun-ed.fr/resources/titles/28777100095780/images/919fbb6632a27fd57413b0fdba8edde8/HIGHQ/9791024019123.jpg | W33: 9791024019123.jpg | AC33: PHI000000;PHI005000;SOC000000;TEC000000 | AD33: 3080 | AE33: J | AF33: 6 | AG33: 28777100095780 | AI33: FALSE | AJ33: FALSE | AK33: 0 | AL33: Disponible | AM33: Gheeraert, Tony, A19; Mellet, Margot, A15; Vitali-Rosati, Marcello, A01 | AN33: Marcello Vitali-Rosati | AR33: https://ceen.univ-rouen.fr/matiere-marcello/ | AS33: 9791024019123 | AT33: 20 | AU33: 4
A34: 9791024018362 | B34: the-stars-in-mindless-space-9791024018362 | C34: The Stars in Mindless Space | D34: A Deeper Image | E34: Jerome Rothenberg | F34: Jerome Rothenberg | J34: Presses universitaires de Rouen et du Havre | L34: To | N34: 2025-03-20 | O34: 1 | P34: Livre broché | Q34: BC | T34: <p>As we move further into the new century and millennium, our work as poets has been compounded by the circumstances of the time in which we've all been working: events that have both reinforced that work—as poetry and prophecy—and an upsurge of forces that have come to stand against it.It is in this sense that we are proposing here an omnipoetics of the American hemisphere, as an experimental instance of what might be attempted further on a worldwide scale, toward what one of us once described as "an anthology of everything."</p> | U34: <p>The Mystery of False Attachments<br/> A Book of Infernos<br/> In the Shadow of a Mad King<br/> From <em>The President of Desolation</em><br/> A Round of Solipsisms<br/> Uncollected &amp; Poems Later: On Reaching Ninety<br/> After <em>Migrations</em>&nbsp;<em>A Poem of Variations for Gloria Gervitz</em></p> <p>&nbsp;&nbsp;&nbsp;&nbsp;&nbsp;&nbsp;&nbsp;&nbsp;&nbsp;&nbsp;&nbsp; Words &amp; Threads: A Poem of Variations</p> <p>&nbsp;&nbsp;&nbsp;&nbsp;&nbsp;&nbsp;&nbsp;&nbsp;&nbsp;&nbsp;&nbsp; For Arie Galles, from <em>A Book of Circles</em></p> <p>&nbsp;&nbsp;&nbsp;&nbsp;&nbsp;&nbsp;&nbsp;&nbsp;&nbsp;&nbsp;&nbsp;&nbsp;&nbsp;&nbsp;&nbsp;&nbsp;&nbsp;&nbsp;&nbsp;&nbsp;&nbsp;&nbsp;&nbsp; A Perfect Circle</p> <p>&nbsp;&nbsp;&nbsp;&nbsp;&nbsp;&nbsp;&nbsp;&nbsp;&nbsp;&nbsp;&nbsp;&nbsp;&nbsp;&nbsp;&nbsp;&nbsp;&nbsp;&nbsp;&nbsp;&nbsp;&nbsp;&nbsp;&nbsp; To Dream Infinity</p> <p>Coda to <em>A Book of Dreams</em></p> <p>The Leonardo Project</p> <p>The Mysteries of Mind Laid Bare in Talking</p> <p>Abraham Abulafia Visits the Pope</p> <p>Postface</p> <p>Author's Biography</p> <p>Publications</p> | V34: https://www.pun-ed.fr/resources/titles/28777100955420/images/f40723ed94042ea9ea36bfb5ad4157b2/HIGHQ/9791024018362.jpg | W34: 9791024018362.jpg | Y34: 11.5 | Z34: 18.5 | AA34: 1.25 | AB34: 159 | AC34: POE000000;POE005010 | AD34: 3435 | AF34: 1 | AG34: 28777100955420 | AH34: 9791024018362 | AI34: TRUE | AJ34: TRUE | AK34: 15 | AL34: Disponible | AM34: Rothenberg, Jerome, A01 | AN34: Jerome Rothenberg | AS34: 9791024018362 | AT34: 20 | AU34: 4 | AV34: DC | BB34: 0 | BC34: 1 | BN34: BC
A35: 9791024018393 | B35: les-etoiles-dans-l-espace-inconscient-9791024018393 | C35: Les Étoiles dans l'espace inconscient | D35: Une image plus profonde | E35: Jerome Rothenberg — Traduit par Anne Talvaz | F35: Jerome Rothenberg | H35: Anne Talvaz | J35: Presses universitaires de Rouen et du Havre | L35: To | N35: 2025-03-20 | O35: 1 | P35: Livre broché | Q35: BC | S35: Éditer un volume poétique et l'intituler « Les étoiles dans l'espace inconscient » se prête ainsi à la traduction en une offrande de lignes directrices et de leçons du passé, à transmettre, aussi, aux générations futures. | T35: <p>Au fur et à mesure que nous avançons dans le nouveau siècle et le nouveau millénaire, notre travail de poètes a été aggravé par les circonstances de l'époque dans laquelle nous avons tous travaillé&nbsp;: des événements qui ont à la fois renforcé ce travail - en tant que poésie et prophétie - et une recrudescence des forces qui sont venues s'y opposer. C'est dans ce sens que nous proposons ici une omnipoétique de l'hémisphère américain, comme un exemple expérimental de ce qui pourrait être tenté plus loin à l'échelle mondiale, vers ce que l'un d'entre nous a décrit un jour comme «&nbsp;une anthologie de tout&nbsp;».</p> | U35: <p>Le mystère des faux attachements<br/> Livre des enfers<br/> Dans l'ombre d'un roi fou<br/> Extraits du<em>&nbsp;Président de la désolation</em><br/> Ronde de solipsismes<br/> Poèmes récents et&nbsp;non édités en recueil : à&nbsp;quatre-vingt-dix ans<br/> La présence des morts dans tous les coins<br/> Après <em>Migrations </em>: <em>Poème de variations pour Gloria Gervitz</em><br/> Mots et fils : Poème de variations<br/> Pour Arie Galles, extrait ue <em>Livre des cercles</em><br/></p> <p style="margin-left:35.4pt;">&nbsp; &nbsp; &nbsp; &nbsp; &nbsp;Un cercle parfait</p> <p style="margin-left:35.4pt;">&nbsp; &nbsp; &nbsp; &nbsp; &nbsp;Rêver l'infini</p> <p>Coda au <em>Livre des rêves</em></p> <p>Le projet Léonard</p> <p>Les mystères de la conscience mis à nu par la parole</p> <p>Abraham Aboulafia rend visite au pape</p> <p>Postface</p> <p>Biographie de l'auteur</p> <p>Bibliographie</p> | V35: https://www.pun-ed.fr/resources/titles/28777100333660/images/9c6947bd95ae487c81d4e19d3ed8cd6f/HIGHQ/9791024018393.jpg | W35: 9791024018393.jpg | Y35: 11.5 | Z35: 18.5 | AA35: 1.25 | AB35: 159 | AC35: POE000000;POE005010 | AD35: 3435 | AF35: 1 | AG35: 28777100333660 | AI35: TRUE | AJ35: TRUE | AK35: 15 | AL35: Disponible | AM35: Rothenberg, Jerome, A01; Talvaz, Anne, B06 | AN35: Jerome Rothenberg | AP35: Anne Talvaz | AS35: 9791024018393 | AT35: 20 | AU35: 4 | AV35: D;DC | BB35: 0 | BC35: 1 | BN35: BC
A36: 9791024018423 | B36: des-objets-nous-accompagnent-9791024018423 | C36: Des objets nous accompagnent | D36: (ou l'inverse) | E36: James Sacré | F36: James Sacré | J36: Presses universitaires de Rouen et du Havre | L36: To | N36: 2025-03-20 | O36: 1 | P36: Livre broché | Q36: BC | S36: L'auteur raconte faire l’expérience d’une forte et apparemment universelle imbrication du familier et de l’étrangeté en toute chose. Tous ces objets nous racontent-ils ? Sans doute que oui, de par leur histoire, leurs formes et couleurs, leurs agencements entre eux… mais quoi comprendre vraiment ? | T36: <p>Selon James Sacré, ce poème invite à ressentir le mot «&nbsp;objet&nbsp;» comme porteur de présence concrète. Les objets sont là depuis toujours, dans les poèmes et dans des peintures, autant que dans le monde qui nous tient vivant. Nous les regardons, nous en parlons, nous les manipulons et en inventons beaucoup. Chaque objet est là dans sa singularité et reste en grande partie une énigme, même si nous les encombrons d'histoire, de souvenirs ou de plus ou moins vagues réflexions à son sujet. «&nbsp;Objet&nbsp;» est un mot qui désigne autant le concret du monde, ses singularités que l’abstraction dont notre parole entoure ces objets qu’elle s’imagine saisir. Les objets nous ramènent vers ce nœud d’activités à l’origine de toutes nos aventures humaines.</p> <p>L’auteur raconte faire l’expérience d’une forte et apparemment universelle imbrication du familier et de l’étrangeté en toute chose. Tous ces objets nous racontent-ils&nbsp;? Sans doute que oui, de par leur histoire, leurs formes et couleurs, leurs agencements entre eux… mais quoi comprendre vraiment&nbsp;? Nous avançons avec eux, les remerciant de nous maintenir vivant, les encombrant de convictions, de désirs et d’interrogations (extrait de la Postface).</p> | U36: <p>Il y a des objets qu'on regarde<br />Poteries données par des mains de partout<br />Toute une vaisselle en métal émaillé qu’on a jetée<br />Outils pour des bricolages d’écriture<br />Tant d’objets qui ne t’ont rien demandé<br />Une guenille plus que déchirée<br />Chaque livre écrit est un objet singulier<br />Le sentiment d’être dans une offrande<br />Ce geste de tasser des laines sur un métier à tisser<br />Des sentiments pour ce qu’on regarde<br />Un bruit de vie dans la mémoire incertaine</p><p>Postface<br />Notice biographique<br />Bibliographie</p> | V36: https://www.pun-ed.fr/resources/titles/28777100090880/images/7a677bb4477ae2dd371add568dd19e23/HIGHQ/9791024018423.jpg | W36: 9791024018423.jpg | X36: 168 | Y36: 11.5 | Z36: 18.5 | AA36: 1.5 | AB36: 150 | AC36: POE000000 | AD36: 3633 | AF36: 6 | AG36: 28777100090880 | AH36: 9791024018423 | AI36: TRUE | AJ36: TRUE | AK36: 13 | AL36: Disponible | AM36: Sacré, James, A01 | AN36: James Sacré | AS36: 9791024018423 | AT36: 20 | AU36: 4 | AV36: DC | BN36: BC
A37: 9791024018454 | B37: some-objects-stay-with-us-9791024018454 | C37: Some Objects Stay with Us | D37: (Or the Other Way Round) | E37: James Sacré — Traduit par David Ball | F37: James Sacré | H37: David Ball | J37: Presses universitaires de Rouen et du Havre | L37: To | N37: 2025-03-20 | O37: 1 | P37: Livre broché | Q37: BC | U37: <p>Translator's introduction<br /> There are objects that we look at<br /> Pieces of pottery given by hands from all over<br /> A whole set of enamelware dishes that someone threw out<br /> Tools for odd jobs of writing<br /> So many objects that didn't ask you a thing<br /> A more than ragged rag<br /> Each book written is a singular object<br /> The feeling of being in an offering<br /> That gesture of packing woolen thread onto a loom<br /> Feelings for what you're looking at<br /> A Sound of Life in the Uncertain Memory</p> <p>Postface<br /> The poet<br /> The translator</p> | V37: https://www.pun-ed.fr/resources/titles/28777100528460/images/7684e5225ab986f6b32ed950eec5621d/HIGHQ/9791024018454.jpg | W37: 9791024018454.jpg | X37: 156 | Y37: 11.5 | Z37: 18.5 | AA37: 1.15 | AB37: 150 | AC37: POE000000 | AD37: 3633 | AF37: 6 | AG37: 28777100528460 | AH37: 9791024018454 | AI37: TRUE | AJ37: TRUE | AK37: 13 | AL37: Disponible | AM37: Ball, David, B06; Sacré, James, A01 | AN37: James Sacré | AP37: David Ball | AS37: 9791024018454 | AT37: 20 | AU37: 4 | AV37: DC | BN37: BC
A38: 9791024018584 | B38: moses-roper-josiah-henson-9791024018584 | C38: Moses Roper, Josiah Henson | D38: Deux récits d'esclaves fugitifs | E38: Parfait, Claire, B10; Chambon, Simone, B10; Roy, Michaël, B10 | F38: Claire Parfait | J38: Presses universitaires de Rouen et du Havre | L38: Récits d'esclaves | N38: 2025-03-20 | O38: 1 | P38: Livre broché | Q38: BC | S38: Ce volume rassemble deux récits d'esclaves fugitifs, ceux de Moses Roper et Josiah Henson. Leurs témoignages apportent un éclairage contrasté sur des expériences de vie et d’évasion très différentes. Une introduction, des notes et des cartes les replacent dans le contexte de l’« institution particulière » aux États-Unis. | T38: <p>Ce volume de la collection «&nbsp;Récits d'esclaves&nbsp;» rassemble deux récits d’esclaves fugitifs, ceux de Moses Roper et Josiah Henson, publiés respectivement en 1837 et 1849. Les témoignages de ces deux hommes, l’un presque blanc, l’autre non métissé, l’un vivant dans le Sud profond et l’autre dans le Sud septentrional, l’un rebelle né, le second l’image même de la respectabilité, apportent un éclairage contrasté sur des expériences de vie puis d’évasion très différentes. Une introduction, des notes et des cartes replacent les récits et leurs auteurs dans le contexte de l’«&nbsp;institution particulière&nbsp;» aux États-Unis.</p> | U38: <p>Introduction<br />Avertissement sur les traductions</p><p><br />Récit des aventures et de l'évasion de Moses Roper, réchappé de l’esclavage en Amérique<br />Préface<br />Introduction<br />Notes de fin</p><p><br /> Vie de Josiah Henson, autrefois esclave, et désormais habitant du Canada, narrée par lui-même<br />Avertissement<br />Notes de fin</p><p><br />Annexes<br />Table des illustrations</p> | V38: https://www.pun-ed.fr/resources/titles/28777100369130/images/ce128c3e8f0c0ae4b3e843dc7cbab0f7/HIGHQ/9791024018584.jpg | W38: 9791024018584.jpg | X38: 186 | Y38: 15 | Z38: 20.5 | AA38: 1.35 | AB38: 245 | AC38: HIS000000;HIS037060;HIS036000;HIS056000 | AD38: 3377 | AE38: NHTS | AF38: 5 | AG38: 28777100369130 | AI38: TRUE | AJ38: TRUE | AK38: 18 | AL38: Disponible | AM38: Chambon, Simone, B10; Parfait, Claire, B10; Roy, Michaël, B10 | AS38: 9791024018584 | AT38: 32 | AU38: 4 | AV38: H;HB;HBTS | BB38: 0 | BD38: NHTS | BE38: NHTS | BF38: NHTS | BN38: BC
A39: 9791024018614 | B39: austriaca-n-96-9791024018614 | C39: Austriaca, n° 96 | D39: Jacques Bouveresse, philosophe « autrichien » au pays de Descartes | E39: Weinmann, Ute, B15; Bonnet, Christian, B15 | F39: Ute Weinmann | J39: Presses universitaires de Rouen et du Havre | L39: Austriaca | M39: 96 | N39: 2025-03-20 | O39: 1 | P39: Livre broché | Q39: BC | S39: Figure historique de la revue Austriaca, mais peu connu du grand public, car très éloigné des tribunes médiatiques, le philosophe Jacques Bouveresse (1940-2021) a exercé une influence majeure en France sur toute une génération de philosophes, tant par son enseignement que par son œuvre. | T39: <p>Figure historique d'<em>Austriaca</em> – dont il fut pendant plus trente-cinq ans membre du comité de rédaction, puis du comité scientifique – mais peu connu du grand public, car très éloigné des tribunes médiatiques, le philosophe Jacques Bouveresse (1940-2021) a exercé une influence majeure en France sur toute une génération de philosophes, tant par son enseignement à la Sorbonne, puis au Collège de France, que par son œuvre&nbsp;: une cinquantaine de livres et près de deux-cents articles publiés.</p> <p>Outre différentes études consacrées à sa lecture et à sa contribution à la réception de Wittgenstein, de Kraus, de Musil ou du Cercle de Vienne, ainsi qu’à sa réflexion sur la question du langage et sur la musique, le présent numéro d’hommage comporte deux textes de Bouveresse&nbsp;: un inédit sur Ludwig Boltzmann et la traduction allemande d’un chapitre du<em> Philosophe et le réel</em> susceptible d’offrir aux germanophones un premier accès à son œuvre et d’en encourager, espérons-le, la traduction en allemand, comblant ainsi une lacune lourde de conséquences, comme le confirme l’étude de sa réception dans les pays de langue allemande. Le volume se clôt, enfin, sur plusieurs témoignages de collègues et personnalités qui lui rendent hommage de manière plus personnelle (Avant-propos de Christian Bonnet, extrait).</p> | U39: <p>Avant-propos&nbsp;</p> <p>Jean-Claude MONOD&nbsp;<br /> Bouveresse et la responsabilité à l'égard du langage<br /> Pierre WAGNER<br /> Bouveresse et le Cercle de Vienne<br /> Christiane CHAUVIRÉ<br /> La Vienne de Bouveresse&nbsp;<br /> Jocelyn BENOIST<br /> Wittgenstein dans le champ de la philosophie française&nbsp;<br /> Jacques BOUVERESSE&nbsp;<br /> Ludwig Boltzmann comme penseur autrichien<br /> Gerald STIEG<br /> Jacques Bouveresse, lecteur de Karl Kraus<br /> Gerald STIEG<br /> Ein Grubenhund und seine Folgen<br /> Christian BONNET<br /> Lire Musil en philosophe<br /> Herta-Luise OTT&nbsp;<br /> Sprechen – Rede – Sprache? Anmerkungen zu<em> Le parler de la musique</em> von Jacques Bouveresse<br /> Ute WEINMANN<br /> Jacques Bouveresse, « le plus autrichien des philosophes français » dans les pays de langue allemande : histoire d'une non-réception ?<br /> Jacques BOUVERESSE<br /> <em>Philosophieren</em>, traduit par Martin Baltzer&nbsp;</p> <p><br /> <strong>Hommages et témoignages&nbsp;</strong></p> <p>Denis PODALYDÈS<br /> Bouveresse puis Jacques<br /> Catrin MISSELHORN<br /> Musik und eine kleine Giraffe. Erinnerungen an Jacques Bouveresse<br /> Sandra LAUGIER<br /> Souvenirs de jeunesse<br /> Emmanuel BOURDIEU<br /> L'autre philosophie&nbsp;<br /> Manfred FRANK<br /> <em>In memoriam</em> Jacques Bouveresse</p> <p>Notices bibliographiques<br /> Publications récentes sur l’Autriche<br /> Résumés/<em>Zusammenfassungen</em>/<em>Abstracts</em><br /> &nbsp;</p> | V39: https://www.pun-ed.fr/resources/titles/28777100297620/images/164f4bfe061c94c60871d700d953f2f5/HIGHQ/9791024018614.jpg | W39: 9791024018614.jpg | X39: 250 | Y39: 15.5 | Z39: 24 | AB39: 350 | AC39: PHI000000;PHI031000;PHI038000 | AD39: 3126 | AF39: 6 | AG39: 28777100297620 | AH39: 9791024018614 | AI39: TRUE | AJ39: TRUE | AK39: 25 | AL39: Disponible | AM39: Bonnet, Christian, B15; Weinmann, Ute, B15 | AS39: 9791024018614 | AT39: 20 | AU39: 4 | AV39: HP | BB39: 0 | BN39: BC
A40: 9791024018706 | B40: psychanalyse-et-education-9791024018706 | C40: Psychanalyse et éducation | D40: Questions à Mireille Cifali | E40: Prot, Frédérique-Marie, B16 | F40: Frédérique-Marie Prot | J40: Presses universitaires de Rouen et du Havre | L40: Penser les valeurs en éducation et en formation | N40: 2025-03-20 | O40: 1 | P40: Livre broché | Q40: BC | S40: Mireille Cifali est l'une des grandes figures des sciences de l’éducation. Elle a consacré l’entièreté de sa carrière universitaire aux « métiers de l’humain ». Son travail de recherche s’attache à définir une approche clinique en sciences de l’éducation. Le présent ouvrage paraît en hommage à la carrière et aux travaux de Mireille Cifali. | T40: <p>Mireille Cifali est l'une des grandes figures des sciences de l’éducation. Elle a consacré l’entièreté de sa carrière universitaire aux «&nbsp;métiers de l’humain&nbsp;». Son travail de recherche s’attache à définir une approche clinique en sciences de l’éducation. Historienne et psychanalyste, Mireille Cifali a occupé plusieurs fonctions au sein de la section des sciences de l’éducation de l’université de Genève, en Suisse. En tant qu’historienne, ses recherches furent d’abord de saisir comment des pédagogues se préoccupent de psychanalyse, cela dès le début du XX<sup>e</sup> siècle. Avec Daniel Hameline, elle a créé les Archives Institut Jean-Jacques Rousseau en 1984. Son goût pour le littéraire et son lien avec la construction des connaissances l’ont amenée à interroger les processus d’écriture de l’expérience. Depuis sa retraite, Mireille Cifali nous offre la poursuite de ses écrits, recueille des images, les assemble et pense les liens entre processus cliniques et processus de création.</p> <p>Le présent ouvrage paraît en hommage à la carrière et aux travaux de Mireille Cifali.</p> | U40: <p><strong>Présentation</strong><br type="_moz" /> <em>Mireille Cifali professeure</em>, Étiennette Velas<br type="_moz" /> <em>Mireille Cifali : une oeuvre</em>, Henri Louis Go</p> <p><strong>Histoire, psychanalyse, éducation</strong><br type="_moz" /> <em>L'âme enfantine et la psychanalyse, entre présent et passé</em>, Mireille CIfali<br /> <em>(Re)lire l'oeuvre de Charles Baudouin via Mireille Cifali</em>, Xavier Riondet<br /> <em>Peut-on parler d'une "doctrine Cifali" ?</em> Daniel Hameline<br /> Éthique, psychanalyse, éduction<br /> <em>Éthique psychanalytique dans le champ de l'éducation</em>, Mireille Cifali<br /> <em>La psychanalyse et le philosophe</em>, Eirick Prairat<br /> <em>L'éthique du professeur : le désir de transmettre des savoirs d'humanité</em>, Frédérique-Marie Prot<br /> <em>Éloge d'une tension élastique ou les variations du sujet en mouvement</em>, Jean-François Ferbos</p> <p><strong>Clinique, psychanalyse, éducation</strong><br /> <em>Démarches cliniques</em>, Mireille Cifali<br /> <em>L'éducation est un humanisme : pour une approche clinique créative</em>, Nadine Demogeot<br /> <em>Une éducation éclairée par la psychanalyse</em>, Norbert Bon</p> <p><strong>Pédagogie institutionnelle et psychanalyse</strong><br /> <em>Fernand Oury, une écriture qui résiste</em>, Mireille Cifali et Martine Janvier Pernet<br /> <em>Mireille Cifali, l'écriture clinique et la pédagogie institutionnelle</em>, Bruno Robbes<br /> <em>Mireille Cifali, l'ombre portée d'une eau vive</em>, Jacques Pain</p> <p><strong>Psychanalyse et formation</strong><br /> <em>Éthique clinique en formation</em>, Mireille Cifali<br /> <em>Faire bouger, mettre en "je"</em>, Bérengère Kolly<br /> <em>Performance et effacement de la subjectivité en formation</em>, Long Pham Quang<br /> <em>Démarches cliniques, institution(s) et chercheur-apprenant</em>, Jean-Michel Perez</p> <p><strong>Écriture clinique et formation</strong><br /> <em>Psychanalyse et écriture d'une histoire chez Michel de Certeau</em>, Mireille Cifali<br /> <em>La fiction n'est pas contraire à la science</em>, Bessa Myftiu<br /> <em>Une écriture, comme écart</em>, Thomas Périlleux, dialogue avec Mireille Cifali</p> <p><strong>Questions à Mireille Cifali et réponses</strong><br /> <em>Mireille Cifali : l'incertitude comme vertu</em>, Philippe Meirieu</p> <p><em><strong>Postface</strong></em>, Daniel Hameline</p> <p><strong>Publications de Mireille Cifali</strong></p> <p><strong>Les auteur·e·s</strong></p> <p>&nbsp;</p> | V40: https://www.pun-ed.fr/resources/titles/28777100251620/images/b974006f61bd5a3f95e3e9530a579d14/HIGHQ/9791024018706.jpg | W40: 9791024018706.jpg | X40: 348 | Y40: 15.5 | Z40: 22 | AA40: 2.5 | AB40: 495 | AC40: EDU000000;PSY000000 | AE40: J | AF40: 5 | AG40: 28777100251620 | AI40: TRUE | AJ40: TRUE | AK40: 18 | AL40: Disponible | AM40: Prot, Frédérique-Marie, B16 | AR40: https://books.openedition.org/purh/23656 | AS40: 9791024018706 | AT40: 20 | AU40: 4 | AV40: J;JM;JN | BB40: 0 | BD40: J | BE40: J | BF40: J | BN40: BC
A41: 9791024018188 | B41: former-les-therapeutes-par-les-interactions-9791024018188 | C41: Former les thérapeutes par les interactions | D41: Au cœur de la professionnalité des superviseurs | E41: Alexandra Nguyen | F41: Alexandra Nguyen | J41: Presses universitaires de Rouen et du Havre | L41: La professionnalisation, entre travail et formation | N41: 2025-01-23 | O41: 1 | P41: Livre broché | Q41: BC | S41: Former les thérapeutes par la supervision requiert des compétences d'interaction dans la gestion des rapports de pouvoir, d’expertise et d’affectivité. L’ouvrage présente les actions de supervision nécessaires pour un espace interactionnel formateur. Les compétences révélées offrent des perspectives pour les professions de la relation à autrui. | T41: <p>La supervision est un ingrédient essentiel de la formation à la relation thérapeutique. L'analyse des interactions entre superviseurs et thérapeutes révèle les enjeux relationnels, émotionnels, d’expertise et de pouvoir, ainsi qu’une véritable mise en abyme de la relation clinique dans la relation de supervision. Les trajectoires de l’affectivité observées montrent les actions de supervision qui conduisent progressivement le thérapeute vers une auto-réflexivité orientée vers sa posture professionnelle. L’ouvrage présente les éléments de la professionnalité du superviseur et ouvre sur les compétences d’interaction des professions dont le cœur des pratiques se situe dans la relation à autrui.</p> | U41: <p><em>Remerciements</em></p> <p><em>Préface</em></p> <p><em>Introduction</em><br /> &nbsp;</p> <p>Chapitre&nbsp;1.&nbsp;Les pratiques de supervision selon une perspective interactionnelle</p> <p>Trajectoires topicales</p> <p>Structures et organisation des séances de supervision</p> <p>Cinq activités de supervision</p> <p>Simulations discursives dans la supervision</p> <p><br /> Chapitre&nbsp;2.&nbsp;Emboîtement des cadres interactionnels</p> <p>Emboîtement du cadre interactionnel clinique</p> <p>Emboîtement du cadre interactionnel privé</p> <p>Emboîtement du cadre interactionnel de la supervision</p> <p>Emboîtement enchevêtré des cadres interactionnels</p> <p><br /> Chapitre&nbsp;3.&nbsp;La dynamique des places dans la supervision</p> <p>Trois ordres de l'interaction en constante négociation</p> <p>Rapports épistémiques et bascules de places</p> <p>Autorités déontiques et dynamiques d'influence</p> <p>Rôles et places dans la gestion de l’affectivité</p> <p>Ressources interactionnelles pour agir sur les positionnements interactionnels</p> <p><br /> Chapitre&nbsp;4. Les trajectoires de l’affectivité en supervision</p> <p>Émotions et interaction</p> <p>Centralité des émotions dans les discours en supervision</p> <p>Implication&nbsp;: le signalement d’une affectivité augmentée</p> <p>Actions affiliatives et désaffiliatives du superviseur</p> <p>Gestion collaborative de l’affectivité et discours réflexif du thérapeute</p> <p><br /> Chapitre 5.&nbsp;La professionnalité du superviseur</p> <p>Un leadership collaboratif dans la conduite des séances</p> <p>La conduite des trajectoires affectives et cognitives</p> <p>L’organisation d’un environnement expérientiel formateur</p> <p>Former aux compétences de supervision</p> <p><em>Conclusion</em></p> <p><em>Postface</em></p> <p><em>Références bibliographiques</em></p> | V41: https://www.pun-ed.fr/resources/titles/28777100375770/images/90968598e1b1d4ae4838f0ad8e39bf11/HIGHQ/9791024018188.jpg | W41: 9791024018188.jpg | X41: 392 | Y41: 15.5 | Z41: 22 | AA41: 1.9 | AB41: 552 | AC41: EDU000000;EDU012000;EDU026000;EDU049000 | AD41: 3080 | AF41: 6 | AG41: 28777100375770 | AH41: 9791024018188 | AI41: TRUE | AJ41: TRUE | AK41: 25 | AL41: Disponible | AM41: Nguyen, Alexandra, A01 | AN41: Alexandra Nguyen | AS41: 9791024018188 | AT41: 20 | AU41: 4 | AV41: J;JM;JN | BB41: 0 | BN41: BC
A42: 9791024018218 | B42: les-medailles-de-louis-xiv-et-leur-livre-9791024018218 | C42: Les médailles de Louis XIV et leur livre | D42: Volume 3 | E42: Loskoutoff, Yvan, B15 | F42: Yvan Loskoutoff | J42: Presses universitaires de Rouen et du Havre | N42: 2025-01-23 | O42: 1 | P42: Livre broché | Q42: BC | S42: Ce 3e volume consacré à l'histoire métallique de Louis XIV, médailles et livres, analyse dans un premier temps les sujets traités, il examine ensuite ses antécédents puis sa postérité, enfin, des varia la confrontent au succès des sciences naturelles, la comparent aux albums de propagande royale, mesurent sa présence dans la presse contemporaine. | T42: <p>Ce nouveau volume consacré à l'histoire métallique de Louis XIV, médailles et livres, réunit des articles issus des troisième et quatrième colloques internationaux tenus à la Monnaie de Paris, en juin 2019 et en octobre 2021. On y examine d’abord les sujets des médailles, séparément (la régence d’Anne d’Autriche, l’accueil de Jacques II d’Angleterre exilé, l’école de Saint-Cyr) ou en groupe (le canal du Midi, les entrées royales, les ambassades). On y aborde ensuite les antécédents (Moyen Âge ou XVII<sup>e</sup> siècle) puis la postérité dans l’Angleterre du règne d’Anne (1702-1714), dans la Hollande du XVIII<sup>e</sup> siècle ou sous l’Empire napoléonien. Enfin, des <em>varia</em> permettent de confronter l’histoire métallique au succès des sciences naturelles, de la comparer aux albums de propagande royale, de mesurer sa présence dans la presse<em>.</em></p> | U42: <p><em>Introduction</em></p><p style="text-align: center;">Première partie&nbsp;: Thématiques</p><p>Yvan Loskoutoff, <em>La médaille de «&nbsp;La régence de la Reyne Mère&nbsp;»</em></p><p>Mark Jones, <em>La réception du roi d'Angleterre en France, 1689</em></p><p>Marie-Claude Canova-Green, <em>La médaille de Saint-Cyr ou la piété du roi</em></p><p>William Eisler, <em>L'histoire du canal du Midi réécrite dans le livre des médailles de Louis XIV</em></p><p>Marie-Claude Canova-Green, <em>D'une reine l'autre. Les entrées dans Paris de Christine de Suède et de Marie-Thérèse d'Autriche</em></p><p>Daniela del Pesco, <em>Les ambassades</em></p><p style="text-align: center;">Deuxième partie&nbsp;: Antécédents</p><p>Yvan Loskoutoff, <em>Les monnaies romaines aux sources des médailles de Louis XIV&nbsp;: les projets&nbsp; refusés</em></p><p>Pierre Couhault, <em>Le Moyen Âge chez Apollon&nbsp;? Les impuissances de l’antique</em></p><p>Antoine Gallay, <em>Le projet inachevé d’une </em>Histoire métallique des rois de France <em>(1682-1688)&nbsp;: un modèle pour les </em>Médailles sur les principaux événements du règne de Louis le Grand&nbsp;<em>?</em></p><p>Léa Gagnon, <em>L’histoire métallique de Louis XIV et les tapisseries du roi</em></p><p style="text-align: center;">Troisième partie&nbsp;: Postérité</p><p>Thomas Cocano, <em>Les médailles de la reine Anne et celles de Louis XIV&nbsp;: des proximités iconographiques au cours de la guerre de Succession d’Espagne (1702-1713)&nbsp;?</em></p><p>Mark Hengerer, <em>Les </em>Annales de la monarchie française <em>de Henri-Philippe Limiers (1724-1736)&nbsp;: un livre des médailles de Louis&nbsp;XIV</em></p><p>Charlotte Rousset, <em>Le portrait métallique de Louis XV à l’avers des médailles uniformes frappées pour son règne</em></p><p>William Eisler, <em>L’histoire métallique de Napoléon I<sup>er </sup>et l’impact des médailles du Roi-Soleil</em></p><p>Dominique Hollard, <em>La médaille napoléonienne&nbsp;: de l’Empire romain à l’Empire français en passant, ou non, par l’histoire métallique de Louis XIV</em></p><p style="text-align: center;">Quatrième partie&nbsp;: <em>Varia</em></p><p>Inès Villela-Petit, <em>Histoire métallique et histoire naturelle</em></p><p>Bernard Teyssandier, <em>Les </em>Médailles sur les principaux événements du règne de Louis le Grand&nbsp;<em>: un livre monument&nbsp;?</em></p><p>William Eisler, <em>La médaille et le </em>Mercure galant&nbsp;<em>: l’histoire métallique du roi selon Jean Donneau de Vizé (1638-1710)</em></p><p>&nbsp;</p><p><em>Postface</em></p><p><em>Bibliographie</em></p><p><em>Table des figures</em></p> | V42: https://www.pun-ed.fr/resources/titles/28777100662040/images/45e7f4b7b70aea2ca2053b78bf65fd2c/HIGHQ/9791024018218.jpg | W42: 9791024018218.jpg | X42: 444 | Y42: 15.5 | Z42: 24 | AA42: 2.8 | AB42: 750 | AC42: HIS000000;ART000000;ART037000;HIS037040;HIS037050 | AE42: NH | AF42: 1 | AG42: 28777100662040 | AI42: TRUE | AJ42: TRUE | AK42: 27 | AL42: Disponible | AM42: Loskoutoff, Yvan, B15 | AS42: 9791024018218 | AT42: 20 | AU42: 4 | AV42: HB;A;HBJD | BB42: 0 | BD42: NH | BE42: NH | BF42: NH | BN42: BC
A43: 9791024018126 | B43: penser-l-education-n-54-9791024018126 | C43: Penser l'éducation, n° 54 | D43: La philosophie politique de l'éducation, à l'épreuve des crises démocratiques contemporaines | E43: Chauvigné, Céline, B15; Roelens, Camille, B15 | F43: Céline Chauvigné | J43: Presses universitaires de Rouen et du Havre | L43: Penser l'éducation | M43: 54 | N43: 45657 | O43: 1 | P43: Livre broché | Q43: BC | S43: La revue s'inscrit dans un champ qui croise la philosophie de l'éducation et l'histoire des idées pédagogiques. Le thème de ce numéro est : La philosophie politique de l'éducation, à l’épreuve des crises démocratiques contemporaines. Problématiques et mises en perspectives | T43: <p>La revue<em> Penser l'éducation</em> est une revue scientifique internationale à comité de lecture, adossée au Centre interdisciplinaire de recherches normand en éducation et en formation (CIRNEF), laboratoire de l'université de Rouen.<br /> Cette revue, qui existe depuis 1996, s'inscrit dans le champ spécifique qui croise la philosophie de l'éducation et l'histoire des idées pédagogiques.<br /> Traditionnellement, ces deux aspects sont reliés et relèvent de la philosophie de l'éducation. <em>Penser l'éducation</em> n'est pas un titre anodin, il porte une injonction et une promesse: en ces temps de mutation, il s'agit de (re)penser, à nouveaux frais, l'éducation, dans ses principes, ses finalités, ses valeurs, ses pratiques et leurs conséquences.<br /> Deux numéros sont publiés chaque année.La taille des articles n'est ni formatée ni normalisée, sans autre justification que celle d'un processus d'évaluation rigoureux.</p> <p>Ce n° 54 est thématique&nbsp;: "La philosophie politique de l’éducation, à l’épreuve des crises démocratiques contemporaines. Problématiques et mises en perspectives". Les mots-clés sont&nbsp;: citoyenneté, démocratie, éducation au politique, éduquer des citoyens, philosophie politique, technocratie, populisme, questions socialement vives, engagement, raison publique, enseignement des faits religieux, sécularisation, hubris, basculement, complexité, considération, convivance, théorie critique, fonds du MUNAÉ.</p> | U43: <p>Introduction</p> <p>Philippe Foray<br /> <em>Que signifie&nbsp;: «&nbsp;éduquer des citoyens&nbsp;»&nbsp;?</em></p> <p>Michel Fabre<br /> <em>Vous avez dit l'éducation </em>au <em>politique&nbsp;?</em></p> <p>Céline Chauvigné<br /> <em>Les questions socialement vives&nbsp;: vers un renouveau dans une formation du citoyen en milieu scolaire&nbsp;?</em></p> <p>Anne-Claire Husser<br /> <em>L'enseignement laïque des faits religieux peut-il contribuer à la formation politique&nbsp;?</em></p> <p>Marco Barroca-Paccard et Yves Debernardi<br /> <em>Éviter la tyrannie des experts&nbsp;: réflexion sur l'intérêt des sciences citoyennes dans le cadre des enseignements de sciences et de technologies à l’école</em></p> <p>François Prouteau et Nathanaël Wallenhorst<br /> <em>Une pensée convivialiste d’une éducation politique en Anthropocène</em></p> <p><strong>Recension</strong><br /> <em>Cécile Redondo,</em> Figures inspirantes pour l’éducation&nbsp;: Contours épistémologiques, approches expérientielles <em>(Rémi Casanova et Camille Roelens dir., L’Harmattan, 2022)</em></p> <p><strong>Les fonds du MUNAÉ</strong><br /> S’habiller pour l’école<em>, une exposition au MUNAÉ</em><em> </em></p> | V43: https://www.pun-ed.fr/resources/titles/28777100077350/images/37f2fc94430a30d7dba690d94d7e1223/HIGHQ/9791024018126.jpg | W43: 9791024018126.jpg | X43: 140 | Y43: 15.5 | Z43: 24 | AB43: 230 | AC43: EDU000000;EDU040000 | AD43: 3161 | AF43: 6 | AG43: 28777100077350 | AH43: 9791024018126 | AI43: TRUE | AJ43: TRUE | AK43: 26 | AL43: Disponible | AM43: Chauvigné, Céline, B15; Roelens, Camille, B15 | AS43: 9791024018126 | AT43: 20 | AU43: 4 | AV43: JNA;JN;JNB | BB43: 0 | BN43: BC
A44: 9791024017679 | B44: co-intelligence-des-contraires-9791024017679 | C44: Co-intelligence des contraires | D44: Duchamp des possibles | E44: Castanet, Pierre Albert, B15 | F44: Pierre Albert Castanet | J44: Presses universitaires de Rouen et du Havre | N44: 2024-12-05 | O44: 1 | P44: Livre broché | Q44: BC | S44: "Co-intelligence des contraires. Duchamp des possibles" traite du grand Œuvre de Marcel Duchamp (1887-1968). Embrassant les domaines de l'artistique et de la poétique… des arts visuels et même de la musique… l’ouvrage porte sur de riches notions touchant autant au muséal qu’au conceptuel, autant à l’objet technique qu’à l’humour circonstancié. | T44: <p></p> <p><em>Co-intelligence des contraires. Duchamp des possibles</em> traite du grand Œuvre du génial anartiste normand Marcel Duchamp (1887-1968), <em>ready-maker</em> de renommée internationale. Présenté en trois grandes parties («&nbsp;Concepts&nbsp;», «&nbsp;Percepts&nbsp;» et «&nbsp;Affects&nbsp;»), l'ouvrage embrasse les domaines de l’artistique et de la poétique, de l’esthétique et de la philosophie, de l’épistémologie et de la poïétique, des jeux de mots et des arts visuels, de l’érotisme et même de la musique… Ainsi, écrites par les meilleurs spécialistes du moment, les diverses communications magistrales portent sur de riches notions touchant autant au muséal qu’au conceptuel, autant à l’objet technique qu’à l’humour circonstancié.</p> | U44: <p><em>Avant-propos</em></p><p><em>Remerciements</em></p><p><em>Introduction</em></p><p>Prélude, <em>Mode d'emploi du temps</em>, Max Schoendorff</p><p>I.&nbsp;Concepts</p><p><em>Marcel Duchamp et l'individuation des objets techniques</em>, John Didier</p><p><em>Les «&nbsp;Stoppages&nbsp;» des Notes de la Boîte en suédine verte</em>, Françoise Le Penven</p><p><em>«&nbsp;Gallery&nbsp;1759&nbsp;: Duchamp, Étant donnés, et le Philadelphia Museum of Art&nbsp;» d'après «&nbsp;A Conversation with Marcel Duchamp&nbsp;</em>» (1955),<em> Le Grand Verre</em>, Matthew Affron</p><p>II.&nbsp;Percepts</p><p><em>Saisir l'inframince (lecture croisée de Marcel Duchamp et Roland Barthes)</em>, Quentin Jouret</p><p><em>La découverte de la vision de l'esprit&nbsp;: Marcel Duchamp à Munich en 1912</em>, Herbert Molderings (trad. Jean Torrent)</p><p><em>Marcel Duchamp, «&nbsp;prophète en son pays&nbsp;»&nbsp;? Histoire d'une exposition oubliée (Rouen/Paris, 1967)</em>, Séverine Gossart</p><p><em>Duchamp, Man Ray &amp; Co.&nbsp;: réception et filiation (?) en Grande-Bretagne</em>, Antoine Capet</p><p>III.&nbsp;Affects</p><p><em>Duchamp voyageur</em>, Dawn Adès</p><p><em>Humour, physique-amusante et science de l'imaginaire dans la musique de Marcel Duchamp</em>, Sophie Stévance</p><p><em>Érotisme et jeux de mots</em>, Marc Décimo</p><p>Postlude, <em>Monsieur Tout-le-monde, l'Artiste et l'Université</em>, Pierre Albert Castanet</p><p><em>Index des noms propres</em></p><p><em>Table des figures et des crédits</em></p><p><em>Les auteur·e·s</em></p> | V44: https://www.pun-ed.fr/resources/titles/28777100623200/images/db261d4f615f0e982983be499e57ccda/HIGHQ/9791024017679.jpg | W44: 9791024017679.jpg | X44: 272 | Y44: 17 | Z44: 23 | AA44: 1.15 | AB44: 520 | AC44: ART000000;ART008000;ART060000;ART023000 | AD44: 3667 | AE44: A | AF44: 6 | AG44: 28777100623200 | AI44: TRUE | AJ44: TRUE | AK44: 24 | AL44: Disponible | AM44: Castanet, Pierre Albert, B15 | AS44: 9791024017679 | AT44: 20 | AU44: 4 | AV44: A;AFK | BB44: 0 | BD44: A | BE44: A | BF44: A | BN44: BC
A45: 9791024017952 | B45: les-dockers-du-havre-de-la-revolution-a-nos-jours-9791024017952 | C45: Les dockers du Havre, de la Révolution à nos jours | E45: John Barzman | F45: John Barzman | J45: Presses universitaires de Rouen et du Havre | N45: 2024-12-05 | P45: Livre broché | Q45: BC | S45: Corporatistes, bagarreurs, trafiquants, modèles de solidarité, les clichés à propos des dockers abondent. En plus de deux siècles, à travers les réorganisations du port du Havre et du trafic maritime, et malgré des épisodes de répression forte, ils ont su construire un système de valeurs solidaires et développer une activité syndicale peu commune. | T45: <p>Les dockers du Havre ont longtemps été victimes d'une légende noire. Au cours des trente dernières années, les médias n’en ont parlé que pour laisser entendre que leurs grèves menaçaient l’avenir de la ville, les accuser de népotisme ou insinuer une accointance avec des trafiquants. Ces critiques, généralement sans fondement, n’en ont pas moins détourné l’attention du phénomène remarquable qu’incarne leur organisation. Héritière de traditions qui remontent à la Révolution française, la corporation des dockers du Havre a su unifier les travailleurs du port, puis s’adapter aux transformations des bassins, des machines, des navires et des conteneurs.</p> <p>Bien que le terme «&nbsp;docker&nbsp;» ne s’impose qu’à partir de la construction des docks au milieu du XIXe siècle, les anciens métiers contrôlés par la municipalité (brouettiers, voiliers, porteurs et mesureurs) ont graduellement partagé l’emploi avec les hommes embauchés à la tâche par les capitaines,<br /> négociants, employeurs de main-d’oeuvre, puis par la Compagnie des docks et entrepôts du Havre. Une identité collective de «&nbsp;travailleurs habituels du port&nbsp;» s’est affirmée au travers d’exigences communes, cortèges, pétitions, et, face à la mécanisation – notamment les premières grues –,<br /> par des grèves et syndicats. Dès lors, les valeurs et les pratiques «&nbsp;dockers&nbsp;» liées au travail s’imbriquèrent étroitement avec le syndicat, sans pour autant se confondre. De la grève victorieuse de 1928 à la conteneurisation des années 1980, la volonté d’unité dans une seule organisation, au nom de la défense des intérêts de la corporation, s’est manifestée avec constance. C’est cette longue histoire, pleine de rebondissements et de personnalités remarquables, que raconte cet ouvrage.</p> | U45: <p>Préface de Marcel Van der Linden</p><p>Introduction</p><p>Chapitre 1 - Qui sont les ancêtres des dockers&nbsp;? La manutention portuaire dans la première moitié du XIXe siècle</p><p>Chapitre 2 - Le modèle de la manufactur et ses adversaires (1856-1885)</p><p>Chapitre 3 - Cargos, grues et statistiques. De la fin des années 1880 à 1928</p><p>Chapitre 4 - L'ère de Jules Durand (1885-1928)</p><p>Chapitre 5 - Docker = Syndiqué. (1928-1965)</p><p>Chapitre 6 - Mieux payés, moins nombreux. (1965-1993)</p><p>Chapitre 7 - Rebond (1993-2020)</p><p>Conclusion</p><p>Annexe</p><p>Bibliographie</p><p>Table des figures et tableaux</p> | V45: https://www.pun-ed.fr/resources/titles/28777100625000/images/982025df3dc7f9eae503a74980c29713/THUMBNAIL/9791024017952.jpg | W45: 9791024017952.jpg | X45: 515 | Y45: 15.5 | Z45: 24 | AA45: 3.25 | AB45: 880 | AC45: HIS037070;HIS013000;TRA006000 | AD45: 3377 | AE45: NHTM | AF45: 6 | AG45: 28777100625000 | AI45: TRUE | AJ45: TRUE | AK45: 29 | AL45: Disponible | AM45: Barzman, John, A01 | AN45: John Barzman | AS45: 9791024017952 | AT45: 20 | AU45: 4 | AV45: HBTM;HBJD;HBTK | BB45: 0 | BC45: 1 | BD45: NHTM | BE45: NHTM | BF45: NHTM | BN45: BC
A46: 9791024018270 | B46: austriaca-n-95-9791024018270 | C46: Austriaca, n° 95 | D46: L'occupation française en Autriche (1945-1955) | E46: Ducange, Jean-Numa, B15; Vincent, Marie-Bénédicte, B15 | F46: Jean-Numa Ducange | J46: Presses universitaires de Rouen et du Havre | L46: Austriaca | M46: 95 | N46: 2024-12-05 | O46: 1 | P46: Livre broché | Q46: BC | S46: Ce numéro d'Austriaca regroupe sans prétention à l’exhaustivité des études singulières et originales sur un sujet fort peu traité par l’historiographie, notamment celle de langue française : l’occupation française en Autriche de 1945 à 1955. | T46: <p>Le présent dossier regroupe des contributions de chercheurs de différentes générations, montrant l'évolution de l’historiographie de ces quarante dernières années. On ne compte plus les histoires du nazisme et des principaux acteurs de cette idéologie politique, mais l’Autriche est le plus souvent évoquée à la marge, ou en faisant fi de ses singularités. Et même si une inflexion récente est à souligner, la même remarque s’applique à la dénazification et à la période d’occupation. Un des éléments structurants de ce dossier est de tenir compte de ce déséquilibre <em>de facto</em> entre l’Allemagne et l’Autriche – un déséquilibre classique pour les historiens de l’Autriche – en cherchant à dresser les points communs et particularités entre les deux pays germanophones. Si l’on compare le nombre d’études consacrées à la zone française d’occupation en Autriche par rapport aux autres zones d’occupation du pays, le déséquilibre est flagrant.</p><p>L’ensemble entend être également une incitation à poursuivre des études spécifiques quand d’autres invitent davantage à une réflexion historiographique plus globale&nbsp;: dans quelle mesure l’occupation a-t-elle conditionné des éléments structurels de la reconstitution du pays qui s’impose ensuite pendant quarante ans comme – une différence majeure avec l’Allemagne – le lieu de la «&nbsp;neutralité active&nbsp;»&nbsp;?</p> <h2>Prix littéraire</h2><p><b><em>Les dockers du Havre, de la Révolution à nos jours</em> a obtenu le prix Pellecat 2025 de l'Académie des arts, sciences et belles-lettres de Rouen.<b></p><h2>Ils en ont parlé</h2><p> Michel Pigenet, « John Barzman, Les dockers du Havre, de la Révolution à nos jours », Le Mouvement social, n° 287 (avril-juin 2024)<br />Yannick Marec, « John Barzman, Les Dockers du Havre, de la Révolution à nos jours », <a href=https://doi.org/10.4000/163bu>Cahiers d’histoire, revue d’histoire critique n° 165, 2026</a><br />Lex Heerma van Voss, « John Barzman, Les dockers du Havre, de la révolution à nos jours (PURH, 2024), <em>Francia- recensio</em> 2026<br />Christian Chevandier, « John Barzman, Les dockers du Havre, de la révolution à nos jours (PURH, 2024) », <a href=https://doi.org/10.3917/vin.169.0179>revue d'histoire, n° 69</a><br />Sylvain Boulouque, « Les gars du port - Une étude du bastion havrais », <a href=https://www.lours.org/lours-542-juillet-aout-2025-est-sorti/>OURS (Office universitaire de recherche socialiste)</a><br />Danielle Tartakowsky, « Tenir jusqu’au bout de la journée », <a href=https://www.en-attendant-nadeau.fr/2025/03/04/tenir-jusquau-bout-de-la-journee-travail/>En attendant Nadeau n° 216</a><br /><p> | U46: <p><em>Avant-propos </em></p> <p>&nbsp;</p> <p>Marie-Bénédicte Vincent</p> <p><em>L'occupation française de l'Autriche (1945-1955) : état des lieux historiographique</em></p> <p>&nbsp;</p> <p>Lauriane Bustanji, avec Marie-Laure Rebora, Asya Kurtuldu, Marie Birken, Louise Guerot, Marguertie De Cibeins</p> <p><em>Les archives de l'occupation française en Autriche à La Courneuve. Présentation et études de cas</em></p> <p>&nbsp;</p> <p>Jean-Numa Ducange</p> <p><em>L</em><em>'</em><em>occupation et la dénazification de l</em><em>’</em><em>Autriche dans la revue française </em>Austriaca</p> <p>&nbsp;</p> <p>Julia Maspero</p> <p><em>La politique française à l’égard des personnes déplacées a-t-elle été identique en Allemagne et en Autriche après la seconde guerre mondiale&nbsp;? La coopération entre la France et l'UNRRA comme outil d’analyse (1945-1947)</em></p> <p>&nbsp;</p> <p>Teresa Hämmerle</p> <p><em>Verfolgung und Verurteilung der Verbrecher des Arbeitserziehungslagers Reichenau durch amerikanische, französische, österreichische und deutsche Behörden</em></p> <p>&nbsp;</p> <p>Roman Pfefferle</p> <p><em>Geistige Erneuerung oder personelle Kontinuität? </em><em>Entnazifizierung und Rehabilitierung der Professorenschaft an der Universität Wien nach 1945</em></p> <p>&nbsp;</p> <p>Herta Luise Ott</p> <p><em>Un travail critique&nbsp;inhibé dans les milieux culturels autrichiens après 1945 : refoulements, atermoiements et force des choses</em></p> <p>&nbsp;</p> <p>Klaus Eisterer</p> <p><em>Kriegsende in Österreich: Geschichte und Erinnerung an die Besatzung durch Frankreich (19451955). Ein Essay</em></p> <p>&nbsp;</p> <p><strong>Des idées et des faits</strong></p> <p>Paul Pasteur</p> <p>«&nbsp;C’est avec plaisir que j’égratigne la laque rouge-blanc-rouge&nbsp;», Elizabeth T. Spira 1942-2019</p> <p>&nbsp;</p> <p>Charles Bolduc</p> <p>Le Dostoïevski de Freud : une étude de cas</p> <p>&nbsp;</p> <p><em>Notices bibliographiques</em></p> <p><em>Publications récentes sur l’Autriche</em></p> <p><em>Résumés</em>/Zusammenfassungen/Abstracts</p> | V46: https://www.pun-ed.fr/resources/titles/28777100648850/images/90c34175923a36ab7a5de4b981c1972f/THUMBNAIL/9791024018270.jpg | W46: 9791024018270.jpg | X46: 234 | Y46: 15.5 | Z46: 24 | AA46: 1.3 | AB46: 450 | AC46: HIS000000;HIS010000;HIS040000;HIS013000 | AD46: 3377 | AE46: NHD | AF46: 5 | AG46: 28777100648850 | AI46: TRUE | AJ46: TRUE | AK46: 25 | AL46: Disponible | AM46: Ducange, Jean-Numa, B15; Vincent, Marie-Bénédicte, B15 | AS46: 9791024018270 | AT46: 20 | AU46: 4 | AV46: H;HB;HBJD;HBL;HBLW | BB46: 0 | BD46: NHD | BE46: NHD | BF46: NHD | BN46: BC
A47: 9791024018249 | B47: la-vacillante-lumiere-de-la-raison-9791024018249 | C47: La vacillante lumière de la raison | D47: Lire De la littérature de Germaine de Staël | E47: Blandine Poirier | F47: Blandine Poirier | J47: Presses universitaires de Rouen et du Havre | L47: Cours | N47: 2024-11-14 | O47: 1 | P47: Livre broché | Q47: BC | S47: En 1800, Staël fait paraître De la littérature, réflexion sur les liens entre la littérature et les « institutions sociales ». Il s'agit pour elle de montrer ce que pourrait être une littérature en régime républicain. La présente étude se propose de guider le lecteur pour mieux appréhender les différentes facettes du premier grand essai staëlie | T47: <p>En 1800, Staël fait paraître <em>De la littérature</em>. L'ouvrage se veut une réflexion sur les rapports entre la littérature et les «&nbsp;institutions sociales&nbsp;» (lois, mœurs, religion) pour comprendre l’histoire des formes littéraires et le progrès des idées. Empruntant à Montesquieu et à Condorcet, il s’agit pour l’autrice de réfléchir à ce que pourrait être une littérature en régime républicain, spécifique au cas français. Mais la conception d’une humanité toujours en progrès est-elle absolument tenable&nbsp;? N’existe-t-il pas des obstacles puissants à une telle évolution&nbsp;? La présente étude se propose de guider le lecteur pour mieux appréhender les différentes facettes du premier grand essai staëlien.En 1800, Staël fait paraître <em>De la littérature</em>. L’ouvrage se veut une réflexion sur les rapports entre la littérature et les «&nbsp;institutions sociales&nbsp;» (lois, mœurs, religion) pour comprendre l’histoire des formes littéraires et le progrès des idées. Empruntant à Montesquieu et à Condorcet, il s’agit pour l’autrice de réfléchir à ce que pourrait être une littérature en régime républicain, spécifique au cas français. Mais la conception d’une humanité toujours en progrès est-elle absolument tenable&nbsp;? N’existe-t-il pas des obstacles puissants à une telle évolution&nbsp;? La présente étude se propose de guider le lecteur pour mieux appréhender les différentes facettes du premier grand essai staëlien.</p> | U47: <p>Introduction</p> <p>&nbsp;</p> <p>Chapitre 1&nbsp;: Le moment 1800</p> <p>Chapitre 2&nbsp;: « Le rapport qui existait entre la littérature et les institutions de chaque siècle et de chaque pays »</p> <p>Chapitre 3&nbsp;: Le cas français, de l'Ancien Régime à la République</p> <p>Chapitre 4&nbsp;: Défendre les Lumières, malgré tout</p> <p>Conclusion&nbsp;: Liberté, liberté chérie</p> <p>Anthologie de textes critiques</p> <p>Annexes</p> <p>Bibliographie</p> | V47: https://www.pun-ed.fr/resources/titles/28777100014210/images/5fe8fdc79ce292c39c5f209d734b7206/HIGHQ/9791024018249.jpg | W47: 9791024018249.jpg | X47: 154 | Y47: 15 | Z47: 20.5 | AA47: 1.1 | AB47: 200 | AC47: LIT024030 | AD47: 3439 | AF47: 6 | AG47: 28777100014210 | AI47: TRUE | AJ47: TRUE | AK47: 15 | AL47: Disponible | AM47: Poirier, Blandine, A01 | AN47: Blandine Poirier | AR47: https://books.openedition.org/purh/21297 | AS47: 9791024018249 | AT47: 20 | AU47: 4 | AV47: DS | BB47: 0 | BC47: 1 | BN47: BC
A48: 9791024018256 | B48: la-desillusion-comique-9791024018256 | C48: La désillusion comique | D48: Étude de La Place Royale, du Menteur et de La Suite du Menteur de Pierre Corneille | E48: Yohann Deguin | F48: Yohann Deguin | J48: Presses universitaires de Rouen et du Havre | L48: Cours | N48: 2024-11-14 | O48: 1 | P48: Livre broché | Q48: BC | T48: <p>Le présent ouvrage propose une étude de trois comédies de Pierre Corneille (1606-1684)&nbsp;: <em>La Place royale </em>(1634), <em>Le Menteur</em> (1643) et <em>La Suite du Menteur </em>(1644).<br /> Il s'agit d'offrir au lecteur une introduction à la comédie du début du XVII<sup>e</sup> siècle, c'est-à-dire à la comédie avant Molière. Il s'agit aussi de voir sous un autre jour un dramaturge surtout connu pour son œuvre tragique ou tragi-comique (<em>Le Cid</em>, <em>Cinna</em>, etc.), mais qui consacra en vérité la première partie de sa longue carrière (1629-1674) à renouveler en profondeur et avec succès le théâtre comique, mettant en scène les amours et les désamours de la jeunesse citadine de son temps. L'étude est suivie d'une anthologie critique et d'une bibliographie.<br /> Disponible en format broché, ou accessible gratuitement en ligne via <a href="https://books.openedition.org/purh/21296?lang=fr" style="color: lightblue; text-decoration: underline;" target="_blank"> openedition </a>.</p> | U48: <p><em>Introduction</em></p> <p><em>Préambule</em></p> <p>Corneille et la comédie dans la première moitié du XVII<sup>e</sup>&nbsp;siècle</p> <p>Le mauvais genre de Corneille&nbsp;: enquête sur la comédie cornélienne</p> <p>Chapitre 1. Pourquoi Corneille est-il original ? Quelques éléments de dramaturgie</p> <p style="margin-left: 40px;">Jusqu'à <em>La Place Royale</em></p> <p style="margin-left: 40px;"><em>La Place Royale ou L'Amoureux extravagant</em></p> <p style="margin-left: 40px;"><em>Le Menteur</em></p> <p style="margin-left: 40px;"><em>La Suite du Menteur</em></p> <p>Chapitre 2. Les genres de la comédie</p> <p style="margin-left: 40px;">De la pastorale à la <em>comedia</em> ou un aller et retour</p> <p style="margin-left: 40px;">La comédie, « Un pays de romans » (<em>Le Menteur</em>, v. 552) ?</p> <p>Chapitre 3. Corneille quasi comique : le risque du tragique</p> <p style="margin-left: 40px;">« Tout change, et de la joie on passe à la tristesse » (<em>La Suite du Menteur</em>, <em>op. cit</em>., p. 301)</p> <p style="margin-left: 40px;">« Aux plus grands déplaisirs succède l'allégresse » (<em>La Suite du Menteur</em>, <em>op. cit</em>., p. 301)</p> <p style="margin-left: 40px;">Des comédies du mensonge à l’épreuve de l’héroïsme : <em>Héros ou personnages ?</em></p> <p>Chapitre 4. Érato et Thalie : la comédie des formes</p> <p style="margin-left: 40px;">Dialogue, versification, fragmentation</p> <p style="margin-left: 40px;">L’expression lyrique de la comédie : stances et monologues</p> <p style="margin-left: 40px;">Tirades fabuleuses : narrer, décrire, inventer</p> <p><em>Conclusion</em></p> <p><em>Anthologie critique</em></p> <p><em>Bibliographie</em></p> | V48: https://www.pun-ed.fr/resources/titles/28777100412820/images/f9d396c7f5a391a9251c5fa6d49aa873/HIGHQ/9791024018256.jpg | W48: 9791024018256.jpg | Y48: 15 | Z48: 20.5 | AA48: 1.1 | AB48: 200 | AC48: LIT000000;LIT013000;LIT024000;LIT025000 | AD48: 3435 | AF48: 6 | AG48: 28777100412820 | AH48: 9791024018256 | AI48: TRUE | AJ48: TRUE | AK48: 15 | AL48: Disponible | AM48: Deguin, Yohann, A01 | AN48: Yohann Deguin | AR48: https://books.openedition.org/purh/21296 | AS48: 9791024018256 | AT48: 20 | AU48: 4
A49: 9791024018263 | B49: l-art-d-aimer-comme-des-betes-lecture-du-bestiaire-d-amour-de-richard-de-fourniv-9791024018263 | C49: L'art d'aimer comme des bêtes. Lecture du Bestiaire d'amour de Richard de Fournival et de la Response du Bestiaire | E49: Yoan Boudes | F49: Yoan Boudes | J49: Presses universitaires de Rouen et du Havre | L49: Cours | N49: 2024-11-14 | O49: 1 | P49: Livre broché | Q49: BC | T49: <p>Tour à tour coq, singe, licorne, l'amant-poète du <em>Bestiaire d’amour</em> joue à fusionner écriture didactique et histoire d’un échec amoureux pour mieux souligner les limites d’un savoir érotique qui ne se livre que fragmenté. Entre traité et récit, Richard de Fournival décrit aussi l’abandon de la poésie pour la prose et l’image dans le but avoué de fixer en mémoire un amour qui, pour malheureux qu’il soit, n’en charme pas moins l’œil et l’oreille.</p> | U49: <p>[à venir]</p> | W49: 9791024018263.jpg | Y49: 15 | Z49: 20.5 | AA49: 2 | AB49: 350 | AC49: LIT000000;LIT011000;LIT014000 | AD49: 3435 | AF49: 6 | AG49: 28777100484130 | AH49: 9791024018263 | AI49: FALSE | AJ49: FALSE | AK49: 15 | AL49: Indisponible | AM49: Boudes, Yoan, A01 | AN49: Yoan Boudes | AS49: 9791024018263 | AT49: 40 | AU49: 1 | AV49: DS;DSC | BB49: 0 | BN49: BC
A50: 9791024018300 | B50: journees-archeologiques-de-normandie-2019-9791024018300 | C50: Journées archéologiques de Normandie, 2019 | D50: Caen, 26-27 avril 2019 | E50: Auteurs divers | F50: Auteurs divers | J50: Presses universitaires de Rouen et du Havre | L50: Journées archéologiques de Normandie | N50: 2024-11-14 | O50: 1 | P50: Livre broché | Q50: BC | S50: Chaque année, les journées archéologiques de Normandie permettent la rencontre des acteurs de la recherche régionale, professionnels ou bénévoles, et la restitution au public des résultats de fouilles ou d'études récentes. En 2019, elles se sont tenues à Caen les 26 et 27 avril. Onze articles témoignent de la vitalité de la recherche régionale. | T50: <p><table border="0" cellpadding="0"> <tbody> <tr> <td> </td> <td> <p>Chaque année, les journées archéologiques de Normandie permettent la rencontre des acteurs de la recherche régionale, professionnels ou bénévoles, et la restitution au public des résultats de fouilles ou d'études récentes. En 2019, elles se sont tenues à Caen les 26 et 27 avril. Onze articles témoignent de la vitalité de la recherche régionale.</p> </td> </tr> </tbody> </table></P> | U50: <p>Préface</p> <p>Hubert Lepaumier, Élise Séhier, Emmanuel Ghesquière, Nicolas Le Maux, Karine Chanson, Yves-Marie Adrian et Stéphanie Dervin<br /> Moult-Chicheboville (Calvados), « Le Relais de Poste », résultats des fouilles de 2017</p> <p>Fabien Briand, Jimmy Ménager, Geoffrey Leblé et Magali Gary<br /> Hénouville (Seine-Maritime), route de Saint-Martin : des enclos protohistoriques au clos-masure contemporain</p> <p>Corinne Thevenet<br /> Un ensemble funéraire de l'âge du bronze ancien à Sannerville (Calvados), rue de Lirose</p> <p>Hubert Lepaumier, Raphaëlle Lefebvre et Olivier Cotté<br /> Creully (Calvados), le « Clos de l’Épinette » : une occupation dense au second âge du fer</p> <p>Grégory Schütz<br /> Bayeux <em>Augustodurum </em>(Calvados). État des connaissances sur le chef-lieu de la cité gallo-romaine des Baïocasses</p> <p>Éric Follain<br /> Urbanisme chez les Calètes : le forum de <em>Juliobona </em>(Lillebonne, Seine-Maritime)</p> <p>Jonas Parétias et Victor Viquesnel-Schlosser<br /> Contributions à l’étude de la ville de <em>Briga </em>– Eu, « Bois l’Abbé » (Seine-Maritime) : points sur l’approche architecturale des monuments publics et sur l’étude de la céramique antique</p> <p>Frédérique Jimenez, Nicolas Roudié, Yves-Marie Adrian, Pauline Petit, Caroline Riche, Nolwenn Zaour et Hélène Seignac<br /> Grèges, « La Maison Blanche » (Seine-Maritime) : habitat rural et artisanat du fer au haut Moyen Âge (fin du V<sup>e</sup> siècle-VII<sup>e</sup> siècle)</p> <p>Nicolas Wasylyszyn<br /> L’église Saint-Christophe de Reuilly (Eure) : de l’étude du bâti à la datation radiocarbone</p> <p>Alban Gottfrois<br /> Exmes (Orne) : histoire d’un pôle de pouvoir, des origines au XII<sup>e</sup> siècle</p> <p>Lise Levieux<br /> Appréhender les transformations de Rouen au Moyen Âge à l’aide des systèmes d’information géographique</p> <p>Aude Painchault<br /> L’utilisation de la craie dans les constructions en Normandie orientale entre le X<sup>e</sup> et le XIV<sup>e</sup> siècle : méthodologie et résultats</p> <p>Hélène Dupont<br /> Au pied du château de Caen (Calvados) entre le XII<sup>e</sup> siècle et le milieu du XX<sup>e</sup> siècle</p> | V50: https://www.pun-ed.fr/resources/titles/28777100934820/images/da16202114b72b61f71124a219db6e3e/HIGHQ/9791024018300.jpg | W50: 9791024018300.jpg | X50: 192 | Y50: 21 | Z50: 27 | AA50: 1.15 | AB50: 760 | AC50: SCI000000 | AD50: 4117 | AF50: 6 | AG50: 28777100934820 | AH50: 9791024018300 | AI50: TRUE | AJ50: TRUE | AK50: 25 | AL50: Disponible | AM50: Auteurs divers, A01 | AN50: Auteurs divers | AS50: 9791024018300 | AT50: 20 | AU50: 4 | AV50: HD | BB50: 0 | BN50: BC
A51: 9791024018157 | B51: la-guerre-de-siege-a-l-epreuve-de-la-revolution-francaise-9791024018157 | C51: La guerre de siège à l'épreuve de la Révolution française | D51: Retentissements et perceptions | E51: Barbaray, Côme, B15 | F51: Côme Barbaray | J51: Presses universitaires de Rouen et du Havre | L51: Changer d'époque | M51: 38 | N51: 2024-07-18 | O51: 1 | P51: Livre broché | Q51: BC | S51: La guerre de siège, composante décisive des conflits de la période révolutionnaire, invite à penser le positionnement des civils et des militaires en interrogeant leur perception des pratiques obsidionales. Les moyens d'élaboration et de diffusion de l’information sur les sièges affectent autant les débats politiques que la conduite de la guerre. | T51: <p>Confronter guerre et société révèle l'interpénétration de deux notions indissociables. D’un côté, la guerre modèle la société en lui imposant ses rigueurs et ses besoins, de l’autre, la société imprègne les affrontements, pour beaucoup à travers les individus qu’elle y envoie. Parmi les recherches menées au croisement des sphères militaire, politique, sociale et culturelle, se distinguent les travaux menés sur la guerre de siège.</p> <p>L’étude de cette pratique très ancienne, qui tend progressivement à se normaliser à l’époque moderne, s’avère extrêmement pertinente durant la Révolution française. En effet, entre rhétorique politique et réalité du terrain, la guerre de siège révolutionnaire est l’objet de multiples interprétations dans une période de grands bouleversements. Dans un contexte de guerre généralisée, les sièges constituent des enjeux pour le pouvoir, ainsi que des catalyseurs locaux en regroupant antagonismes et tentatives de négociations.</p> <p>L’objectif de ce volume est bien d’appréhender la perception que les contemporains, combattants ou non, peuvent avoir des usages obsidionaux, à travers des médias élaborant et diffusant des nouvelles sur la guerre de siège.</p> | U51: <p>Introduction</p> <p><br /> Sébastien Le Gal, <em>La réforme du droit des places de guerre par l'Assemblée nationale</em></p> <p>Valentin Barrier, <em>À l'ombre des places fortes : camps retranchés, lignes fortifiées et redoutes. Le rôle de la fortification passagère dans les premières campagnes des guerres de la Révolution</em></p> <p>Gilles Candela, <em>Les sièges de Mantoue dans la stratégie française en Italie (1792-1799)</em></p> <p>Christophe Pommier, <em>L’artillerie de Gribeauval dans la guerre de siège : les leçons de Maastricht</em></p> <p>Olivier Aranda, <em>Un siège amphibie ? Retour sur le « blocus » de Brest (1793-1801)</em></p> <p>Vincent Cuvilliers, <em>Usages militaires et politiques de la guerre de siège : l’exemple du général Custine à travers les sièges de Spire, Worms, Francfort et Mayence (septembre 1792-août 1793)</em></p> <p>Côme Barbaray, <em>Donner à voir le siège révolutionnaire : entre relais de l’information auprès du peuple et déformation de l’expérience militaire</em></p> <p>Stanislas de Chabalier, <em>Dans les décombres d’une ville bombardée : l’indemnisation des victimes lilloises après le siège de 1792</em></p> <p>Conclusion<br /> &nbsp;</p> <p>Bibliographie</p> <p>Index</p> <p>Lexique</p> <p>Les auteurs</p> | V51: https://www.pun-ed.fr/resources/titles/28777100414550/images/dbafb94acd0f5bb51afb63a64a03bf2f/HIGHQ/9791024018157.jpg | W51: 9791024018157.jpg | X51: 170 | Y51: 15.5 | Z51: 23 | AA51: 0.85 | AB51: 80 | AC51: HIS000000;HIS010000;HIS027000;HIS031000 | AD51: 3377 | AE51: NHW | AF51: 1 | AG51: 28777100414550 | AI51: TRUE | AJ51: TRUE | AK51: 17 | AL51: Disponible | AM51: Barbaray, Côme, B15 | AS51: 9791024018157 | AT51: 20 | AU51: 4 | AV51: H;HB;HBW | BB51: 0 | BD51: NHW | BE51: NHW | BF51: NHW | BN51: BC
A52: 9791024017730 | B52: wagner-vu-de-rouen-9791024017730 | C52: Wagner vu de Rouen | E52: Yannick Simon | F52: Yannick Simon | J52: Presses universitaires de Rouen et du Havre | L52: Changer d'époque | M52: 37 | N52: 2024-06-20 | O52: 1 | P52: Livre relié | Q52: BB | S52: Ce livre raconte le parcours de Richard Wagner au Théâtre des Arts de Rouen entre 1891 et 2020. À travers cet exemple, il retrace l'histoire du wagnérisme français, mais aussi celle des modes de production de l'opéra de la fin du XIXe siècle à aujourd’hui tout en proposant une approche décentrée de l’histoire de la vie musicale en France. | T52: <p>Ce livre raconte le parcours de Richard Wagner au Théâtre des Arts de Rouen entre 1891 et 2020. L'intérêt se porte tout autant sur la manière dont les œuvres sont interprétées que sur la façon dont elles sont perçues à l'échelle locale mais aussi nationale. L’ouvrage montre en effet qu’à plusieurs reprises, l’institution rouennaise joue un rôle déterminant dans le processus d’acceptation de Wagner en France. Plus largement, il retrace l’histoire du wagnérisme français, mais aussi celle des modes de production de l’opéra de la fin du XIX<sup>e</sup> siècle à aujourd’hui à travers l’exemple singulier de Rouen. Ce faisant, il participe d’une approche décentrée de l’histoire de la vie musicale en France.</p> | U52: <p>Préface</p> <p>Introduction</p> <p>L'entrée chaotique de Richard Wagner au répertoire français</p> <p>130&nbsp;ans de wagnérisme à Rouen</p> <p><em>Lohengrin</em>, 1891</p> <p>&nbsp;&nbsp;&nbsp;&nbsp;&nbsp;&nbsp;&nbsp; <em>Loiehencrin</em></p> <p>&nbsp;&nbsp;&nbsp;&nbsp;&nbsp;&nbsp;&nbsp; 1891-1900, de <em>Lohengrin</em> à <em>Siegfried</em></p> <p><em>Siegfried</em>, 1900</p> <p>Les livres de souvenirs de Paul Stuart et de Raoul François</p> <p>1900-1914, de <em>Siegfried</em> à <em>Tristan</em></p> <p><em>Tristan et Isolde</em>, 1914</p> <p>1914-1927, de <em>Tristan </em>à la Tétralogie</p> <p>La première Tétralogie, 1927</p> <p>Wagner au Cirque</p> <p>1927-1969, de la Tétralogie au <em>Ring</em></p> <p>La deuxième Tétralogie, 1969</p> <p>1969-1995, de la Tétralogie à <em>Parsifal</em></p> <p><em>Parsifal</em>, 1995</p> <p>Le retour de <em>Lohengrin</em>, 2015</p> <p>Conclusion</p> <p>Sources et bibliographie</p> <p>Table des figures et crédits photographiques</p> <p>Index</p> | V52: https://www.pun-ed.fr/resources/titles/28777100283080/images/41869b81c91e34f789fb0175802326d3/HIGHQ/9791024017730.jpg | W52: 9791024017730.jpg | X52: 148 | Y52: 15.5 | Z52: 23 | AA52: 0.75 | AB52: 200 | AC52: MUS000000;ART015000;HIS010000;MUS020000;MUS050000 | AE52: AVN | AF52: 5 | AG52: 28777100283080 | AH52: 9791024017730 | AI52: TRUE | AJ52: TRUE | AK52: 15 | AL52: Disponible | AM52: Simon, Yannick, A01 | AN52: Yannick Simon | AS52: 9791024017730 | AT52: 20 | AU52: 4 | AV52: A;AV;HB | AW52: 1D | BB52: 0 | BD52: AVN | BE52: AVN | BF52: AVN | BN52: BB
A53: 9791024017853 | B53: la-shoah-en-mots-et-en-images-9791024017853 | C53: La Shoah en mots et en images | D53: De Perec à la littérature de jeunesse | E53: Éléonore Hamaide | F53: Éléonore Hamaide | J53: Presses universitaires de Rouen et du Havre | L53: Littérature de jeunesse et histoire | N53: 2024-06-20 | O53: 1 | P53: Livre broché | Q53: BC | S53: À partir d'un corpus de plus de 200 œuvres, cet ouvrage retrace l’histoire de la Shoah dans le livre pour enfants en la croisant avec l’écriture du génocide pour adultes, en particulier celle de Perec. De 1944 à 2021, ces livres montrent l’oscillation entre écriture littéraire et surenchère éditoriale, voire commerciale. | T53: <p>À partir d'un corpus de plus de 200 œuvres, cet ouvrage parcourt environ 70 ans d’écriture de la Shoah à destination des enfants. Reprenant d’abord des motifs propres à la littérature génocidaire pour adultes, en particulier ceux de Perec, les auteurs de littérature de jeunesse s’émancipent en centrant leur propos sur une démarche identitaire conforme à leur public et en interrogeant la représentation possible du génocide par les images. La dimension littéraire irrigue encore cette production, pourtant parfois soumise à des formes de surenchère éditoriale, mais invitée à se renouveler dans ses genres, ses personnages et ses enjeux institutionnels, culturels et médiatiques.</p> <p></p> | U53: <p><em>Introduction</em></p> <p><strong>Partie I – Le récit de la Shoah, entre tradition et innovation</strong><br /> Même pas juif. Des personnages en quête d'identité<br /> Où est qui ? Du témoignage à la reconstruction fictionnelle<br /> C'est toujours pareil. Les <em>topoï </em>de la représentation de la Shoah</p> <p><strong>Partie II – Une identité à reconquérir</strong><br /> D'en famille à sans famille, réinventer sa lignée<br /> Ce changement-là : redevenir juif après</p> <p><strong>Partie III – Une démarche esthétique</strong><br /> Caché ! Écrire la Shoah : le refus de l'exhibition<br /> Dedans, dehors. Le mélange des genres</p> <p><strong>Partie IV – Survivre à l'écriture de la Shoah : quel présent et quel avenir pour la littérature du génocide ?</strong><br /> Le bon côté du mur. De la littérature à la prescription<br /> Héros. Le besoin de « nouvelles » grandes figures : la sortie du purgatoire<br /> Bazar bizarre. Diversification ou risque du « tout se vaut » ?</p> <p><em>Conclusion</em><br /> &nbsp;</p> | V53: https://www.pun-ed.fr/resources/titles/28777100142380/images/5b5abc705cc52b743cc9d6ad5fffdfa4/HIGHQ/9791024017853.jpg | W53: 9791024017853.jpg | X53: 474 | Y53: 15.5 | Z53: 24 | AA53: 3 | AB53: 850 | AC53: LIT009000;HIS043000;HIS022000;HIS037070;HIS037080 | AD53: 3728 | AF53: 6 | AG53: 28777100142380 | AH53: 9791024017853 | AI53: TRUE | AJ53: TRUE | AK53: 24 | AL53: Disponible | AM53: Hamaide, Éléonore, A01 | AN53: Éléonore Hamaide | AS53: 9791024017853 | AT53: 20 | AU53: 4 | AV53: DS;HBTZ1;DSYC | BN53: BC
A54: 9791024017983 | B54: austriaca-n-94-9791024017983 | C54: Austriaca, n° 94 | D54: Les cercles viennois de l'entre-deux-guerres | E54: Herrera, Carlos, B15; Lecoutre, François, B15 | F54: Carlos Herrera | J54: Presses universitaires de Rouen et du Havre | L54: Austriaca | M54: 94 | N54: 2024-06-20 | O54: 1 | P54: Livre broché | Q54: BC | S54: Espace de sociabilité, mais aussi lieu de construction intellectuelle, le « cercle » se distingue-t-il clairement d'une « école » ? Et y aurait-il de quoi les singulariser en tant que « cercles » par-delà les circonstances historiques ? L'analyse porte ici sur le cadre autrichien de la première moitié du xxe siècle, et sur l’entre-deux-guerres. | T54: <p>L'interrogation à propos des cercles viennois en tant qu’objet de réflexion est apparue depuis un certain moment dans les études d’histoire intellectuelle. Espace de sociabilité, mais aussi lieu de construction intellectuelle, le «&nbsp;cercle&nbsp;» se distingue-t-il clairement d’une «&nbsp;école&nbsp;»&nbsp;? Et y aurait-il dans ces différents groupements des traits qui permettraient de les singulariser en tant que «&nbsp;cercles&nbsp;» par-delà les circonstances historiques&nbsp;? Les deux problématisations sont étroitement liées et sont analysées ici dans le cadre autrichien de la première moitié du xx<sup>e</sup> siècle, avec un accent particulier mis sur la période de l’entre-deux guerres. Car quelle particularité «&nbsp;autrichienne&nbsp;» renferment ces cercles&nbsp;? Le cercle, cette forme d’organiser les échanges, ou plus précisément son mode de production des concepts, donne-t-il naissance à un nouveau style de construction de la pensée autrichienne (dans le domaine de la philosophie, mais également de l’esthétique, de la science sociale, de la clinique, etc.).</p> <p>Ce sont des notions liées tantôt à la politique tantôt aux sphères sociales et intellectuelles qui sont confrontées dans ce numéro 94, de même qu’il y est question des Wiener Kreis et Geistkreis, entre autres, et de figures comme Stefan George, Sigmund Freud, Hans Kelsen ou encore Othmar Spann.</p> | U54: <p><em>Avant-propos - Penser en cercles. </em><em>Vienne 1918-1938</em></p> <p>&nbsp;</p> <p>Alice Pechriggl</p> <p><em>Le </em><em>«</em><em>&nbsp;Freud-Kreis&nbsp;</em><em>»</em><em>. Structures changeantes d'un cercle, d'un mouvement et d'une institution</em></p> <p>&nbsp;</p> <p>Emmanuel Faye</p> <p><em>Mythologie politique et </em><em>«</em><em>&nbsp;George-Kreis&nbsp;</em><em>» à Vienne. Sur la genèse de la pensée politique d'Eric Voegelin</em></p> <p>&nbsp;</p> <p>Jean-Numa Ducange</p> <p><em>Les cercles austro-marxistes à Vienne pendant la Première République autrichienne</em></p> <p>&nbsp;</p> <p>Nicoletta Bersier Ladavac</p> <p><em>Le cercle autour de Hans Kelsen</em></p> <p>&nbsp;</p> <p>Renaud Fillieule</p> <p><em>Le </em><em>«</em><em>&nbsp;Mises-Kreis&nbsp;</em><em>»&nbsp;: science sociale et libéralisme</em></p> <p>&nbsp;</p> <p>Christian E. Roques</p> <p><em>Le </em><em>«</em><em>&nbsp;Spann-Kreis&nbsp;</em><em>» et le néoromantisme nationaliste</em></p> <p>&nbsp;</p> <p>François Lecoutre</p> <p><em>Anatomie du Geistkreis</em></p> <p>&nbsp;</p> <p>Christian Bonnet</p> <p><em>Le Wiener Kreis et le positivisme logique</em></p> <p>&nbsp;</p> <p>Antonia Soulez</p> <p><em>Otto Neurath&nbsp;: la force d’une pensée constructiviste du possible contre le déclinisme</em></p> <p>&nbsp;</p> <p>François Lecoutre</p> <p><em>Hans Kelsen et le positivisme logique du Cercle de Vienne</em></p> <p>&nbsp;</p> <p><strong><em>Varia</em></strong></p> <p>Delphine Edy</p> <p><em>Thomas Ostermeier : Horváth « von heute für heute </em><em>»</em></p> <p>&nbsp;</p> <p>Stefano Apostolo</p> <p><em>„alles / auf Gedanken aufgebaut". Thomas Bernhard und die Geburt einer neuen Prosa</em></p> <p>&nbsp;</p> <p><em>Notices bibliographiques</em></p> <p><em>Publications récentes sur l’Autriche</em></p> <p><em>Résumés/</em>Zusammenfassungen<em>/</em>Abstracts</p> | V54: https://www.pun-ed.fr/resources/titles/28777100666560/images/1f8c4b6a0115a4617e285b4494126fbf/HIGHQ/9791024017983.jpg | W54: 9791024017983.jpg | X54: 316 | Y54: 15.5 | Z54: 24 | AA54: 1.65 | AB54: 450 | AC54: HIS040000;POL010000 | AD54: 3089 | AF54: 6 | AG54: 28777100666560 | AH54: 9791024017983 | AI54: TRUE | AJ54: TRUE | AK54: 25 | AL54: Disponible | AM54: Herrera, Carlos, B15; Lecoutre, François, B15 | AS54: 9791024017983 | AT54: 20 | AU54: 4 | AV54: HBTB;JPF | BB54: 0 | BN54: BC
A55: 9791024018058 | B55: anthropocene-et-education-9791024018058 | C55: Anthropocène et éducation | D55: Repères pour un monde incertain | E55: Fabre, Michel, B15; Chauvigné, Céline, B15 | F55: Michel Fabre | J55: Presses universitaires de Rouen et du Havre | L55: Penser les valeurs en éducation et en formation | N55: 2024-06-20 | O55: 1 | P55: Livre broché | Q55: BC | S55: Que signifie éduquer quand le changement climatique menace la planète ? L'originalité de ce travail est de chercher des réponses chez des intellectuels contemporains qui sont autant de lanceurs d’alerte : ils osent dire, à grand cri, ce que peu de personnes veulent entendre. L’ouvrage se termine sur un entretien avec Edgar Morin. | T55: <p>Les questions que Hans Jonas formulait à la fin du XX<sup>e</sup> siècle sont devenues d'une actualité brûlante&nbsp;: Quelle Terre allons-nous laisser à nos enfants&nbsp;? Qu’adviendra-t-il de l’humanité comme telle&nbsp;? L’éducation a-t-elle encore un sens dans un tel contexte&nbsp;? L’originalité de ce travail, issu de l’équipe «&nbsp;Questions socialement vives&nbsp;» du Centre de recherche en éducation de Nantes (CREN), est de chercher des réponses chez des intellectuels contemporains connus (Giorgio Agamben, Ulrich Beck, Umberto Eco, René Girard, André Gorz, Hans Jonas, Bruno Latour, Hartmut Rosa, Umberto Eco), ou moins connus (Alexandre Grothendieck, Katsuhiro Otomo, Kyle Harper, Xi Jinping, Frédérique Aït-Touati…). Beaucoup de ces auteurs sont des lanceurs d’alerte qui osent dire, ce que personne ne veut entendre. L’ouvrage se termine sur un entretien avec Edgar Morin.</p> | U55: <p><em>Remerciements</em></p> <p><em>Introduction</em></p> <p>Chapitre liminaire : Rien de nouveau sous le soleil&nbsp;? - François Prouteau et Nathanaël Wallenhorst</p> <p style="text-align: center;">Signification, légitimité de la pensée catastrophique</p> <p><em>Grothendieck. La brutalité cataclysmique</em>, Pierre Billouet</p> <p><em>De la société du risque à la société résiliente : l'apport d'Ulrich Beck aux débats contemporains sur le changement climatique</em>, Marco Barroca-Paccard</p> <p><em>En finir avec l'idée de nature&nbsp;? Bruno Latour, de Pasteur à Gaïa</em>, Jean-Marc Lamarre</p> <p style="text-align: center;">Éducation et responsabilité</p> <p><em>Face à la catastrophe écologique. L'utopie concrète d'André Gorz</em>, Céline Chauvigné</p> <p><em>L'éducation à la responsabilité : Hans Jonas&nbsp;et Jean-Pierre Dupuy</em>, Michel Fabre</p> <p><em>Éducation et contemporanéité. Une approche à partir de l'œuvre de Giorgio Agamben</em>, Alfred Romuald Gambou</p> <p><em>Former des forces de résistance aux effondrements</em>, Renaud Hétier</p> <p style="text-align: center;">La catastrophe : un imaginaire occidental ?</p> <p><em>La chute de Rome et les invasions barbares&nbsp;: l'effondrement ou le destin de l'Occident</em>, Frédéric Le Blay</p> <p><em>Le rêve chinois, l'État rééducateur et le catastrophisme cosmologique</em>, Roland Depierre</p> <p><em>Penser la catastrophe avec Katsuhiro Otomo&nbsp;: jeunesses incertaines</em>, Camille Roelens</p> <p><em>Un catastrophisme sans moralisme&nbsp;dans un album de jeunesse&nbsp;: </em>Les Gnomes de Gnou <em>d’Eugenio Carmi et Umberto Eco</em>, Catherine Huchet</p> <p><em>« Anthropo-scènes »&nbsp;: spectacle vivant et spectacle du vivant,</em> Sylvie Fontaine</p> <p><em>Entretien avec Edgar Morin</em></p> <p><em>Postface</em></p> <p><em>Bibliographie</em></p> <p><em>Les auteurs</em></p> | V55: https://www.pun-ed.fr/resources/titles/28777100536720/images/514a70448c235ccb8b6842ef5e02ad3b/HIGHQ/9791024018058.jpg | W55: 9791024018058.jpg | X55: 302 | Y55: 22 | Z55: 15.5 | AA55: 2.3 | AB55: 400 | AC55: EDU000000;EDU040000;PHI000000;SOC000000;SOC026000 | AD55: 3161 | AF55: 6 | AG55: 28777100536720 | AH55: 9791024018058 | AI55: TRUE | AJ55: TRUE | AK55: 21 | AL55: Disponible | AM55: Chauvigné, Céline, B15; Fabre, Michel, B15 | AS55: 9791024018058 | AT55: 20 | AU55: 4 | AV55: JN;HP;J;JH;RN | BB55: 0 | BC55: 1 | BN55: BC
